Workbook

Sheet Dashboard
B1: DASHBOARD DE COBRANZAS — CENTIC SAS
B2: Control de cartera por cobrar · Cursos y certificaciones
B3: Los indicadores se recalculan automáticamente a partir de la hoja "Ventas". Última actualización: fórmulas en vivo.
B5: CARTERA TOTAL PENDIENTE | E5: N° DE REGISTROS CON SALDO | H5: SALDO PROMEDIO POR REGISTRO | K5: % CARTERA "AL DÍA" | M5: % CARTERA EN GESTIÓN / RIESGO
B7: =TEXT(SUM(Ventas!M3:M306),"$ #,##0") -> $ 55,986,967 | E7: =COUNT(Ventas!M3:M306) -> 64 | H7: =TEXT(AVERAGE(Ventas!M3:M306),"$ #,##0") -> $ 874,796 | K7: =TEXT(COUNTIF(Ventas!O3:O306,"Al día")/COUNT(Ventas!M3:M306),"0%") -> 11% | M7: =TEXT(1-COUNTIF(Ventas!O3:O306,"Al día")/COUNT(Ventas!M3:M306),"0%") -> 89%
B11: ="Mayor saldo individual: " & INDEX(Ventas!B3:B306,MATCH(1,Ventas!R3:R306,0)) & " — $" & TEXT(INDEX(Ventas!M3:M306,MATCH(1,Ventas!R3:R306,0)),"#,##0") & " · Vendedor: " & INDEX(Ventas!N3:N306,MATCH(1,Ventas!R3:R306,0)) -> Mayor saldo individual: Gabriel Enrique Moreno Pérez — $3,150,000 · Vendedor: Sebas
B13: ① Cartera por estado de gestión | H13: ⑤ Top 10 registros con mayor saldo pendiente
B14: Estado | C14: Cartera ($) | D14: N° registros | H14: Cliente | I14: Saldo ($) | J14: Vendedor
B15: Al día | C15: =SUMIF(Ventas!$O$3:$O$306,B15,Ventas!$M$3:$M$306) -> 6040000 | D15: =COUNTIF(Ventas!$O$3:$O$306,B15) -> 7 | H15: =IFERROR(INDEX(Ventas!$B$3:$B$306,MATCH(1,Ventas!$R$3:$R$306,0)),"") -> Gabriel Enrique Moreno Pérez | I15: =IFERROR(INDEX(Ventas!$M$3:$M$306,MATCH(1,Ventas!$R$3:$R$306,0)),"") -> 3150000 | J15: =IFERROR(INDEX(Ventas!$N$3:$N$306,MATCH(1,Ventas!$R$3:$R$306,0)),"") -> Sebas
B16: Pendiente / Compromiso | C16: =SUMIF(Ventas!$O$3:$O$306,B16,Ventas!$M$3:$M$306) -> 9069967 | D16: =COUNTIF(Ventas!$O$3:$O$306,B16) -> 11 | H16: =IFERROR(INDEX(Ventas!$B$3:$B$306,MATCH(2,Ventas!$R$3:$R$306,0)),"") -> Jhon Isaias Muñoz Remolina | I16: =IFERROR(INDEX(Ventas!$M$3:$M$306,MATCH(2,Ventas!$R$3:$R$306,0)),"") -> 2390000 | J16: =IFERROR(INDEX(Ventas!$N$3:$N$306,MATCH(2,Ventas!$R$3:$R$306,0)),"") -> Ximena
B17: Sin respuesta / Inactivo | C17: =SUMIF(Ventas!$O$3:$O$306,B17,Ventas!$M$3:$M$306) -> 5100000 | D17: =COUNTIF(Ventas!$O$3:$O$306,B17) -> 2 | H17: =IFERROR(INDEX(Ventas!$B$3:$B$306,MATCH(3,Ventas!$R$3:$R$306,0)),"") -> Jhon Edison Puerto Jiménez | I17: =IFERROR(INDEX(Ventas!$M$3:$M$306,MATCH(3,Ventas!$R$3:$R$306,0)),"") -> 2050000 | J17: =IFERROR(INDEX(Ventas!$N$3:$N$306,MATCH(3,Ventas!$R$3:$R$306,0)),"") -> Carolina
B18: Sin gestionar | C18: =SUMIF(Ventas!$O$3:$O$306,B18,Ventas!$M$3:$M$306) -> 35777000 | D18: =COUNTIF(Ventas!$O$3:$O$306,B18) -> 44 | H18: =IFERROR(INDEX(Ventas!$B$3:$B$306,MATCH(4,Ventas!$R$3:$R$306,0)),"") -> Cesar Augusto Ramirez | I18: =IFERROR(INDEX(Ventas!$M$3:$M$306,MATCH(4,Ventas!$R$3:$R$306,0)),"") -> 1950000 | J18: =IFERROR(INDEX(Ventas!$N$3:$N$306,MATCH(4,Ventas!$R$3:$R$306,0)),"") -> Ximena
H19: =IFERROR(INDEX(Ventas!$B$3:$B$306,MATCH(5,Ventas!$R$3:$R$306,0)),"") -> JOHAN YESID MORENO SARMIENTO | I19: =IFERROR(INDEX(Ventas!$M$3:$M$306,MATCH(5,Ventas!$R$3:$R$306,0)),"") -> 1850000 | J19: =IFERROR(INDEX(Ventas!$N$3:$N$306,MATCH(5,Ventas!$R$3:$R$306,0)),"") -> Carolina
H20: =IFERROR(INDEX(Ventas!$B$3:$B$306,MATCH(6,Ventas!$R$3:$R$306,0)),"") -> Andrea Olarte Trujillo | I20: =IFERROR(INDEX(Ventas!$M$3:$M$306,MATCH(6,Ventas!$R$3:$R$306,0)),"") -> 1750000 | J20: =IFERROR(INDEX(Ventas!$N$3:$N$306,MATCH(6,Ventas!$R$3:$R$306,0)),"") -> Sebas
B21: ② Cartera por vendedor | H21: =IFERROR(INDEX(Ventas!$B$3:$B$306,MATCH(7,Ventas!$R$3:$R$306,0)),"") -> Natalia Fernanda Huertas Rodriguez | I21: =IFERROR(INDEX(Ventas!$M$3:$M$306,MATCH(7,Ventas!$R$3:$R$306,0)),"") -> 1600000 | J21: =IFERROR(INDEX(Ventas!$N$3:$N$306,MATCH(7,Ventas!$R$3:$R$306,0)),"") -> Ximena
B22: Vendedor | C22: Cartera ($) | D22: N° registros | H22: =IFERROR(INDEX(Ventas!$B$3:$B$306,MATCH(8,Ventas!$R$3:$R$306,0)),"") -> Niver Alberto López Gómez | I22: =IFERROR(INDEX(Ventas!$M$3:$M$306,MATCH(8,Ventas!$R$3:$R$306,0)),"") -> 1600000 | J22: =IFERROR(INDEX(Ventas!$N$3:$N$306,MATCH(8,Ventas!$R$3:$R$306,0)),"") -> Carolina
B23: Ximena | C23: =SUMIF(Ventas!$N$3:$N$306,B23,Ventas!$M$3:$M$306) -> 22661967 | D23: =COUNTIF(Ventas!$N$3:$N$306,B23) -> 32 | H23: =IFERROR(INDEX(Ventas!$B$3:$B$306,MATCH(9,Ventas!$R$3:$R$306,0)),"") -> Juan Diego Salcedo García | I23: =IFERROR(INDEX(Ventas!$M$3:$M$306,MATCH(9,Ventas!$R$3:$R$306,0)),"") -> 1500000 | J23: =IFERROR(INDEX(Ventas!$N$3:$N$306,MATCH(9,Ventas!$R$3:$R$306,0)),"") -> Carolina
B24: Carolina | C24: =SUMIF(Ventas!$N$3:$N$306,B24,Ventas!$M$3:$M$306) -> 17915000 | D24: =COUNTIF(Ventas!$N$3:$N$306,B24) -> 19 | H24: =IFERROR(INDEX(Ventas!$B$3:$B$306,MATCH(10,Ventas!$R$3:$R$306,0)),"") -> Mauricio Villate Granados | I24: =IFERROR(INDEX(Ventas!$M$3:$M$306,MATCH(10,Ventas!$R$3:$R$306,0)),"") -> 1470000 | J24: =IFERROR(INDEX(Ventas!$N$3:$N$306,MATCH(10,Ventas!$R$3:$R$306,0)),"") -> Carolina
B25: Sebas | C25: =SUMIF(Ventas!$N$3:$N$306,B25,Ventas!$M$3:$M$306) -> 14410000 | D25: =COUNTIF(Ventas!$N$3:$N$306,B25) -> 12
B28: ③ Cartera por categoría de servicio
B29: Categoría | C29: Cartera ($) | D29: N° registros
B30: ITIL | C30: =SUMIF(Ventas!$P$3:$P$306,B30,Ventas!$M$3:$M$306) -> 16932000 | D30: =COUNTIF(Ventas!$P$3:$P$306,B30) -> 19
B31: ISO 27001 | C31: =SUMIF(Ventas!$P$3:$P$306,B31,Ventas!$M$3:$M$306) -> 4374967 | D31: =COUNTIF(Ventas!$P$3:$P$306,B31) -> 6
B32: ISO 42001 | C32: =SUMIF(Ventas!$P$3:$P$306,B32,Ventas!$M$3:$M$306) -> 800000 | D32: =COUNTIF(Ventas!$P$3:$P$306,B32) -> 2
B33: Otras ISO | C33: =SUMIF(Ventas!$P$3:$P$306,B33,Ventas!$M$3:$M$306) -> 2200000 | D33: =COUNTIF(Ventas!$P$3:$P$306,B33) -> 2
B34: SCRUM | C34: =SUMIF(Ventas!$P$3:$P$306,B34,Ventas!$M$3:$M$306) -> 1735000 | D34: =COUNTIF(Ventas!$P$3:$P$306,B34) -> 3
B35: BRIDGE | C35: =SUMIF(Ventas!$P$3:$P$306,B35,Ventas!$M$3:$M$306) -> 2860000 | D35: =COUNTIF(Ventas!$P$3:$P$306,B35) -> 6
B36: CDS | C36: =SUMIF(Ventas!$P$3:$P$306,B36,Ventas!$M$3:$M$306) -> 3590000 | D36: =COUNTIF(Ventas!$P$3:$P$306,B36) -> 3
B37: TOGAF | C37: =SUMIF(Ventas!$P$3:$P$306,B37,Ventas!$M$3:$M$306) -> 1000000 | D37: =COUNTIF(Ventas!$P$3:$P$306,B37) -> 1
B38: DPI | C38: =SUMIF(Ventas!$P$3:$P$306,B38,Ventas!$M$3:$M$306) -> 1950000 | D38: =COUNTIF(Ventas!$P$3:$P$306,B38) -> 2
B39: DITS | C39: =SUMIF(Ventas!$P$3:$P$306,B39,Ventas!$M$3:$M$306) -> 3150000 | D39: =COUNTIF(Ventas!$P$3:$P$306,B39) -> 1
B40: AGILE | C40: =SUMIF(Ventas!$P$3:$P$306,B40,Ventas!$M$3:$M$306) -> 390000 | D40: =COUNTIF(Ventas!$P$3:$P$306,B40) -> 1
B41: Ciberseguridad | C41: =SUMIF(Ventas!$P$3:$P$306,B41,Ventas!$M$3:$M$306) -> 1350000 | D41: =COUNTIF(Ventas!$P$3:$P$306,B41) -> 2
B42: Sin definir | C42: =SUMIF(Ventas!$P$3:$P$306,B42,Ventas!$M$3:$M$306) -> 15655000 | D42: =COUNTIF(Ventas!$P$3:$P$306,B42) -> 16
B44: ④ Antigüedad de mora (meses)
B45: Rango | C45: Cartera ($) | D45: N° registros
B46: 1-3 meses | C46: =SUMIF(Ventas!$Q$3:$Q$306,B46,Ventas!$M$3:$M$306) -> 0 | D46: =COUNTIF(Ventas!$Q$3:$Q$306,B46) -> 0
B47: 4-6 meses | C47: =SUMIF(Ventas!$Q$3:$Q$306,B47,Ventas!$M$3:$M$306) -> 3507000 | D47: =COUNTIF(Ventas!$Q$3:$Q$306,B47) -> 4
B48: +6 meses | C48: =SUMIF(Ventas!$Q$3:$Q$306,B48,Ventas!$M$3:$M$306) -> 290000 | D48: =COUNTIF(Ventas!$Q$3:$Q$306,B48) -> 1
B49: Sin dato registrado | C49: =SUMIF(Ventas!$Q$3:$Q$306,B49,Ventas!$M$3:$M$306) -> 52189967 | D49: =COUNTIF(Ventas!$Q$3:$Q$306,B49) -> 59
B113: Notas metodológicas
B114: • "Cartera total pendiente" suma la columna Total a pagar de la hoja Ventas (columna auxiliar M, que también convierte a número los valores escritos como texto, ej. "$1.000.000").
B115: • El estado de cartera se clasifica automáticamente cruzando las columnas "Estado de cobro" y "Estado de cobro2" por palabras clave (AL DIA, PENDIENTE, COMPROMISO, QUIETO, ESPERANDO, etc.). Los registros sin ninguna de estas palabras quedan en "Sin gestionar": es la categoría más grande (44 de 65) porque muchos registros aún no tienen un estado de cobro registrado en el archivo original.
B116: • La antigüedad de mora usa la columna "Meses en mora", que solo tiene datos numéricos en 6 de 65 registros; el resto aparece como "Sin dato registrado". Se recomienda diligenciar esta columna de forma más consistente para que este indicador sea representativo.
B117: • El Top 10 se calcula por registro individual (un mismo cliente puede tener más de un registro si tomó varios cursos).
B118: • No fue posible construir una comparación mensual (como en la plantilla de referencia) porque la columna "Fecha del contacto" solo está diligenciada en 7 de 65 registros.
B119: • Para actualizar el dashboard: agrega filas nuevas en la hoja Ventas (las fórmulas auxiliares llegan hasta la fila 300) y todos los indicadores, tablas y gráficos se recalculan solos.

Sheet Ventas
A1: ID_Venta | B1: Nombre completo | C1: Fecha del contacto | D1: Vendedor | E1: Servicio | F1: Estado de cobro | G1: % interes de mora | H1: Valor de interes de mora | I1: Total a pagar | J1: Fecha de compromiso de pago | K1: Meses en mora | L1: Estado de cobro2 | M1: AYUDA PARA DASHBOARD — NO EDITAR (se calcula solo)
A2: 1 | B2: Froilán González Roa | C2: 46127 | D2: Carolina | E2: ITIL 4 Fundamentos | F2: Curso y examen | G2: no | H2: no | I2: 890000 | J2: ABONO 5 MAYO | K2: 3 | L2: PAGO AL DIA | M2: Total depurado ($) | N2: Vendedor (normalizado) | O2: Estado cartera (normalizado) | P2: Categoría servicio | Q2: Rango antigüedad mora | R2: Rank saldo (para Top 10)
A3: 2 | B3: Karen Sirley Hernandez Morales | C3: 46107 | D3: Ximena | E3: SCRUM Plus | F3: M+PO | G3: INCREMENTO | H3: 100000 | I3: 290000 | J3: ABONO 1 31 MAR Y ABONO 2 15 ABRIL | K3: 8 | L3: Pendiente | M3: =IF(B3="","",IF(ISNUMBER(I3),I3,IFERROR(VALUE(SUBSTITUTE(SUBSTITUTE(I3,"$",""),".","")),0))) -> 290000 | N3: =IF(B3="","",PROPER(TRIM(D3))) -> Ximena | O3: =IF(B3="","",IF(OR(ISNUMBER(SEARCH("AL DIA",L3)),ISNUMBER(SEARCH("AL DIA",F3))),"Al día",IF(OR(ISNUMBER(SEARCH("QUIETO",L3)),ISNUMBER(SEARCH("QUIETO",F3)),ISNUMBER(SEARCH("ESPERANDO",L3)),ISNUMBER(SEARCH("ESPERANDO",F3))),"Sin respuesta / Inactivo",IF(OR(ISNUMBER(SEARCH("PENDIENTE",L3)),ISNUMBER(SEARCH("PENDIENTE",F3)),ISNUMBER(SEARCH("COMPROMISO",F3)),ISNUMBER(SEARCH("COMPROMISO",L3)),ISNUMBER(SEARCH("PROCESO",F3)),ISNUMBER(SEARCH("LLAMAR",F3)),ISNUMBER(SEARCH("ABONO",J3)),EXACT(L3,"P"),EXACT(F3,"P")),"Pendiente / Compromiso","Sin gestionar")))) -> Pendiente / Compromiso | P3: =IF(B3="","",IF(E3="","Sin definir",IF(ISNUMBER(SEARCH("ITIL",E3)),"ITIL",IF(ISNUMBER(SEARCH("ISO 27001",E3)),"ISO 27001",IF(ISNUMBER(SEARCH("ISO 42001",E3)),"ISO 42001",IF(ISNUMBER(SEARCH("ISO",E3)),"Otras ISO",IF(ISNUMBER(SEARCH("SCRUM",E3)),"SCRUM",IF(ISNUMBER(SEARCH("BRIDGE",E3)),"BRIDGE",IF(ISNUMBER(SEARCH("CDS",E3)),"CDS",IF(ISNUMBER(SEARCH("TOGAF",E3)),"TOGAF",IF(ISNUMBER(SEARCH("DPI",E3)),"DPI",IF(ISNUMBER(SEARCH("DITS",E3)),"DITS",IF(ISNUMBER(SEARCH("AGILE",E3)),"AGILE",IF(ISNUMBER(SEARCH("Ciberseguridad",E3)),"Ciberseguridad","Otros")))))))))))))) -> SCRUM | Q3: =IF(B3="","",IF(ISNUMBER(K3),IF(K3<=3,"1-3 meses",IF(K3<=6,"4-6 meses","+6 meses")),"Sin dato registrado")) -> +6 meses | R3: =IF(OR(B3="",M3=""),"",RANK(M3,$M$3:$M$306)+COUNTIF($M$3:M3,M3)-1) -> 55
A4: 3 | B4: Edgar Enrique Beltran Hernandez | C4: 46107 | D4: Ximena | E4: ITIL 4 Fundamentos | F4: Curso y examen | G4: INCREMENTO | H4: X | I4: 190000 | J4: abono1 27 de marzo hasta 15 mayo | K4: 6 | L4: PAGO AL DIA | M4: =IF(B4="","",IF(ISNUMBER(I4),I4,IFERROR(VALUE(SUBSTITUTE(SUBSTITUTE(I4,"$",""),".","")),0))) -> 190000 | N4: =IF(B4="","",PROPER(TRIM(D4))) -> Ximena | O4: =IF(B4="","",IF(OR(ISNUMBER(SEARCH("AL DIA",L4)),ISNUMBER(SEARCH("AL DIA",F4))),"Al día",IF(OR(ISNUMBER(SEARCH("QUIETO",L4)),ISNUMBER(SEARCH("QUIETO",F4)),ISNUMBER(SEARCH("ESPERANDO",L4)),ISNUMBER(SEARCH("ESPERANDO",F4))),"Sin respuesta / Inactivo",IF(OR(ISNUMBER(SEARCH("PENDIENTE",L4)),ISNUMBER(SEARCH("PENDIENTE",F4)),ISNUMBER(SEARCH("COMPROMISO",F4)),ISNUMBER(SEARCH("COMPROMISO",L4)),ISNUMBER(SEARCH("PROCESO",F4)),ISNUMBER(SEARCH("LLAMAR",F4)),ISNUMBER(SEARCH("ABONO",J4)),EXACT(L4,"P"),EXACT(F4,"P")),"Pendiente / Compromiso","Sin gestionar")))) -> Al día | P4: =IF(B4="","",IF(E4="","Sin definir",IF(ISNUMBER(SEARCH("ITIL",E4)),"ITIL",IF(ISNUMBER(SEARCH("ISO 27001",E4)),"ISO 27001",IF(ISNUMBER(SEARCH("ISO 42001",E4)),"ISO 42001",IF(ISNUMBER(SEARCH("ISO",E4)),"Otras ISO",IF(ISNUMBER(SEARCH("SCRUM",E4)),"SCRUM",IF(ISNUMBER(SEARCH("BRIDGE",E4)),"BRIDGE",IF(ISNUMBER(SEARCH("CDS",E4)),"CDS",IF(ISNUMBER(SEARCH("TOGAF",E4)),"TOGAF",IF(ISNUMBER(SEARCH("DPI",E4)),"DPI",IF(ISNUMBER(SEARCH("DITS",E4)),"DITS",IF(ISNUMBER(SEARCH("AGILE",E4)),"AGILE",IF(ISNUMBER(SEARCH("Ciberseguridad",E4)),"Ciberseguridad","Otros")))))))))))))) -> ITIL | Q4: =IF(B4="","",IF(ISNUMBER(K4),IF(K4<=3,"1-3 meses",IF(K4<=6,"4-6 meses","+6 meses")),"Sin dato registrado")) -> 4-6 meses | R4: =IF(OR(B4="",M4=""),"",RANK(M4,$M$3:$M$306)+COUNTIF($M$3:M4,M4)-1) -> 60
A5: 4 | B5: José León Nuñez Oñate | C5: 46108 | D5: Ximena | E5: ITIL 4 Fundamentos | F5: Curso y examen | G5: PROCESO | H5: 100000 | I5: 850000 | K5: 6 | M5: =IF(B5="","",IF(ISNUMBER(I5),I5,IFERROR(VALUE(SUBSTITUTE(SUBSTITUTE(I5,"$",""),".","")),0))) -> 850000 | N5: =IF(B5="","",PROPER(TRIM(D5))) -> Ximena | O5: =IF(B5="","",IF(OR(ISNUMBER(SEARCH("AL DIA",L5)),ISNUMBER(SEARCH("AL DIA",F5))),"Al día",IF(OR(ISNUMBER(SEARCH("QUIETO",L5)),ISNUMBER(SEARCH("QUIETO",F5)),ISNUMBER(SEARCH("ESPERANDO",L5)),ISNUMBER(SEARCH("ESPERANDO",F5))),"Sin respuesta / Inactivo",IF(OR(ISNUMBER(SEARCH("PENDIENTE",L5)),ISNUMBER(SEARCH("PENDIENTE",F5)),ISNUMBER(SEARCH("COMPROMISO",F5)),ISNUMBER(SEARCH("COMPROMISO",L5)),ISNUMBER(SEARCH("PROCESO",F5)),ISNUMBER(SEARCH("LLAMAR",F5)),ISNUMBER(SEARCH("ABONO",J5)),EXACT(L5,"P"),EXACT(F5,"P")),"Pendiente / Compromiso","Sin gestionar")))) -> Sin gestionar | P5: =IF(B5="","",IF(E5="","Sin definir",IF(ISNUMBER(SEARCH("ITIL",E5)),"ITIL",IF(ISNUMBER(SEARCH("ISO 27001",E5)),"ISO 27001",IF(ISNUMBER(SEARCH("ISO 42001",E5)),"ISO 42001",IF(ISNUMBER(SEARCH("ISO",E5)),"Otras ISO",IF(ISNUMBER(SEARCH("SCRUM",E5)),"SCRUM",IF(ISNUMBER(SEARCH("BRIDGE",E5)),"BRIDGE",IF(ISNUMBER(SEARCH("CDS",E5)),"CDS",IF(ISNUMBER(SEARCH("TOGAF",E5)),"TOGAF",IF(ISNUMBER(SEARCH("DPI",E5)),"DPI",IF(ISNUMBER(SEARCH("DITS",E5)),"DITS",IF(ISNUMBER(SEARCH("AGILE",E5)),"AGILE",IF(ISNUMBER(SEARCH("Ciberseguridad",E5)),"Ciberseguridad","Otros")))))))))))))) -> ITIL | Q5: =IF(B5="","",IF(ISNUMBER(K5),IF(K5<=3,"1-3 meses",IF(K5<=6,"4-6 meses","+6 meses")),"Sin dato registrado")) -> 4-6 meses | R5: =IF(OR(B5="",M5=""),"",RANK(M5,$M$3:$M$306)+COUNTIF($M$3:M5,M5)-1) -> 27
A6: 5 | B6: Luis Alberto Solarte Lopez | C6: 46108 | D6: Ximena | E6: ITIL 4 Fundamentos | F6: Curso y examen | G6: PROCESO | H6: 100000 | I6: 1267000 | K6: 6 | M6: =IF(B6="","",IF(ISNUMBER(I6),I6,IFERROR(VALUE(SUBSTITUTE(SUBSTITUTE(I6,"$",""),".","")),0))) -> 1267000 | N6: =IF(B6="","",PROPER(TRIM(D6))) -> Ximena | O6: =IF(B6="","",IF(OR(ISNUMBER(SEARCH("AL DIA",L6)),ISNUMBER(SEARCH("AL DIA",F6))),"Al día",IF(OR(ISNUMBER(SEARCH("QUIETO",L6)),ISNUMBER(SEARCH("QUIETO",F6)),ISNUMBER(SEARCH("ESPERANDO",L6)),ISNUMBER(SEARCH("ESPERANDO",F6))),"Sin respuesta / Inactivo",IF(OR(ISNUMBER(SEARCH("PENDIENTE",L6)),ISNUMBER(SEARCH("PENDIENTE",F6)),ISNUMBER(SEARCH("COMPROMISO",F6)),ISNUMBER(SEARCH("COMPROMISO",L6)),ISNUMBER(SEARCH("PROCESO",F6)),ISNUMBER(SEARCH("LLAMAR",F6)),ISNUMBER(SEARCH("ABONO",J6)),EXACT(L6,"P"),EXACT(F6,"P")),"Pendiente / Compromiso","Sin gestionar")))) -> Sin gestionar | P6: =IF(B6="","",IF(E6="","Sin definir",IF(ISNUMBER(SEARCH("ITIL",E6)),"ITIL",IF(ISNUMBER(SEARCH("ISO 27001",E6)),"ISO 27001",IF(ISNUMBER(SEARCH("ISO 42001",E6)),"ISO 42001",IF(ISNUMBER(SEARCH("ISO",E6)),"Otras ISO",IF(ISNUMBER(SEARCH("SCRUM",E6)),"SCRUM",IF(ISNUMBER(SEARCH("BRIDGE",E6)),"BRIDGE",IF(ISNUMBER(SEARCH("CDS",E6)),"CDS",IF(ISNUMBER(SEARCH("TOGAF",E6)),"TOGAF",IF(ISNUMBER(SEARCH("DPI",E6)),"DPI",IF(ISNUMBER(SEARCH("DITS",E6)),"DITS",IF(ISNUMBER(SEARCH("AGILE",E6)),"AGILE",IF(ISNUMBER(SEARCH("Ciberseguridad",E6)),"Ciberseguridad","Otros")))))))))))))) -> ITIL | Q6: =IF(B6="","",IF(ISNUMBER(K6),IF(K6<=3,"1-3 meses",IF(K6<=6,"4-6 meses","+6 meses")),"Sin dato registrado")) -> 4-6 meses | R6: =IF(OR(B6="",M6=""),"",RANK(M6,$M$3:$M$306)+COUNTIF($M$3:M6,M6)-1) -> 14
A7: 6 | B7: Juan Pablo Zambrano Sanchez | C7: 46108 | D7: Ximena | E7: ISO 22301 | F7: Curso y examen | G7: PROCESO | H7: 110000 | I7: 1200000 | K7: 5 | M7: =IF(B7="","",IF(ISNUMBER(I7),I7,IFERROR(VALUE(SUBSTITUTE(SUBSTITUTE(I7,"$",""),".","")),0))) -> 1200000 | N7: =IF(B7="","",PROPER(TRIM(D7))) -> Ximena | O7: =IF(B7="","",IF(OR(ISNUMBER(SEARCH("AL DIA",L7)),ISNUMBER(SEARCH("AL DIA",F7))),"Al día",IF(OR(ISNUMBER(SEARCH("QUIETO",L7)),ISNUMBER(SEARCH("QUIETO",F7)),ISNUMBER(SEARCH("ESPERANDO",L7)),ISNUMBER(SEARCH("ESPERANDO",F7))),"Sin respuesta / Inactivo",IF(OR(ISNUMBER(SEARCH("PENDIENTE",L7)),ISNUMBER(SEARCH("PENDIENTE",F7)),ISNUMBER(SEARCH("COMPROMISO",F7)),ISNUMBER(SEARCH("COMPROMISO",L7)),ISNUMBER(SEARCH("PROCESO",F7)),ISNUMBER(SEARCH("LLAMAR",F7)),ISNUMBER(SEARCH("ABONO",J7)),EXACT(L7,"P"),EXACT(F7,"P")),"Pendiente / Compromiso","Sin gestionar")))) -> Sin gestionar | P7: =IF(B7="","",IF(E7="","Sin definir",IF(ISNUMBER(SEARCH("ITIL",E7)),"ITIL",IF(ISNUMBER(SEARCH("ISO 27001",E7)),"ISO 27001",IF(ISNUMBER(SEARCH("ISO 42001",E7)),"ISO 42001",IF(ISNUMBER(SEARCH("ISO",E7)),"Otras ISO",IF(ISNUMBER(SEARCH("SCRUM",E7)),"SCRUM",IF(ISNUMBER(SEARCH("BRIDGE",E7)),"BRIDGE",IF(ISNUMBER(SEARCH("CDS",E7)),"CDS",IF(ISNUMBER(SEARCH("TOGAF",E7)),"TOGAF",IF(ISNUMBER(SEARCH("DPI",E7)),"DPI",IF(ISNUMBER(SEARCH("DITS",E7)),"DITS",IF(ISNUMBER(SEARCH("AGILE",E7)),"AGILE",IF(ISNUMBER(SEARCH("Ciberseguridad",E7)),"Ciberseguridad","Otros")))))))))))))) -> Otras ISO | Q7: =IF(B7="","",IF(ISNUMBER(K7),IF(K7<=3,"1-3 meses",IF(K7<=6,"4-6 meses","+6 meses")),"Sin dato registrado")) -> 4-6 meses | R7: =IF(OR(B7="",M7=""),"",RANK(M7,$M$3:$M$306)+COUNTIF($M$3:M7,M7)-1) -> 15
A8: 7 | B8: Dorian Lizeth Vera Cano | C8: 46108 | D8: Ximena | G8: CAMBIO AGILE A ITIL | M8: =IF(B8="","",IF(ISNUMBER(I8),I8,IFERROR(VALUE(SUBSTITUTE(SUBSTITUTE(I8,"$",""),".","")),0))) -> 0 | N8: =IF(B8="","",PROPER(TRIM(D8))) -> Ximena | O8: =IF(B8="","",IF(OR(ISNUMBER(SEARCH("AL DIA",L8)),ISNUMBER(SEARCH("AL DIA",F8))),"Al día",IF(OR(ISNUMBER(SEARCH("QUIETO",L8)),ISNUMBER(SEARCH("QUIETO",F8)),ISNUMBER(SEARCH("ESPERANDO",L8)),ISNUMBER(SEARCH("ESPERANDO",F8))),"Sin respuesta / Inactivo",IF(OR(ISNUMBER(SEARCH("PENDIENTE",L8)),ISNUMBER(SEARCH("PENDIENTE",F8)),ISNUMBER(SEARCH("COMPROMISO",F8)),ISNUMBER(SEARCH("COMPROMISO",L8)),ISNUMBER(SEARCH("PROCESO",F8)),ISNUMBER(SEARCH("LLAMAR",F8)),ISNUMBER(SEARCH("ABONO",J8)),EXACT(L8,"P"),EXACT(F8,"P")),"Pendiente / Compromiso","Sin gestionar")))) -> Sin gestionar | P8: =IF(B8="","",IF(E8="","Sin definir",IF(ISNUMBER(SEARCH("ITIL",E8)),"ITIL",IF(ISNUMBER(SEARCH("ISO 27001",E8)),"ISO 27001",IF(ISNUMBER(SEARCH("ISO 42001",E8)),"ISO 42001",IF(ISNUMBER(SEARCH("ISO",E8)),"Otras ISO",IF(ISNUMBER(SEARCH("SCRUM",E8)),"SCRUM",IF(ISNUMBER(SEARCH("BRIDGE",E8)),"BRIDGE",IF(ISNUMBER(SEARCH("CDS",E8)),"CDS",IF(ISNUMBER(SEARCH("TOGAF",E8)),"TOGAF",IF(ISNUMBER(SEARCH("DPI",E8)),"DPI",IF(ISNUMBER(SEARCH("DITS",E8)),"DITS",IF(ISNUMBER(SEARCH("AGILE",E8)),"AGILE",IF(ISNUMBER(SEARCH("Ciberseguridad",E8)),"Ciberseguridad","Otros")))))))))))))) -> Sin definir | Q8: =IF(B8="","",IF(ISNUMBER(K8),IF(K8<=3,"1-3 meses",IF(K8<=6,"4-6 meses","+6 meses")),"Sin dato registrado")) -> Sin dato registrado | R8: =IF(OR(B8="",M8=""),"",RANK(M8,$M$3:$M$306)+COUNTIF($M$3:M8,M8)-1) -> 61
A9: 8 | B9: Vivian Sanz Martelo | G9: COMPROMISO DE PAGO | H9: X | I9: $1.000.000 | J9: ABONO 10ABRIL | K9: X | L9: PAGO AL DIA | M9: =IF(B9="","",IF(ISNUMBER(I9),I9,IFERROR(VALUE(SUBSTITUTE(SUBSTITUTE(I9,"$",""),".","")),0))) -> 1000000 | N9: =IF(B9="","",PROPER(TRIM(D9))) | O9: =IF(B9="","",IF(OR(ISNUMBER(SEARCH("AL DIA",L9)),ISNUMBER(SEARCH("AL DIA",F9))),"Al día",IF(OR(ISNUMBER(SEARCH("QUIETO",L9)),ISNUMBER(SEARCH("QUIETO",F9)),ISNUMBER(SEARCH("ESPERANDO",L9)),ISNUMBER(SEARCH("ESPERANDO",F9))),"Sin respuesta / Inactivo",IF(OR(ISNUMBER(SEARCH("PENDIENTE",L9)),ISNUMBER(SEARCH("PENDIENTE",F9)),ISNUMBER(SEARCH("COMPROMISO",F9)),ISNUMBER(SEARCH("COMPROMISO",L9)),ISNUMBER(SEARCH("PROCESO",F9)),ISNUMBER(SEARCH("LLAMAR",F9)),ISNUMBER(SEARCH("ABONO",J9)),EXACT(L9,"P"),EXACT(F9,"P")),"Pendiente / Compromiso","Sin gestionar")))) -> Al día | P9: =IF(B9="","",IF(E9="","Sin definir",IF(ISNUMBER(SEARCH("ITIL",E9)),"ITIL",IF(ISNUMBER(SEARCH("ISO 27001",E9)),"ISO 27001",IF(ISNUMBER(SEARCH("ISO 42001",E9)),"ISO 42001",IF(ISNUMBER(SEARCH("ISO",E9)),"Otras ISO",IF(ISNUMBER(SEARCH("SCRUM",E9)),"SCRUM",IF(ISNUMBER(SEARCH("BRIDGE",E9)),"BRIDGE",IF(ISNUMBER(SEARCH("CDS",E9)),"CDS",IF(ISNUMBER(SEARCH("TOGAF",E9)),"TOGAF",IF(ISNUMBER(SEARCH("DPI",E9)),"DPI",IF(ISNUMBER(SEARCH("DITS",E9)),"DITS",IF(ISNUMBER(SEARCH("AGILE",E9)),"AGILE",IF(ISNUMBER(SEARCH("Ciberseguridad",E9)),"Ciberseguridad","Otros")))))))))))))) -> Sin definir | Q9: =IF(B9="","",IF(ISNUMBER(K9),IF(K9<=3,"1-3 meses",IF(K9<=6,"4-6 meses","+6 meses")),"Sin dato registrado")) -> Sin dato registrado | R9: =IF(OR(B9="",M9=""),"",RANK(M9,$M$3:$M$306)+COUNTIF($M$3:M9,M9)-1) -> 18
A10: 9 | B10: Sindy Lorena Ortiz Gonzalez | D10: Sebas | E10: SCRUM gold | G10: COMPROMISO DE PAGO | H10: X | I10: $1.100.000 | J10: ABONO 15 JUN | L10: Pendiente X FECHA | M10: =IF(B10="","",IF(ISNUMBER(I10),I10,IFERROR(VALUE(SUBSTITUTE(SUBSTITUTE(I10,"$",""),".","")),0))) -> 1100000 | N10: =IF(B10="","",PROPER(TRIM(D10))) -> Sebas | O10: =IF(B10="","",IF(OR(ISNUMBER(SEARCH("AL DIA",L10)),ISNUMBER(SEARCH("AL DIA",F10))),"Al día",IF(OR(ISNUMBER(SEARCH("QUIETO",L10)),ISNUMBER(SEARCH("QUIETO",F10)),ISNUMBER(SEARCH("ESPERANDO",L10)),ISNUMBER(SEARCH("ESPERANDO",F10))),"Sin respuesta / Inactivo",IF(OR(ISNUMBER(SEARCH("PENDIENTE",L10)),ISNUMBER(SEARCH("PENDIENTE",F10)),ISNUMBER(SEARCH("COMPROMISO",F10)),ISNUMBER(SEARCH("COMPROMISO",L10)),ISNUMBER(SEARCH("PROCESO",F10)),ISNUMBER(SEARCH("LLAMAR",F10)),ISNUMBER(SEARCH("ABONO",J10)),EXACT(L10,"P"),EXACT(F10,"P")),"Pendiente / Compromiso","Sin gestionar")))) -> Pendiente / Compromiso | P10: =IF(B10="","",IF(E10="","Sin definir",IF(ISNUMBER(SEARCH("ITIL",E10)),"ITIL",IF(ISNUMBER(SEARCH("ISO 27001",E10)),"ISO 27001",IF(ISNUMBER(SEARCH("ISO 42001",E10)),"ISO 42001",IF(ISNUMBER(SEARCH("ISO",E10)),"Otras ISO",IF(ISNUMBER(SEARCH("SCRUM",E10)),"SCRUM",IF(ISNUMBER(SEARCH("BRIDGE",E10)),"BRIDGE",IF(ISNUMBER(SEARCH("CDS",E10)),"CDS",IF(ISNUMBER(SEARCH("TOGAF",E10)),"TOGAF",IF(ISNUMBER(SEARCH("DPI",E10)),"DPI",IF(ISNUMBER(SEARCH("DITS",E10)),"DITS",IF(ISNUMBER(SEARCH("AGILE",E10)),"AGILE",IF(ISNUMBER(SEARCH("Ciberseguridad",E10)),"Ciberseguridad","Otros")))))))))))))) -> SCRUM | Q10: =IF(B10="","",IF(ISNUMBER(K10),IF(K10<=3,"1-3 meses",IF(K10<=6,"4-6 meses","+6 meses")),"Sin dato registrado")) -> Sin dato registrado | R10: =IF(OR(B10="",M10=""),"",RANK(M10,$M$3:$M$306)+COUNTIF($M$3:M10,M10)-1) -> 17
A11: 10 | B11: Osiris Yasbleidy Torres Gutierrez | D11: Sebas | E11: Ciberseguridad | G11: COMPROMISO DE PAGO | H11: X | I11: 850000 | J11: ABONO 15 ABR | L11: PAGO AL DIA | M11: =IF(B11="","",IF(ISNUMBER(I11),I11,IFERROR(VALUE(SUBSTITUTE(SUBSTITUTE(I11,"$",""),".","")),0))) -> 850000 | N11: =IF(B11="","",PROPER(TRIM(D11))) -> Sebas | O11: =IF(B11="","",IF(OR(ISNUMBER(SEARCH("AL DIA",L11)),ISNUMBER(SEARCH("AL DIA",F11))),"Al día",IF(OR(ISNUMBER(SEARCH("QUIETO",L11)),ISNUMBER(SEARCH("QUIETO",F11)),ISNUMBER(SEARCH("ESPERANDO",L11)),ISNUMBER(SEARCH("ESPERANDO",F11))),"Sin respuesta / Inactivo",IF(OR(ISNUMBER(SEARCH("PENDIENTE",L11)),ISNUMBER(SEARCH("PENDIENTE",F11)),ISNUMBER(SEARCH("COMPROMISO",F11)),ISNUMBER(SEARCH("COMPROMISO",L11)),ISNUMBER(SEARCH("PROCESO",F11)),ISNUMBER(SEARCH("LLAMAR",F11)),ISNUMBER(SEARCH("ABONO",J11)),EXACT(L11,"P"),EXACT(F11,"P")),"Pendiente / Compromiso","Sin gestionar")))) -> Al día | P11: =IF(B11="","",IF(E11="","Sin definir",IF(ISNUMBER(SEARCH("ITIL",E11)),"ITIL",IF(ISNUMBER(SEARCH("ISO 27001",E11)),"ISO 27001",IF(ISNUMBER(SEARCH("ISO 42001",E11)),"ISO 42001",IF(ISNUMBER(SEARCH("ISO",E11)),"Otras ISO",IF(ISNUMBER(SEARCH("SCRUM",E11)),"SCRUM",IF(ISNUMBER(SEARCH("BRIDGE",E11)),"BRIDGE",IF(ISNUMBER(SEARCH("CDS",E11)),"CDS",IF(ISNUMBER(SEARCH("TOGAF",E11)),"TOGAF",IF(ISNUMBER(SEARCH("DPI",E11)),"DPI",IF(ISNUMBER(SEARCH("DITS",E11)),"DITS",IF(ISNUMBER(SEARCH("AGILE",E11)),"AGILE",IF(ISNUMBER(SEARCH("Ciberseguridad",E11)),"Ciberseguridad","Otros")))))))))))))) -> Ciberseguridad | Q11: =IF(B11="","",IF(ISNUMBER(K11),IF(K11<=3,"1-3 meses",IF(K11<=6,"4-6 meses","+6 meses")),"Sin dato registrado")) -> Sin dato registrado | R11: =IF(OR(B11="",M11=""),"",RANK(M11,$M$3:$M$306)+COUNTIF($M$3:M11,M11)-1) -> 28
A12: 11 | B12: Gianella Mendoza Ruiz | D12: Sebas | E12: ITIL 4 Fundamentos | G12: COMPROMISO DE PAGO | H12: X | I12: 975000 | J12: ABONO 30 ABR | L12: PAGO AL DIA | M12: =IF(B12="","",IF(ISNUMBER(I12),I12,IFERROR(VALUE(SUBSTITUTE(SUBSTITUTE(I12,"$",""),".","")),0))) -> 975000 | N12: =IF(B12="","",PROPER(TRIM(D12))) -> Sebas | O12: =IF(B12="","",IF(OR(ISNUMBER(SEARCH("AL DIA",L12)),ISNUMBER(SEARCH("AL DIA",F12))),"Al día",IF(OR(ISNUMBER(SEARCH("QUIETO",L12)),ISNUMBER(SEARCH("QUIETO",F12)),ISNUMBER(SEARCH("ESPERANDO",L12)),ISNUMBER(SEARCH("ESPERANDO",F12))),"Sin respuesta / Inactivo",IF(OR(ISNUMBER(SEARCH("PENDIENTE",L12)),ISNUMBER(SEARCH("PENDIENTE",F12)),ISNUMBER(SEARCH("COMPROMISO",F12)),ISNUMBER(SEARCH("COMPROMISO",L12)),ISNUMBER(SEARCH("PROCESO",F12)),ISNUMBER(SEARCH("LLAMAR",F12)),ISNUMBER(SEARCH("ABONO",J12)),EXACT(L12,"P"),EXACT(F12,"P")),"Pendiente / Compromiso","Sin gestionar")))) -> Al día | P12: =IF(B12="","",IF(E12="","Sin definir",IF(ISNUMBER(SEARCH("ITIL",E12)),"ITIL",IF(ISNUMBER(SEARCH("ISO 27001",E12)),"ISO 27001",IF(ISNUMBER(SEARCH("ISO 42001",E12)),"ISO 42001",IF(ISNUMBER(SEARCH("ISO",E12)),"Otras ISO",IF(ISNUMBER(SEARCH("SCRUM",E12)),"SCRUM",IF(ISNUMBER(SEARCH("BRIDGE",E12)),"BRIDGE",IF(ISNUMBER(SEARCH("CDS",E12)),"CDS",IF(ISNUMBER(SEARCH("TOGAF",E12)),"TOGAF",IF(ISNUMBER(SEARCH("DPI",E12)),"DPI",IF(ISNUMBER(SEARCH("DITS",E12)),"DITS",IF(ISNUMBER(SEARCH("AGILE",E12)),"AGILE",IF(ISNUMBER(SEARCH("Ciberseguridad",E12)),"Ciberseguridad","Otros")))))))))))))) -> ITIL | Q12: =IF(B12="","",IF(ISNUMBER(K12),IF(K12<=3,"1-3 meses",IF(K12<=6,"4-6 meses","+6 meses")),"Sin dato registrado")) -> Sin dato registrado | R12: =IF(OR(B12="",M12=""),"",RANK(M12,$M$3:$M$306)+COUNTIF($M$3:M12,M12)-1) -> 22
A13: 12 | B13: Luis Fernando Ramirez Cancelado | D13: Ximena | E13: Ciberseguridad | G13: COMPROMISO DE PAGO | H13: X | I13: 500000 | J13: ABONO 16 ABR | L13: Pendiente X FECHA | M13: =IF(B13="","",IF(ISNUMBER(I13),I13,IFERROR(VALUE(SUBSTITUTE(SUBSTITUTE(I13,"$",""),".","")),0))) -> 500000 | N13: =IF(B13="","",PROPER(TRIM(D13))) -> Ximena | O13: =IF(B13="","",IF(OR(ISNUMBER(SEARCH("AL DIA",L13)),ISNUMBER(SEARCH("AL DIA",F13))),"Al día",IF(OR(ISNUMBER(SEARCH("QUIETO",L13)),ISNUMBER(SEARCH("QUIETO",F13)),ISNUMBER(SEARCH("ESPERANDO",L13)),ISNUMBER(SEARCH("ESPERANDO",F13))),"Sin respuesta / Inactivo",IF(OR(ISNUMBER(SEARCH("PENDIENTE",L13)),ISNUMBER(SEARCH("PENDIENTE",F13)),ISNUMBER(SEARCH("COMPROMISO",F13)),ISNUMBER(SEARCH("COMPROMISO",L13)),ISNUMBER(SEARCH("PROCESO",F13)),ISNUMBER(SEARCH("LLAMAR",F13)),ISNUMBER(SEARCH("ABONO",J13)),EXACT(L13,"P"),EXACT(F13,"P")),"Pendiente / Compromiso","Sin gestionar")))) -> Pendiente / Compromiso | P13: =IF(B13="","",IF(E13="","Sin definir",IF(ISNUMBER(SEARCH("ITIL",E13)),"ITIL",IF(ISNUMBER(SEARCH("ISO 27001",E13)),"ISO 27001",IF(ISNUMBER(SEARCH("ISO 42001",E13)),"ISO 42001",IF(ISNUMBER(SEARCH("ISO",E13)),"Otras ISO",IF(ISNUMBER(SEARCH("SCRUM",E13)),"SCRUM",IF(ISNUMBER(SEARCH("BRIDGE",E13)),"BRIDGE",IF(ISNUMBER(SEARCH("CDS",E13)),"CDS",IF(ISNUMBER(SEARCH("TOGAF",E13)),"TOGAF",IF(ISNUMBER(SEARCH("DPI",E13)),"DPI",IF(ISNUMBER(SEARCH("DITS",E13)),"DITS",IF(ISNUMBER(SEARCH("AGILE",E13)),"AGILE",IF(ISNUMBER(SEARCH("Ciberseguridad",E13)),"Ciberseguridad","Otros")))))))))))))) -> Ciberseguridad | Q13: =IF(B13="","",IF(ISNUMBER(K13),IF(K13<=3,"1-3 meses",IF(K13<=6,"4-6 meses","+6 meses")),"Sin dato registrado")) -> Sin dato registrado | R13: =IF(OR(B13="",M13=""),"",RANK(M13,$M$3:$M$306)+COUNTIF($M$3:M13,M13)-1) -> 46
A14: 14 | B14: Meredith Ibarra Uyaban | D14: Ximena | E14: ISO 27001 | G14: COMPROMISO DE PAGO | H14: X | I14: 640000 | J14: ABONO 30ABR/31MAY/30JUN | L14: Pendiente X FECHA | M14: =IF(B14="","",IF(ISNUMBER(I14),I14,IFERROR(VALUE(SUBSTITUTE(SUBSTITUTE(I14,"$",""),".","")),0))) -> 640000 | N14: =IF(B14="","",PROPER(TRIM(D14))) -> Ximena | O14: =IF(B14="","",IF(OR(ISNUMBER(SEARCH("AL DIA",L14)),ISNUMBER(SEARCH("AL DIA",F14))),"Al día",IF(OR(ISNUMBER(SEARCH("QUIETO",L14)),ISNUMBER(SEARCH("QUIETO",F14)),ISNUMBER(SEARCH("ESPERANDO",L14)),ISNUMBER(SEARCH("ESPERANDO",F14))),"Sin respuesta / Inactivo",IF(OR(ISNUMBER(SEARCH("PENDIENTE",L14)),ISNUMBER(SEARCH("PENDIENTE",F14)),ISNUMBER(SEARCH("COMPROMISO",F14)),ISNUMBER(SEARCH("COMPROMISO",L14)),ISNUMBER(SEARCH("PROCESO",F14)),ISNUMBER(SEARCH("LLAMAR",F14)),ISNUMBER(SEARCH("ABONO",J14)),EXACT(L14,"P"),EXACT(F14,"P")),"Pendiente / Compromiso","Sin gestionar")))) -> Pendiente / Compromiso | P14: =IF(B14="","",IF(E14="","Sin definir",IF(ISNUMBER(SEARCH("ITIL",E14)),"ITIL",IF(ISNUMBER(SEARCH("ISO 27001",E14)),"ISO 27001",IF(ISNUMBER(SEARCH("ISO 42001",E14)),"ISO 42001",IF(ISNUMBER(SEARCH("ISO",E14)),"Otras ISO",IF(ISNUMBER(SEARCH("SCRUM",E14)),"SCRUM",IF(ISNUMBER(SEARCH("BRIDGE",E14)),"BRIDGE",IF(ISNUMBER(SEARCH("CDS",E14)),"CDS",IF(ISNUMBER(SEARCH("TOGAF",E14)),"TOGAF",IF(ISNUMBER(SEARCH("DPI",E14)),"DPI",IF(ISNUMBER(SEARCH("DITS",E14)),"DITS",IF(ISNUMBER(SEARCH("AGILE",E14)),"AGILE",IF(ISNUMBER(SEARCH("Ciberseguridad",E14)),"Ciberseguridad","Otros")))))))))))))) -> ISO 27001 | Q14: =IF(B14="","",IF(ISNUMBER(K14),IF(K14<=3,"1-3 meses",IF(K14<=6,"4-6 meses","+6 meses")),"Sin dato registrado")) -> Sin dato registrado | R14: =IF(OR(B14="",M14=""),"",RANK(M14,$M$3:$M$306)+COUNTIF($M$3:M14,M14)-1) -> 43
A15: 15 | B15: Maria Paula villamil | D15: Ximena | E15: ISO 27001 | G15: COMPROMISO DE PAGO | H15: X | I15: 594967 | J15: ABONO 30ABR/31MAY/30JUN | L15: Pendiente X FECHA | M15: =IF(B15="","",IF(ISNUMBER(I15),I15,IFERROR(VALUE(SUBSTITUTE(SUBSTITUTE(I15,"$",""),".","")),0))) -> 594967 | N15: =IF(B15="","",PROPER(TRIM(D15))) -> Ximena | O15: =IF(B15="","",IF(OR(ISNUMBER(SEARCH("AL DIA",L15)),ISNUMBER(SEARCH("AL DIA",F15))),"Al día",IF(OR(ISNUMBER(SEARCH("QUIETO",L15)),ISNUMBER(SEARCH("QUIETO",F15)),ISNUMBER(SEARCH("ESPERANDO",L15)),ISNUMBER(SEARCH("ESPERANDO",F15))),"Sin respuesta / Inactivo",IF(OR(ISNUMBER(SEARCH("PENDIENTE",L15)),ISNUMBER(SEARCH("PENDIENTE",F15)),ISNUMBER(SEARCH("COMPROMISO",F15)),ISNUMBER(SEARCH("COMPROMISO",L15)),ISNUMBER(SEARCH("PROCESO",F15)),ISNUMBER(SEARCH("LLAMAR",F15)),ISNUMBER(SEARCH("ABONO",J15)),EXACT(L15,"P"),EXACT(F15,"P")),"Pendiente / Compromiso","Sin gestionar")))) -> Pendiente / Compromiso | P15: =IF(B15="","",IF(E15="","Sin definir",IF(ISNUMBER(SEARCH("ITIL",E15)),"ITIL",IF(ISNUMBER(SEARCH("ISO 27001",E15)),"ISO 27001",IF(ISNUMBER(SEARCH("ISO 42001",E15)),"ISO 42001",IF(ISNUMBER(SEARCH("ISO",E15)),"Otras ISO",IF(ISNUMBER(SEARCH("SCRUM",E15)),"SCRUM",IF(ISNUMBER(SEARCH("BRIDGE",E15)),"BRIDGE",IF(ISNUMBER(SEARCH("CDS",E15)),"CDS",IF(ISNUMBER(SEARCH("TOGAF",E15)),"TOGAF",IF(ISNUMBER(SEARCH("DPI",E15)),"DPI",IF(ISNUMBER(SEARCH("DITS",E15)),"DITS",IF(ISNUMBER(SEARCH("AGILE",E15)),"AGILE",IF(ISNUMBER(SEARCH("Ciberseguridad",E15)),"Ciberseguridad","Otros")))))))))))))) -> ISO 27001 | Q15: =IF(B15="","",IF(ISNUMBER(K15),IF(K15<=3,"1-3 meses",IF(K15<=6,"4-6 meses","+6 meses")),"Sin dato registrado")) -> Sin dato registrado | R15: =IF(OR(B15="",M15=""),"",RANK(M15,$M$3:$M$306)+COUNTIF($M$3:M15,M15)-1) -> 45
A16: 16 | B16: Nilson Andres Urresti Gonzalez | D16: Carolina | E16: ITIL 4 Fundamentos | G16: COMPROMISO DE PAGO | H16: X | I16: 925000 | M16: =IF(B16="","",IF(ISNUMBER(I16),I16,IFERROR(VALUE(SUBSTITUTE(SUBSTITUTE(I16,"$",""),".","")),0))) -> 925000 | N16: =IF(B16="","",PROPER(TRIM(D16))) -> Carolina | O16: =IF(B16="","",IF(OR(ISNUMBER(SEARCH("AL DIA",L16)),ISNUMBER(SEARCH("AL DIA",F16))),"Al día",IF(OR(ISNUMBER(SEARCH("QUIETO",L16)),ISNUMBER(SEARCH("QUIETO",F16)),ISNUMBER(SEARCH("ESPERANDO",L16)),ISNUMBER(SEARCH("ESPERANDO",F16))),"Sin respuesta / Inactivo",IF(OR(ISNUMBER(SEARCH("PENDIENTE",L16)),ISNUMBER(SEARCH("PENDIENTE",F16)),ISNUMBER(SEARCH("COMPROMISO",F16)),ISNUMBER(SEARCH("COMPROMISO",L16)),ISNUMBER(SEARCH("PROCESO",F16)),ISNUMBER(SEARCH("LLAMAR",F16)),ISNUMBER(SEARCH("ABONO",J16)),EXACT(L16,"P"),EXACT(F16,"P")),"Pendiente / Compromiso","Sin gestionar")))) -> Sin gestionar | P16: =IF(B16="","",IF(E16="","Sin definir",IF(ISNUMBER(SEARCH("ITIL",E16)),"ITIL",IF(ISNUMBER(SEARCH("ISO 27001",E16)),"ISO 27001",IF(ISNUMBER(SEARCH("ISO 42001",E16)),"ISO 42001",IF(ISNUMBER(SEARCH("ISO",E16)),"Otras ISO",IF(ISNUMBER(SEARCH("SCRUM",E16)),"SCRUM",IF(ISNUMBER(SEARCH("BRIDGE",E16)),"BRIDGE",IF(ISNUMBER(SEARCH("CDS",E16)),"CDS",IF(ISNUMBER(SEARCH("TOGAF",E16)),"TOGAF",IF(ISNUMBER(SEARCH("DPI",E16)),"DPI",IF(ISNUMBER(SEARCH("DITS",E16)),"DITS",IF(ISNUMBER(SEARCH("AGILE",E16)),"AGILE",IF(ISNUMBER(SEARCH("Ciberseguridad",E16)),"Ciberseguridad","Otros")))))))))))))) -> ITIL | Q16: =IF(B16="","",IF(ISNUMBER(K16),IF(K16<=3,"1-3 meses",IF(K16<=6,"4-6 meses","+6 meses")),"Sin dato registrado")) -> Sin dato registrado | R16: =IF(OR(B16="",M16=""),"",RANK(M16,$M$3:$M$306)+COUNTIF($M$3:M16,M16)-1) -> 24
A17: 17 | B17: Gelmer Parada Parada | D17: Sebas | E17: ITIL 4 Fundamentos | G17: llamar | H17: - | I17: 1450000 | J17: - | K17: - | L17: - | M17: =IF(B17="","",IF(ISNUMBER(I17),I17,IFERROR(VALUE(SUBSTITUTE(SUBSTITUTE(I17,"$",""),".","")),0))) -> 1450000 | N17: =IF(B17="","",PROPER(TRIM(D17))) -> Sebas | O17: =IF(B17="","",IF(OR(ISNUMBER(SEARCH("AL DIA",L17)),ISNUMBER(SEARCH("AL DIA",F17))),"Al día",IF(OR(ISNUMBER(SEARCH("QUIETO",L17)),ISNUMBER(SEARCH("QUIETO",F17)),ISNUMBER(SEARCH("ESPERANDO",L17)),ISNUMBER(SEARCH("ESPERANDO",F17))),"Sin respuesta / Inactivo",IF(OR(ISNUMBER(SEARCH("PENDIENTE",L17)),ISNUMBER(SEARCH("PENDIENTE",F17)),ISNUMBER(SEARCH("COMPROMISO",F17)),ISNUMBER(SEARCH("COMPROMISO",L17)),ISNUMBER(SEARCH("PROCESO",F17)),ISNUMBER(SEARCH("LLAMAR",F17)),ISNUMBER(SEARCH("ABONO",J17)),EXACT(L17,"P"),EXACT(F17,"P")),"Pendiente / Compromiso","Sin gestionar")))) -> Sin gestionar | P17: =IF(B17="","",IF(E17="","Sin definir",IF(ISNUMBER(SEARCH("ITIL",E17)),"ITIL",IF(ISNUMBER(SEARCH("ISO 27001",E17)),"ISO 27001",IF(ISNUMBER(SEARCH("ISO 42001",E17)),"ISO 42001",IF(ISNUMBER(SEARCH("ISO",E17)),"Otras ISO",IF(ISNUMBER(SEARCH("SCRUM",E17)),"SCRUM",IF(ISNUMBER(SEARCH("BRIDGE",E17)),"BRIDGE",IF(ISNUMBER(SEARCH("CDS",E17)),"CDS",IF(ISNUMBER(SEARCH("TOGAF",E17)),"TOGAF",IF(ISNUMBER(SEARCH("DPI",E17)),"DPI",IF(ISNUMBER(SEARCH("DITS",E17)),"DITS",IF(ISNUMBER(SEARCH("AGILE",E17)),"AGILE",IF(ISNUMBER(SEARCH("Ciberseguridad",E17)),"Ciberseguridad","Otros")))))))))))))) -> ITIL | Q17: =IF(B17="","",IF(ISNUMBER(K17),IF(K17<=3,"1-3 meses",IF(K17<=6,"4-6 meses","+6 meses")),"Sin dato registrado")) -> Sin dato registrado | R17: =IF(OR(B17="",M17=""),"",RANK(M17,$M$3:$M$306)+COUNTIF($M$3:M17,M17)-1) -> 12
A18: 18 | B18: Gabriel Enrique Moreno Pérez | D18: Sebas | E18: DITS | G18: PENDIENTE POR INGRESAR CRUSO | H18: X | I18: 3150000 | L18: QUIETO | M18: =IF(B18="","",IF(ISNUMBER(I18),I18,IFERROR(VALUE(SUBSTITUTE(SUBSTITUTE(I18,"$",""),".","")),0))) -> 3150000 | N18: =IF(B18="","",PROPER(TRIM(D18))) -> Sebas | O18: =IF(B18="","",IF(OR(ISNUMBER(SEARCH("AL DIA",L18)),ISNUMBER(SEARCH("AL DIA",F18))),"Al día",IF(OR(ISNUMBER(SEARCH("QUIETO",L18)),ISNUMBER(SEARCH("QUIETO",F18)),ISNUMBER(SEARCH("ESPERANDO",L18)),ISNUMBER(SEARCH("ESPERANDO",F18))),"Sin respuesta / Inactivo",IF(OR(ISNUMBER(SEARCH("PENDIENTE",L18)),ISNUMBER(SEARCH("PENDIENTE",F18)),ISNUMBER(SEARCH("COMPROMISO",F18)),ISNUMBER(SEARCH("COMPROMISO",L18)),ISNUMBER(SEARCH("PROCESO",F18)),ISNUMBER(SEARCH("LLAMAR",F18)),ISNUMBER(SEARCH("ABONO",J18)),EXACT(L18,"P"),EXACT(F18,"P")),"Pendiente / Compromiso","Sin gestionar")))) -> Sin respuesta / Inactivo | P18: =IF(B18="","",IF(E18="","Sin definir",IF(ISNUMBER(SEARCH("ITIL",E18)),"ITIL",IF(ISNUMBER(SEARCH("ISO 27001",E18)),"ISO 27001",IF(ISNUMBER(SEARCH("ISO 42001",E18)),"ISO 42001",IF(ISNUMBER(SEARCH("ISO",E18)),"Otras ISO",IF(ISNUMBER(SEARCH("SCRUM",E18)),"SCRUM",IF(ISNUMBER(SEARCH("BRIDGE",E18)),"BRIDGE",IF(ISNUMBER(SEARCH("CDS",E18)),"CDS",IF(ISNUMBER(SEARCH("TOGAF",E18)),"TOGAF",IF(ISNUMBER(SEARCH("DPI",E18)),"DPI",IF(ISNUMBER(SEARCH("DITS",E18)),"DITS",IF(ISNUMBER(SEARCH("AGILE",E18)),"AGILE",IF(ISNUMBER(SEARCH("Ciberseguridad",E18)),"Ciberseguridad","Otros")))))))))))))) -> DITS | Q18: =IF(B18="","",IF(ISNUMBER(K18),IF(K18<=3,"1-3 meses",IF(K18<=6,"4-6 meses","+6 meses")),"Sin dato registrado")) -> Sin dato registrado | R18: =IF(OR(B18="",M18=""),"",RANK(M18,$M$3:$M$306)+COUNTIF($M$3:M18,M18)-1) -> 1
A19: 19 | B19: Diana Carolina Acuña Serrano | D19: Carolina | E19: CDS | G19: PENDIENTE | H19: - | I19: 200000 | L19: AL DIA | M19: =IF(B19="","",IF(ISNUMBER(I19),I19,IFERROR(VALUE(SUBSTITUTE(SUBSTITUTE(I19,"$",""),".","")),0))) -> 200000 | N19: =IF(B19="","",PROPER(TRIM(D19))) -> Carolina | O19: =IF(B19="","",IF(OR(ISNUMBER(SEARCH("AL DIA",L19)),ISNUMBER(SEARCH("AL DIA",F19))),"Al día",IF(OR(ISNUMBER(SEARCH("QUIETO",L19)),ISNUMBER(SEARCH("QUIETO",F19)),ISNUMBER(SEARCH("ESPERANDO",L19)),ISNUMBER(SEARCH("ESPERANDO",F19))),"Sin respuesta / Inactivo",IF(OR(ISNUMBER(SEARCH("PENDIENTE",L19)),ISNUMBER(SEARCH("PENDIENTE",F19)),ISNUMBER(SEARCH("COMPROMISO",F19)),ISNUMBER(SEARCH("COMPROMISO",L19)),ISNUMBER(SEARCH("PROCESO",F19)),ISNUMBER(SEARCH("LLAMAR",F19)),ISNUMBER(SEARCH("ABONO",J19)),EXACT(L19,"P"),EXACT(F19,"P")),"Pendiente / Compromiso","Sin gestionar")))) -> Al día | P19: =IF(B19="","",IF(E19="","Sin definir",IF(ISNUMBER(SEARCH("ITIL",E19)),"ITIL",IF(ISNUMBER(SEARCH("ISO 27001",E19)),"ISO 27001",IF(ISNUMBER(SEARCH("ISO 42001",E19)),"ISO 42001",IF(ISNUMBER(SEARCH("ISO",E19)),"Otras ISO",IF(ISNUMBER(SEARCH("SCRUM",E19)),"SCRUM",IF(ISNUMBER(SEARCH("BRIDGE",E19)),"BRIDGE",IF(ISNUMBER(SEARCH("CDS",E19)),"CDS",IF(ISNUMBER(SEARCH("TOGAF",E19)),"TOGAF",IF(ISNUMBER(SEARCH("DPI",E19)),"DPI",IF(ISNUMBER(SEARCH("DITS",E19)),"DITS",IF(ISNUMBER(SEARCH("AGILE",E19)),"AGILE",IF(ISNUMBER(SEARCH("Ciberseguridad",E19)),"Ciberseguridad","Otros")))))))))))))) -> CDS | Q19: =IF(B19="","",IF(ISNUMBER(K19),IF(K19<=3,"1-3 meses",IF(K19<=6,"4-6 meses","+6 meses")),"Sin dato registrado")) -> Sin dato registrado | R19: =IF(OR(B19="",M19=""),"",RANK(M19,$M$3:$M$306)+COUNTIF($M$3:M19,M19)-1) -> 59
A20: 20 | B20: Jhon Isaias Muñoz Remolina | D20: Ximena | E20: CDS | G20: COMPROMISO DE PAGO | H20: x | I20: 2390000 | L20: Pendiente X FECHA | M20: =IF(B20="","",IF(ISNUMBER(I20),I20,IFERROR(VALUE(SUBSTITUTE(SUBSTITUTE(I20,"$",""),".","")),0))) -> 2390000 | N20: =IF(B20="","",PROPER(TRIM(D20))) -> Ximena | O20: =IF(B20="","",IF(OR(ISNUMBER(SEARCH("AL DIA",L20)),ISNUMBER(SEARCH("AL DIA",F20))),"Al día",IF(OR(ISNUMBER(SEARCH("QUIETO",L20)),ISNUMBER(SEARCH("QUIETO",F20)),ISNUMBER(SEARCH("ESPERANDO",L20)),ISNUMBER(SEARCH("ESPERANDO",F20))),"Sin respuesta / Inactivo",IF(OR(ISNUMBER(SEARCH("PENDIENTE",L20)),ISNUMBER(SEARCH("PENDIENTE",F20)),ISNUMBER(SEARCH("COMPROMISO",F20)),ISNUMBER(SEARCH("COMPROMISO",L20)),ISNUMBER(SEARCH("PROCESO",F20)),ISNUMBER(SEARCH("LLAMAR",F20)),ISNUMBER(SEARCH("ABONO",J20)),EXACT(L20,"P"),EXACT(F20,"P")),"Pendiente / Compromiso","Sin gestionar")))) -> Pendiente / Compromiso | P20: =IF(B20="","",IF(E20="","Sin definir",IF(ISNUMBER(SEARCH("ITIL",E20)),"ITIL",IF(ISNUMBER(SEARCH("ISO 27001",E20)),"ISO 27001",IF(ISNUMBER(SEARCH("ISO 42001",E20)),"ISO 42001",IF(ISNUMBER(SEARCH("ISO",E20)),"Otras ISO",IF(ISNUMBER(SEARCH("SCRUM",E20)),"SCRUM",IF(ISNUMBER(SEARCH("BRIDGE",E20)),"BRIDGE",IF(ISNUMBER(SEARCH("CDS",E20)),"CDS",IF(ISNUMBER(SEARCH("TOGAF",E20)),"TOGAF",IF(ISNUMBER(SEARCH("DPI",E20)),"DPI",IF(ISNUMBER(SEARCH("DITS",E20)),"DITS",IF(ISNUMBER(SEARCH("AGILE",E20)),"AGILE",IF(ISNUMBER(SEARCH("Ciberseguridad",E20)),"Ciberseguridad","Otros")))))))))))))) -> CDS | Q20: =IF(B20="","",IF(ISNUMBER(K20),IF(K20<=3,"1-3 meses",IF(K20<=6,"4-6 meses","+6 meses")),"Sin dato registrado")) -> Sin dato registrado | R20: =IF(OR(B20="",M20=""),"",RANK(M20,$M$3:$M$306)+COUNTIF($M$3:M20,M20)-1) -> 2
A21: 21 | B21: Lady Marlene Gallego Montoya | D21: Ximena | E21: CDS | G21: COMPROMISO DE PAGO | H21: X | I21: 1000000 | J21: ABONO 30 ABR | L21: Pendiente X FECHA | M21: =IF(B21="","",IF(ISNUMBER(I21),I21,IFERROR(VALUE(SUBSTITUTE(SUBSTITUTE(I21,"$",""),".","")),0))) -> 1000000 | N21: =IF(B21="","",PROPER(TRIM(D21))) -> Ximena | O21: =IF(B21="","",IF(OR(ISNUMBER(SEARCH("AL DIA",L21)),ISNUMBER(SEARCH("AL DIA",F21))),"Al día",IF(OR(ISNUMBER(SEARCH("QUIETO",L21)),ISNUMBER(SEARCH("QUIETO",F21)),ISNUMBER(SEARCH("ESPERANDO",L21)),ISNUMBER(SEARCH("ESPERANDO",F21))),"Sin respuesta / Inactivo",IF(OR(ISNUMBER(SEARCH("PENDIENTE",L21)),ISNUMBER(SEARCH("PENDIENTE",F21)),ISNUMBER(SEARCH("COMPROMISO",F21)),ISNUMBER(SEARCH("COMPROMISO",L21)),ISNUMBER(SEARCH("PROCESO",F21)),ISNUMBER(SEARCH("LLAMAR",F21)),ISNUMBER(SEARCH("ABONO",J21)),EXACT(L21,"P"),EXACT(F21,"P")),"Pendiente / Compromiso","Sin gestionar")))) -> Pendiente / Compromiso | P21: =IF(B21="","",IF(E21="","Sin definir",IF(ISNUMBER(SEARCH("ITIL",E21)),"ITIL",IF(ISNUMBER(SEARCH("ISO 27001",E21)),"ISO 27001",IF(ISNUMBER(SEARCH("ISO 42001",E21)),"ISO 42001",IF(ISNUMBER(SEARCH("ISO",E21)),"Otras ISO",IF(ISNUMBER(SEARCH("SCRUM",E21)),"SCRUM",IF(ISNUMBER(SEARCH("BRIDGE",E21)),"BRIDGE",IF(ISNUMBER(SEARCH("CDS",E21)),"CDS",IF(ISNUMBER(SEARCH("TOGAF",E21)),"TOGAF",IF(ISNUMBER(SEARCH("DPI",E21)),"DPI",IF(ISNUMBER(SEARCH("DITS",E21)),"DITS",IF(ISNUMBER(SEARCH("AGILE",E21)),"AGILE",IF(ISNUMBER(SEARCH("Ciberseguridad",E21)),"Ciberseguridad","Otros")))))))))))))) -> CDS | Q21: =IF(B21="","",IF(ISNUMBER(K21),IF(K21<=3,"1-3 meses",IF(K21<=6,"4-6 meses","+6 meses")),"Sin dato registrado")) -> Sin dato registrado | R21: =IF(OR(B21="",M21=""),"",RANK(M21,$M$3:$M$306)+COUNTIF($M$3:M21,M21)-1) -> 19
A22: 22 | B22: Jhon Edison Puerto Jiménez | D22: Carolina | E22: ITIL 4 Fundamentos | G22: SYNERGY | H22: HASTA 30 MAY | I22: 2050000 | M22: =IF(B22="","",IF(ISNUMBER(I22),I22,IFERROR(VALUE(SUBSTITUTE(SUBSTITUTE(I22,"$",""),".","")),0))) -> 2050000 | N22: =IF(B22="","",PROPER(TRIM(D22))) -> Carolina | O22: =IF(B22="","",IF(OR(ISNUMBER(SEARCH("AL DIA",L22)),ISNUMBER(SEARCH("AL DIA",F22))),"Al día",IF(OR(ISNUMBER(SEARCH("QUIETO",L22)),ISNUMBER(SEARCH("QUIETO",F22)),ISNUMBER(SEARCH("ESPERANDO",L22)),ISNUMBER(SEARCH("ESPERANDO",F22))),"Sin respuesta / Inactivo",IF(OR(ISNUMBER(SEARCH("PENDIENTE",L22)),ISNUMBER(SEARCH("PENDIENTE",F22)),ISNUMBER(SEARCH("COMPROMISO",F22)),ISNUMBER(SEARCH("COMPROMISO",L22)),ISNUMBER(SEARCH("PROCESO",F22)),ISNUMBER(SEARCH("LLAMAR",F22)),ISNUMBER(SEARCH("ABONO",J22)),EXACT(L22,"P"),EXACT(F22,"P")),"Pendiente / Compromiso","Sin gestionar")))) -> Sin gestionar | P22: =IF(B22="","",IF(E22="","Sin definir",IF(ISNUMBER(SEARCH("ITIL",E22)),"ITIL",IF(ISNUMBER(SEARCH("ISO 27001",E22)),"ISO 27001",IF(ISNUMBER(SEARCH("ISO 42001",E22)),"ISO 42001",IF(ISNUMBER(SEARCH("ISO",E22)),"Otras ISO",IF(ISNUMBER(SEARCH("SCRUM",E22)),"SCRUM",IF(ISNUMBER(SEARCH("BRIDGE",E22)),"BRIDGE",IF(ISNUMBER(SEARCH("CDS",E22)),"CDS",IF(ISNUMBER(SEARCH("TOGAF",E22)),"TOGAF",IF(ISNUMBER(SEARCH("DPI",E22)),"DPI",IF(ISNUMBER(SEARCH("DITS",E22)),"DITS",IF(ISNUMBER(SEARCH("AGILE",E22)),"AGILE",IF(ISNUMBER(SEARCH("Ciberseguridad",E22)),"Ciberseguridad","Otros")))))))))))))) -> ITIL | Q22: =IF(B22="","",IF(ISNUMBER(K22),IF(K22<=3,"1-3 meses",IF(K22<=6,"4-6 meses","+6 meses")),"Sin dato registrado")) -> Sin dato registrado | R22: =IF(OR(B22="",M22=""),"",RANK(M22,$M$3:$M$306)+COUNTIF($M$3:M22,M22)-1) -> 3
A23: 23 | B23: JOHAN YESID MORENO SARMIENTO | D23: Carolina | E23: ITIL 4 Fundamentos | G23: P | H23: P | I23: 1850000 | J23: PAGO CON CHEQUE CESANTIAS | L23: AL DIA | M23: =IF(B23="","",IF(ISNUMBER(I23),I23,IFERROR(VALUE(SUBSTITUTE(SUBSTITUTE(I23,"$",""),".","")),0))) -> 1850000 | N23: =IF(B23="","",PROPER(TRIM(D23))) -> Carolina | O23: =IF(B23="","",IF(OR(ISNUMBER(SEARCH("AL DIA",L23)),ISNUMBER(SEARCH("AL DIA",F23))),"Al día",IF(OR(ISNUMBER(SEARCH("QUIETO",L23)),ISNUMBER(SEARCH("QUIETO",F23)),ISNUMBER(SEARCH("ESPERANDO",L23)),ISNUMBER(SEARCH("ESPERANDO",F23))),"Sin respuesta / Inactivo",IF(OR(ISNUMBER(SEARCH("PENDIENTE",L23)),ISNUMBER(SEARCH("PENDIENTE",F23)),ISNUMBER(SEARCH("COMPROMISO",F23)),ISNUMBER(SEARCH("COMPROMISO",L23)),ISNUMBER(SEARCH("PROCESO",F23)),ISNUMBER(SEARCH("LLAMAR",F23)),ISNUMBER(SEARCH("ABONO",J23)),EXACT(L23,"P"),EXACT(F23,"P")),"Pendiente / Compromiso","Sin gestionar")))) -> Al día | P23: =IF(B23="","",IF(E23="","Sin definir",IF(ISNUMBER(SEARCH("ITIL",E23)),"ITIL",IF(ISNUMBER(SEARCH("ISO 27001",E23)),"ISO 27001",IF(ISNUMBER(SEARCH("ISO 42001",E23)),"ISO 42001",IF(ISNUMBER(SEARCH("ISO",E23)),"Otras ISO",IF(ISNUMBER(SEARCH("SCRUM",E23)),"SCRUM",IF(ISNUMBER(SEARCH("BRIDGE",E23)),"BRIDGE",IF(ISNUMBER(SEARCH("CDS",E23)),"CDS",IF(ISNUMBER(SEARCH("TOGAF",E23)),"TOGAF",IF(ISNUMBER(SEARCH("DPI",E23)),"DPI",IF(ISNUMBER(SEARCH("DITS",E23)),"DITS",IF(ISNUMBER(SEARCH("AGILE",E23)),"AGILE",IF(ISNUMBER(SEARCH("Ciberseguridad",E23)),"Ciberseguridad","Otros")))))))))))))) -> ITIL | Q23: =IF(B23="","",IF(ISNUMBER(K23),IF(K23<=3,"1-3 meses",IF(K23<=6,"4-6 meses","+6 meses")),"Sin dato registrado")) -> Sin dato registrado | R23: =IF(OR(B23="",M23=""),"",RANK(M23,$M$3:$M$306)+COUNTIF($M$3:M23,M23)-1) -> 5
A24: 22 | B24: Cesar Augusto Ramirez | D24: Ximena | E24: DPI | G24: P | I24: 1950000 | L24: ESPERANDO CER FUNDAMENTOS | M24: =IF(B24="","",IF(ISNUMBER(I24),I24,IFERROR(VALUE(SUBSTITUTE(SUBSTITUTE(I24,"$",""),".","")),0))) -> 1950000 | N24: =IF(B24="","",PROPER(TRIM(D24))) -> Ximena | O24: =IF(B24="","",IF(OR(ISNUMBER(SEARCH("AL DIA",L24)),ISNUMBER(SEARCH("AL DIA",F24))),"Al día",IF(OR(ISNUMBER(SEARCH("QUIETO",L24)),ISNUMBER(SEARCH("QUIETO",F24)),ISNUMBER(SEARCH("ESPERANDO",L24)),ISNUMBER(SEARCH("ESPERANDO",F24))),"Sin respuesta / Inactivo",IF(OR(ISNUMBER(SEARCH("PENDIENTE",L24)),ISNUMBER(SEARCH("PENDIENTE",F24)),ISNUMBER(SEARCH("COMPROMISO",F24)),ISNUMBER(SEARCH("COMPROMISO",L24)),ISNUMBER(SEARCH("PROCESO",F24)),ISNUMBER(SEARCH("LLAMAR",F24)),ISNUMBER(SEARCH("ABONO",J24)),EXACT(L24,"P"),EXACT(F24,"P")),"Pendiente / Compromiso","Sin gestionar")))) -> Sin respuesta / Inactivo | P24: =IF(B24="","",IF(E24="","Sin definir",IF(ISNUMBER(SEARCH("ITIL",E24)),"ITIL",IF(ISNUMBER(SEARCH("ISO 27001",E24)),"ISO 27001",IF(ISNUMBER(SEARCH("ISO 42001",E24)),"ISO 42001",IF(ISNUMBER(SEARCH("ISO",E24)),"Otras ISO",IF(ISNUMBER(SEARCH("SCRUM",E24)),"SCRUM",IF(ISNUMBER(SEARCH("BRIDGE",E24)),"BRIDGE",IF(ISNUMBER(SEARCH("CDS",E24)),"CDS",IF(ISNUMBER(SEARCH("TOGAF",E24)),"TOGAF",IF(ISNUMBER(SEARCH("DPI",E24)),"DPI",IF(ISNUMBER(SEARCH("DITS",E24)),"DITS",IF(ISNUMBER(SEARCH("AGILE",E24)),"AGILE",IF(ISNUMBER(SEARCH("Ciberseguridad",E24)),"Ciberseguridad","Otros")))))))))))))) -> DPI | Q24: =IF(B24="","",IF(ISNUMBER(K24),IF(K24<=3,"1-3 meses",IF(K24<=6,"4-6 meses","+6 meses")),"Sin dato registrado")) -> Sin dato registrado | R24: =IF(OR(B24="",M24=""),"",RANK(M24,$M$3:$M$306)+COUNTIF($M$3:M24,M24)-1) -> 4
A25: 22 | M25: =IF(B25="","",IF(ISNUMBER(I25),I25,IFERROR(VALUE(SUBSTITUTE(SUBSTITUTE(I25,"$",""),".","")),0))) | N25: =IF(B25="","",PROPER(TRIM(D25))) | O25: =IF(B25="","",IF(OR(ISNUMBER(SEARCH("AL DIA",L25)),ISNUMBER(SEARCH("AL DIA",F25))),"Al día",IF(OR(ISNUMBER(SEARCH("QUIETO",L25)),ISNUMBER(SEARCH("QUIETO",F25)),ISNUMBER(SEARCH("ESPERANDO",L25)),ISNUMBER(SEARCH("ESPERANDO",F25))),"Sin respuesta / Inactivo",IF(OR(ISNUMBER(SEARCH("PENDIENTE",L25)),ISNUMBER(SEARCH("PENDIENTE",F25)),ISNUMBER(SEARCH("COMPROMISO",F25)),ISNUMBER(SEARCH("COMPROMISO",L25)),ISNUMBER(SEARCH("PROCESO",F25)),ISNUMBER(SEARCH("LLAMAR",F25)),ISNUMBER(SEARCH("ABONO",J25)),EXACT(L25,"P"),EXACT(F25,"P")),"Pendiente / Compromiso","Sin gestionar")))) | P25: =IF(B25="","",IF(E25="","Sin definir",IF(ISNUMBER(SEARCH("ITIL",E25)),"ITIL",IF(ISNUMBER(SEARCH("ISO 27001",E25)),"ISO 27001",IF(ISNUMBER(SEARCH("ISO 42001",E25)),"ISO 42001",IF(ISNUMBER(SEARCH("ISO",E25)),"Otras ISO",IF(ISNUMBER(SEARCH("SCRUM",E25)),"SCRUM",IF(ISNUMBER(SEARCH("BRIDGE",E25)),"BRIDGE",IF(ISNUMBER(SEARCH("CDS",E25)),"CDS",IF(ISNUMBER(SEARCH("TOGAF",E25)),"TOGAF",IF(ISNUMBER(SEARCH("DPI",E25)),"DPI",IF(ISNUMBER(SEARCH("DITS",E25)),"DITS",IF(ISNUMBER(SEARCH("AGILE",E25)),"AGILE",IF(ISNUMBER(SEARCH("Ciberseguridad",E25)),"Ciberseguridad","Otros")))))))))))))) | Q25: =IF(B25="","",IF(ISNUMBER(K25),IF(K25<=3,"1-3 meses",IF(K25<=6,"4-6 meses","+6 meses")),"Sin dato registrado")) | R25: =IF(OR(B25="",M25=""),"",RANK(M25,$M$3:$M$306)+COUNTIF($M$3:M25,M25)-1)
A26: 22 | M26: =IF(B26="","",IF(ISNUMBER(I26),I26,IFERROR(VALUE(SUBSTITUTE(SUBSTITUTE(I26,"$",""),".","")),0))) | N26: =IF(B26="","",PROPER(TRIM(D26))) | O26: =IF(B26="","",IF(OR(ISNUMBER(SEARCH("AL DIA",L26)),ISNUMBER(SEARCH("AL DIA",F26))),"Al día",IF(OR(ISNUMBER(SEARCH("QUIETO",L26)),ISNUMBER(SEARCH("QUIETO",F26)),ISNUMBER(SEARCH("ESPERANDO",L26)),ISNUMBER(SEARCH("ESPERANDO",F26))),"Sin respuesta / Inactivo",IF(OR(ISNUMBER(SEARCH("PENDIENTE",L26)),ISNUMBER(SEARCH("PENDIENTE",F26)),ISNUMBER(SEARCH("COMPROMISO",F26)),ISNUMBER(SEARCH("COMPROMISO",L26)),ISNUMBER(SEARCH("PROCESO",F26)),ISNUMBER(SEARCH("LLAMAR",F26)),ISNUMBER(SEARCH("ABONO",J26)),EXACT(L26,"P"),EXACT(F26,"P")),"Pendiente / Compromiso","Sin gestionar")))) | P26: =IF(B26="","",IF(E26="","Sin definir",IF(ISNUMBER(SEARCH("ITIL",E26)),"ITIL",IF(ISNUMBER(SEARCH("ISO 27001",E26)),"ISO 27001",IF(ISNUMBER(SEARCH("ISO 42001",E26)),"ISO 42001",IF(ISNUMBER(SEARCH("ISO",E26)),"Otras ISO",IF(ISNUMBER(SEARCH("SCRUM",E26)),"SCRUM",IF(ISNUMBER(SEARCH("BRIDGE",E26)),"BRIDGE",IF(ISNUMBER(SEARCH("CDS",E26)),"CDS",IF(ISNUMBER(SEARCH("TOGAF",E26)),"TOGAF",IF(ISNUMBER(SEARCH("DPI",E26)),"DPI",IF(ISNUMBER(SEARCH("DITS",E26)),"DITS",IF(ISNUMBER(SEARCH("AGILE",E26)),"AGILE",IF(ISNUMBER(SEARCH("Ciberseguridad",E26)),"Ciberseguridad","Otros")))))))))))))) | Q26: =IF(B26="","",IF(ISNUMBER(K26),IF(K26<=3,"1-3 meses",IF(K26<=6,"4-6 meses","+6 meses")),"Sin dato registrado")) | R26: =IF(OR(B26="",M26=""),"",RANK(M26,$M$3:$M$306)+COUNTIF($M$3:M26,M26)-1)
A27: 22 | M27: =IF(B27="","",IF(ISNUMBER(I27),I27,IFERROR(VALUE(SUBSTITUTE(SUBSTITUTE(I27,"$",""),".","")),0))) | N27: =IF(B27="","",PROPER(TRIM(D27))) | O27: =IF(B27="","",IF(OR(ISNUMBER(SEARCH("AL DIA",L27)),ISNUMBER(SEARCH("AL DIA",F27))),"Al día",IF(OR(ISNUMBER(SEARCH("QUIETO",L27)),ISNUMBER(SEARCH("QUIETO",F27)),ISNUMBER(SEARCH("ESPERANDO",L27)),ISNUMBER(SEARCH("ESPERANDO",F27))),"Sin respuesta / Inactivo",IF(OR(ISNUMBER(SEARCH("PENDIENTE",L27)),ISNUMBER(SEARCH("PENDIENTE",F27)),ISNUMBER(SEARCH("COMPROMISO",F27)),ISNUMBER(SEARCH("COMPROMISO",L27)),ISNUMBER(SEARCH("PROCESO",F27)),ISNUMBER(SEARCH("LLAMAR",F27)),ISNUMBER(SEARCH("ABONO",J27)),EXACT(L27,"P"),EXACT(F27,"P")),"Pendiente / Compromiso","Sin gestionar")))) | P27: =IF(B27="","",IF(E27="","Sin definir",IF(ISNUMBER(SEARCH("ITIL",E27)),"ITIL",IF(ISNUMBER(SEARCH("ISO 27001",E27)),"ISO 27001",IF(ISNUMBER(SEARCH("ISO 42001",E27)),"ISO 42001",IF(ISNUMBER(SEARCH("ISO",E27)),"Otras ISO",IF(ISNUMBER(SEARCH("SCRUM",E27)),"SCRUM",IF(ISNUMBER(SEARCH("BRIDGE",E27)),"BRIDGE",IF(ISNUMBER(SEARCH("CDS",E27)),"CDS",IF(ISNUMBER(SEARCH("TOGAF",E27)),"TOGAF",IF(ISNUMBER(SEARCH("DPI",E27)),"DPI",IF(ISNUMBER(SEARCH("DITS",E27)),"DITS",IF(ISNUMBER(SEARCH("AGILE",E27)),"AGILE",IF(ISNUMBER(SEARCH("Ciberseguridad",E27)),"Ciberseguridad","Otros")))))))))))))) | Q27: =IF(B27="","",IF(ISNUMBER(K27),IF(K27<=3,"1-3 meses",IF(K27<=6,"4-6 meses","+6 meses")),"Sin dato registrado")) | R27: =IF(OR(B27="",M27=""),"",RANK(M27,$M$3:$M$306)+COUNTIF($M$3:M27,M27)-1)
A28: 22 | M28: =IF(B28="","",IF(ISNUMBER(I28),I28,IFERROR(VALUE(SUBSTITUTE(SUBSTITUTE(I28,"$",""),".","")),0))) | N28: =IF(B28="","",PROPER(TRIM(D28))) | O28: =IF(B28="","",IF(OR(ISNUMBER(SEARCH("AL DIA",L28)),ISNUMBER(SEARCH("AL DIA",F28))),"Al día",IF(OR(ISNUMBER(SEARCH("QUIETO",L28)),ISNUMBER(SEARCH("QUIETO",F28)),ISNUMBER(SEARCH("ESPERANDO",L28)),ISNUMBER(SEARCH("ESPERANDO",F28))),"Sin respuesta / Inactivo",IF(OR(ISNUMBER(SEARCH("PENDIENTE",L28)),ISNUMBER(SEARCH("PENDIENTE",F28)),ISNUMBER(SEARCH("COMPROMISO",F28)),ISNUMBER(SEARCH("COMPROMISO",L28)),ISNUMBER(SEARCH("PROCESO",F28)),ISNUMBER(SEARCH("LLAMAR",F28)),ISNUMBER(SEARCH("ABONO",J28)),EXACT(L28,"P"),EXACT(F28,"P")),"Pendiente / Compromiso","Sin gestionar")))) | P28: =IF(B28="","",IF(E28="","Sin definir",IF(ISNUMBER(SEARCH("ITIL",E28)),"ITIL",IF(ISNUMBER(SEARCH("ISO 27001",E28)),"ISO 27001",IF(ISNUMBER(SEARCH("ISO 42001",E28)),"ISO 42001",IF(ISNUMBER(SEARCH("ISO",E28)),"Otras ISO",IF(ISNUMBER(SEARCH("SCRUM",E28)),"SCRUM",IF(ISNUMBER(SEARCH("BRIDGE",E28)),"BRIDGE",IF(ISNUMBER(SEARCH("CDS",E28)),"CDS",IF(ISNUMBER(SEARCH("TOGAF",E28)),"TOGAF",IF(ISNUMBER(SEARCH("DPI",E28)),"DPI",IF(ISNUMBER(SEARCH("DITS",E28)),"DITS",IF(ISNUMBER(SEARCH("AGILE",E28)),"AGILE",IF(ISNUMBER(SEARCH("Ciberseguridad",E28)),"Ciberseguridad","Otros")))))))))))))) | Q28: =IF(B28="","",IF(ISNUMBER(K28),IF(K28<=3,"1-3 meses",IF(K28<=6,"4-6 meses","+6 meses")),"Sin dato registrado")) | R28: =IF(OR(B28="",M28=""),"",RANK(M28,$M$3:$M$306)+COUNTIF($M$3:M28,M28)-1)
A29: 22 | M29: =IF(B29="","",IF(ISNUMBER(I29),I29,IFERROR(VALUE(SUBSTITUTE(SUBSTITUTE(I29,"$",""),".","")),0))) | N29: =IF(B29="","",PROPER(TRIM(D29))) | O29: =IF(B29="","",IF(OR(ISNUMBER(SEARCH("AL DIA",L29)),ISNUMBER(SEARCH("AL DIA",F29))),"Al día",IF(OR(ISNUMBER(SEARCH("QUIETO",L29)),ISNUMBER(SEARCH("QUIETO",F29)),ISNUMBER(SEARCH("ESPERANDO",L29)),ISNUMBER(SEARCH("ESPERANDO",F29))),"Sin respuesta / Inactivo",IF(OR(ISNUMBER(SEARCH("PENDIENTE",L29)),ISNUMBER(SEARCH("PENDIENTE",F29)),ISNUMBER(SEARCH("COMPROMISO",F29)),ISNUMBER(SEARCH("COMPROMISO",L29)),ISNUMBER(SEARCH("PROCESO",F29)),ISNUMBER(SEARCH("LLAMAR",F29)),ISNUMBER(SEARCH("ABONO",J29)),EXACT(L29,"P"),EXACT(F29,"P")),"Pendiente / Compromiso","Sin gestionar")))) | P29: =IF(B29="","",IF(E29="","Sin definir",IF(ISNUMBER(SEARCH("ITIL",E29)),"ITIL",IF(ISNUMBER(SEARCH("ISO 27001",E29)),"ISO 27001",IF(ISNUMBER(SEARCH("ISO 42001",E29)),"ISO 42001",IF(ISNUMBER(SEARCH("ISO",E29)),"Otras ISO",IF(ISNUMBER(SEARCH("SCRUM",E29)),"SCRUM",IF(ISNUMBER(SEARCH("BRIDGE",E29)),"BRIDGE",IF(ISNUMBER(SEARCH("CDS",E29)),"CDS",IF(ISNUMBER(SEARCH("TOGAF",E29)),"TOGAF",IF(ISNUMBER(SEARCH("DPI",E29)),"DPI",IF(ISNUMBER(SEARCH("DITS",E29)),"DITS",IF(ISNUMBER(SEARCH("AGILE",E29)),"AGILE",IF(ISNUMBER(SEARCH("Ciberseguridad",E29)),"Ciberseguridad","Otros")))))))))))))) | Q29: =IF(B29="","",IF(ISNUMBER(K29),IF(K29<=3,"1-3 meses",IF(K29<=6,"4-6 meses","+6 meses")),"Sin dato registrado")) | R29: =IF(OR(B29="",M29=""),"",RANK(M29,$M$3:$M$306)+COUNTIF($M$3:M29,M29)-1)
A30: 22 | M30: =IF(B30="","",IF(ISNUMBER(I30),I30,IFERROR(VALUE(SUBSTITUTE(SUBSTITUTE(I30,"$",""),".","")),0))) | N30: =IF(B30="","",PROPER(TRIM(D30))) | O30: =IF(B30="","",IF(OR(ISNUMBER(SEARCH("AL DIA",L30)),ISNUMBER(SEARCH("AL DIA",F30))),"Al día",IF(OR(ISNUMBER(SEARCH("QUIETO",L30)),ISNUMBER(SEARCH("QUIETO",F30)),ISNUMBER(SEARCH("ESPERANDO",L30)),ISNUMBER(SEARCH("ESPERANDO",F30))),"Sin respuesta / Inactivo",IF(OR(ISNUMBER(SEARCH("PENDIENTE",L30)),ISNUMBER(SEARCH("PENDIENTE",F30)),ISNUMBER(SEARCH("COMPROMISO",F30)),ISNUMBER(SEARCH("COMPROMISO",L30)),ISNUMBER(SEARCH("PROCESO",F30)),ISNUMBER(SEARCH("LLAMAR",F30)),ISNUMBER(SEARCH("ABONO",J30)),EXACT(L30,"P"),EXACT(F30,"P")),"Pendiente / Compromiso","Sin gestionar")))) | P30: =IF(B30="","",IF(E30="","Sin definir",IF(ISNUMBER(SEARCH("ITIL",E30)),"ITIL",IF(ISNUMBER(SEARCH("ISO 27001",E30)),"ISO 27001",IF(ISNUMBER(SEARCH("ISO 42001",E30)),"ISO 42001",IF(ISNUMBER(SEARCH("ISO",E30)),"Otras ISO",IF(ISNUMBER(SEARCH("SCRUM",E30)),"SCRUM",IF(ISNUMBER(SEARCH("BRIDGE",E30)),"BRIDGE",IF(ISNUMBER(SEARCH("CDS",E30)),"CDS",IF(ISNUMBER(SEARCH("TOGAF",E30)),"TOGAF",IF(ISNUMBER(SEARCH("DPI",E30)),"DPI",IF(ISNUMBER(SEARCH("DITS",E30)),"DITS",IF(ISNUMBER(SEARCH("AGILE",E30)),"AGILE",IF(ISNUMBER(SEARCH("Ciberseguridad",E30)),"Ciberseguridad","Otros")))))))))))))) | Q30: =IF(B30="","",IF(ISNUMBER(K30),IF(K30<=3,"1-3 meses",IF(K30<=6,"4-6 meses","+6 meses")),"Sin dato registrado")) | R30: =IF(OR(B30="",M30=""),"",RANK(M30,$M$3:$M$306)+COUNTIF($M$3:M30,M30)-1)
A31: 22 | M31: =IF(B31="","",IF(ISNUMBER(I31),I31,IFERROR(VALUE(SUBSTITUTE(SUBSTITUTE(I31,"$",""),".","")),0))) | N31: =IF(B31="","",PROPER(TRIM(D31))) | O31: =IF(B31="","",IF(OR(ISNUMBER(SEARCH("AL DIA",L31)),ISNUMBER(SEARCH("AL DIA",F31))),"Al día",IF(OR(ISNUMBER(SEARCH("QUIETO",L31)),ISNUMBER(SEARCH("QUIETO",F31)),ISNUMBER(SEARCH("ESPERANDO",L31)),ISNUMBER(SEARCH("ESPERANDO",F31))),"Sin respuesta / Inactivo",IF(OR(ISNUMBER(SEARCH("PENDIENTE",L31)),ISNUMBER(SEARCH("PENDIENTE",F31)),ISNUMBER(SEARCH("COMPROMISO",F31)),ISNUMBER(SEARCH("COMPROMISO",L31)),ISNUMBER(SEARCH("PROCESO",F31)),ISNUMBER(SEARCH("LLAMAR",F31)),ISNUMBER(SEARCH("ABONO",J31)),EXACT(L31,"P"),EXACT(F31,"P")),"Pendiente / Compromiso","Sin gestionar")))) | P31: =IF(B31="","",IF(E31="","Sin definir",IF(ISNUMBER(SEARCH("ITIL",E31)),"ITIL",IF(ISNUMBER(SEARCH("ISO 27001",E31)),"ISO 27001",IF(ISNUMBER(SEARCH("ISO 42001",E31)),"ISO 42001",IF(ISNUMBER(SEARCH("ISO",E31)),"Otras ISO",IF(ISNUMBER(SEARCH("SCRUM",E31)),"SCRUM",IF(ISNUMBER(SEARCH("BRIDGE",E31)),"BRIDGE",IF(ISNUMBER(SEARCH("CDS",E31)),"CDS",IF(ISNUMBER(SEARCH("TOGAF",E31)),"TOGAF",IF(ISNUMBER(SEARCH("DPI",E31)),"DPI",IF(ISNUMBER(SEARCH("DITS",E31)),"DITS",IF(ISNUMBER(SEARCH("AGILE",E31)),"AGILE",IF(ISNUMBER(SEARCH("Ciberseguridad",E31)),"Ciberseguridad","Otros")))))))))))))) | Q31: =IF(B31="","",IF(ISNUMBER(K31),IF(K31<=3,"1-3 meses",IF(K31<=6,"4-6 meses","+6 meses")),"Sin dato registrado")) | R31: =IF(OR(B31="",M31=""),"",RANK(M31,$M$3:$M$306)+COUNTIF($M$3:M31,M31)-1)
A32: 22 | M32: =IF(B32="","",IF(ISNUMBER(I32),I32,IFERROR(VALUE(SUBSTITUTE(SUBSTITUTE(I32,"$",""),".","")),0))) | N32: =IF(B32="","",PROPER(TRIM(D32))) | O32: =IF(B32="","",IF(OR(ISNUMBER(SEARCH("AL DIA",L32)),ISNUMBER(SEARCH("AL DIA",F32))),"Al día",IF(OR(ISNUMBER(SEARCH("QUIETO",L32)),ISNUMBER(SEARCH("QUIETO",F32)),ISNUMBER(SEARCH("ESPERANDO",L32)),ISNUMBER(SEARCH("ESPERANDO",F32))),"Sin respuesta / Inactivo",IF(OR(ISNUMBER(SEARCH("PENDIENTE",L32)),ISNUMBER(SEARCH("PENDIENTE",F32)),ISNUMBER(SEARCH("COMPROMISO",F32)),ISNUMBER(SEARCH("COMPROMISO",L32)),ISNUMBER(SEARCH("PROCESO",F32)),ISNUMBER(SEARCH("LLAMAR",F32)),ISNUMBER(SEARCH("ABONO",J32)),EXACT(L32,"P"),EXACT(F32,"P")),"Pendiente / Compromiso","Sin gestionar")))) | P32: =IF(B32="","",IF(E32="","Sin definir",IF(ISNUMBER(SEARCH("ITIL",E32)),"ITIL",IF(ISNUMBER(SEARCH("ISO 27001",E32)),"ISO 27001",IF(ISNUMBER(SEARCH("ISO 42001",E32)),"ISO 42001",IF(ISNUMBER(SEARCH("ISO",E32)),"Otras ISO",IF(ISNUMBER(SEARCH("SCRUM",E32)),"SCRUM",IF(ISNUMBER(SEARCH("BRIDGE",E32)),"BRIDGE",IF(ISNUMBER(SEARCH("CDS",E32)),"CDS",IF(ISNUMBER(SEARCH("TOGAF",E32)),"TOGAF",IF(ISNUMBER(SEARCH("DPI",E32)),"DPI",IF(ISNUMBER(SEARCH("DITS",E32)),"DITS",IF(ISNUMBER(SEARCH("AGILE",E32)),"AGILE",IF(ISNUMBER(SEARCH("Ciberseguridad",E32)),"Ciberseguridad","Otros")))))))))))))) | Q32: =IF(B32="","",IF(ISNUMBER(K32),IF(K32<=3,"1-3 meses",IF(K32<=6,"4-6 meses","+6 meses")),"Sin dato registrado")) | R32: =IF(OR(B32="",M32=""),"",RANK(M32,$M$3:$M$306)+COUNTIF($M$3:M32,M32)-1)
A33: 22 | M33: =IF(B33="","",IF(ISNUMBER(I33),I33,IFERROR(VALUE(SUBSTITUTE(SUBSTITUTE(I33,"$",""),".","")),0))) | N33: =IF(B33="","",PROPER(TRIM(D33))) | O33: =IF(B33="","",IF(OR(ISNUMBER(SEARCH("AL DIA",L33)),ISNUMBER(SEARCH("AL DIA",F33))),"Al día",IF(OR(ISNUMBER(SEARCH("QUIETO",L33)),ISNUMBER(SEARCH("QUIETO",F33)),ISNUMBER(SEARCH("ESPERANDO",L33)),ISNUMBER(SEARCH("ESPERANDO",F33))),"Sin respuesta / Inactivo",IF(OR(ISNUMBER(SEARCH("PENDIENTE",L33)),ISNUMBER(SEARCH("PENDIENTE",F33)),ISNUMBER(SEARCH("COMPROMISO",F33)),ISNUMBER(SEARCH("COMPROMISO",L33)),ISNUMBER(SEARCH("PROCESO",F33)),ISNUMBER(SEARCH("LLAMAR",F33)),ISNUMBER(SEARCH("ABONO",J33)),EXACT(L33,"P"),EXACT(F33,"P")),"Pendiente / Compromiso","Sin gestionar")))) | P33: =IF(B33="","",IF(E33="","Sin definir",IF(ISNUMBER(SEARCH("ITIL",E33)),"ITIL",IF(ISNUMBER(SEARCH("ISO 27001",E33)),"ISO 27001",IF(ISNUMBER(SEARCH("ISO 42001",E33)),"ISO 42001",IF(ISNUMBER(SEARCH("ISO",E33)),"Otras ISO",IF(ISNUMBER(SEARCH("SCRUM",E33)),"SCRUM",IF(ISNUMBER(SEARCH("BRIDGE",E33)),"BRIDGE",IF(ISNUMBER(SEARCH("CDS",E33)),"CDS",IF(ISNUMBER(SEARCH("TOGAF",E33)),"TOGAF",IF(ISNUMBER(SEARCH("DPI",E33)),"DPI",IF(ISNUMBER(SEARCH("DITS",E33)),"DITS",IF(ISNUMBER(SEARCH("AGILE",E33)),"AGILE",IF(ISNUMBER(SEARCH("Ciberseguridad",E33)),"Ciberseguridad","Otros")))))))))))))) | Q33: =IF(B33="","",IF(ISNUMBER(K33),IF(K33<=3,"1-3 meses",IF(K33<=6,"4-6 meses","+6 meses")),"Sin dato registrado")) | R33: =IF(OR(B33="",M33=""),"",RANK(M33,$M$3:$M$306)+COUNTIF($M$3:M33,M33)-1)
A34: 22 | M34: =IF(B34="","",IF(ISNUMBER(I34),I34,IFERROR(VALUE(SUBSTITUTE(SUBSTITUTE(I34,"$",""),".","")),0))) | N34: =IF(B34="","",PROPER(TRIM(D34))) | O34: =IF(B34="","",IF(OR(ISNUMBER(SEARCH("AL DIA",L34)),ISNUMBER(SEARCH("AL DIA",F34))),"Al día",IF(OR(ISNUMBER(SEARCH("QUIETO",L34)),ISNUMBER(SEARCH("QUIETO",F34)),ISNUMBER(SEARCH("ESPERANDO",L34)),ISNUMBER(SEARCH("ESPERANDO",F34))),"Sin respuesta / Inactivo",IF(OR(ISNUMBER(SEARCH("PENDIENTE",L34)),ISNUMBER(SEARCH("PENDIENTE",F34)),ISNUMBER(SEARCH("COMPROMISO",F34)),ISNUMBER(SEARCH("COMPROMISO",L34)),ISNUMBER(SEARCH("PROCESO",F34)),ISNUMBER(SEARCH("LLAMAR",F34)),ISNUMBER(SEARCH("ABONO",J34)),EXACT(L34,"P"),EXACT(F34,"P")),"Pendiente / Compromiso","Sin gestionar")))) | P34: =IF(B34="","",IF(E34="","Sin definir",IF(ISNUMBER(SEARCH("ITIL",E34)),"ITIL",IF(ISNUMBER(SEARCH("ISO 27001",E34)),"ISO 27001",IF(ISNUMBER(SEARCH("ISO 42001",E34)),"ISO 42001",IF(ISNUMBER(SEARCH("ISO",E34)),"Otras ISO",IF(ISNUMBER(SEARCH("SCRUM",E34)),"SCRUM",IF(ISNUMBER(SEARCH("BRIDGE",E34)),"BRIDGE",IF(ISNUMBER(SEARCH("CDS",E34)),"CDS",IF(ISNUMBER(SEARCH("TOGAF",E34)),"TOGAF",IF(ISNUMBER(SEARCH("DPI",E34)),"DPI",IF(ISNUMBER(SEARCH("DITS",E34)),"DITS",IF(ISNUMBER(SEARCH("AGILE",E34)),"AGILE",IF(ISNUMBER(SEARCH("Ciberseguridad",E34)),"Ciberseguridad","Otros")))))))))))))) | Q34: =IF(B34="","",IF(ISNUMBER(K34),IF(K34<=3,"1-3 meses",IF(K34<=6,"4-6 meses","+6 meses")),"Sin dato registrado")) | R34: =IF(OR(B34="",M34=""),"",RANK(M34,$M$3:$M$306)+COUNTIF($M$3:M34,M34)-1)
A35: 22 | M35: =IF(B35="","",IF(ISNUMBER(I35),I35,IFERROR(VALUE(SUBSTITUTE(SUBSTITUTE(I35,"$",""),".","")),0))) | N35: =IF(B35="","",PROPER(TRIM(D35))) | O35: =IF(B35="","",IF(OR(ISNUMBER(SEARCH("AL DIA",L35)),ISNUMBER(SEARCH("AL DIA",F35))),"Al día",IF(OR(ISNUMBER(SEARCH("QUIETO",L35)),ISNUMBER(SEARCH("QUIETO",F35)),ISNUMBER(SEARCH("ESPERANDO",L35)),ISNUMBER(SEARCH("ESPERANDO",F35))),"Sin respuesta / Inactivo",IF(OR(ISNUMBER(SEARCH("PENDIENTE",L35)),ISNUMBER(SEARCH("PENDIENTE",F35)),ISNUMBER(SEARCH("COMPROMISO",F35)),ISNUMBER(SEARCH("COMPROMISO",L35)),ISNUMBER(SEARCH("PROCESO",F35)),ISNUMBER(SEARCH("LLAMAR",F35)),ISNUMBER(SEARCH("ABONO",J35)),EXACT(L35,"P"),EXACT(F35,"P")),"Pendiente / Compromiso","Sin gestionar")))) | P35: =IF(B35="","",IF(E35="","Sin definir",IF(ISNUMBER(SEARCH("ITIL",E35)),"ITIL",IF(ISNUMBER(SEARCH("ISO 27001",E35)),"ISO 27001",IF(ISNUMBER(SEARCH("ISO 42001",E35)),"ISO 42001",IF(ISNUMBER(SEARCH("ISO",E35)),"Otras ISO",IF(ISNUMBER(SEARCH("SCRUM",E35)),"SCRUM",IF(ISNUMBER(SEARCH("BRIDGE",E35)),"BRIDGE",IF(ISNUMBER(SEARCH("CDS",E35)),"CDS",IF(ISNUMBER(SEARCH("TOGAF",E35)),"TOGAF",IF(ISNUMBER(SEARCH("DPI",E35)),"DPI",IF(ISNUMBER(SEARCH("DITS",E35)),"DITS",IF(ISNUMBER(SEARCH("AGILE",E35)),"AGILE",IF(ISNUMBER(SEARCH("Ciberseguridad",E35)),"Ciberseguridad","Otros")))))))))))))) | Q35: =IF(B35="","",IF(ISNUMBER(K35),IF(K35<=3,"1-3 meses",IF(K35<=6,"4-6 meses","+6 meses")),"Sin dato registrado")) | R35: =IF(OR(B35="",M35=""),"",RANK(M35,$M$3:$M$306)+COUNTIF($M$3:M35,M35)-1)
A36: 22 | M36: =IF(B36="","",IF(ISNUMBER(I36),I36,IFERROR(VALUE(SUBSTITUTE(SUBSTITUTE(I36,"$",""),".","")),0))) | N36: =IF(B36="","",PROPER(TRIM(D36))) | O36: =IF(B36="","",IF(OR(ISNUMBER(SEARCH("AL DIA",L36)),ISNUMBER(SEARCH("AL DIA",F36))),"Al día",IF(OR(ISNUMBER(SEARCH("QUIETO",L36)),ISNUMBER(SEARCH("QUIETO",F36)),ISNUMBER(SEARCH("ESPERANDO",L36)),ISNUMBER(SEARCH("ESPERANDO",F36))),"Sin respuesta / Inactivo",IF(OR(ISNUMBER(SEARCH("PENDIENTE",L36)),ISNUMBER(SEARCH("PENDIENTE",F36)),ISNUMBER(SEARCH("COMPROMISO",F36)),ISNUMBER(SEARCH("COMPROMISO",L36)),ISNUMBER(SEARCH("PROCESO",F36)),ISNUMBER(SEARCH("LLAMAR",F36)),ISNUMBER(SEARCH("ABONO",J36)),EXACT(L36,"P"),EXACT(F36,"P")),"Pendiente / Compromiso","Sin gestionar")))) | P36: =IF(B36="","",IF(E36="","Sin definir",IF(ISNUMBER(SEARCH("ITIL",E36)),"ITIL",IF(ISNUMBER(SEARCH("ISO 27001",E36)),"ISO 27001",IF(ISNUMBER(SEARCH("ISO 42001",E36)),"ISO 42001",IF(ISNUMBER(SEARCH("ISO",E36)),"Otras ISO",IF(ISNUMBER(SEARCH("SCRUM",E36)),"SCRUM",IF(ISNUMBER(SEARCH("BRIDGE",E36)),"BRIDGE",IF(ISNUMBER(SEARCH("CDS",E36)),"CDS",IF(ISNUMBER(SEARCH("TOGAF",E36)),"TOGAF",IF(ISNUMBER(SEARCH("DPI",E36)),"DPI",IF(ISNUMBER(SEARCH("DITS",E36)),"DITS",IF(ISNUMBER(SEARCH("AGILE",E36)),"AGILE",IF(ISNUMBER(SEARCH("Ciberseguridad",E36)),"Ciberseguridad","Otros")))))))))))))) | Q36: =IF(B36="","",IF(ISNUMBER(K36),IF(K36<=3,"1-3 meses",IF(K36<=6,"4-6 meses","+6 meses")),"Sin dato registrado")) | R36: =IF(OR(B36="",M36=""),"",RANK(M36,$M$3:$M$306)+COUNTIF($M$3:M36,M36)-1)
... A206: 22 | M206: =IF(B206="","",IF(ISNUMBER(I206),I206,IFERROR(VALUE(SUBSTITUTE(SUBSTITUTE(I206,"$",""),".","")),0))) | N206: =IF(B206="","",PROPER(TRIM(D206))) | O206: =IF(B206="","",IF(OR(ISNUMBER(SEARCH("AL DIA",L206)),ISNUMBER(SEARCH("AL DIA",F206))),"Al día",IF(OR(ISNUMBER(SEARCH("QUIETO",L206)),ISNUMBER(SEARCH("QUIETO",F206)),ISNUMBER(SEARCH("ESPERANDO",L206)),ISNUMBER(SEARCH("ESPERANDO",F206))),"Sin respuesta / Inactivo",IF(OR(ISNUMBER(SEARCH("PENDIENTE",L206)),ISNUMBER(SEARCH("PENDIENTE",F206)),ISNUMBER(SEARCH("COMPROMISO",F206)),ISNUMBER(SEARCH("COMPROMISO",L206)),ISNUMBER(SEARCH("PROCESO",F206)),ISNUMBER(SEARCH("LLAMAR",F206)),ISNUMBER(SEARCH("ABONO",J206)),EXACT(L206,"P"),EXACT(F206,"P")),"Pendiente / Compromiso","Sin gestionar")))) | P206: =IF(B206="","",IF(E206="","Sin definir",IF(ISNUMBER(SEARCH("ITIL",E206)),"ITIL",IF(ISNUMBER(SEARCH("ISO 27001",E206)),"ISO 27001",IF(ISNUMBER(SEARCH("ISO 42001",E206)),"ISO 42001",IF(ISNUMBER(SEARCH("ISO",E206)),"Otras ISO",IF(ISNUMBER(SEARCH("SCRUM",E206)),"SCRUM",IF(ISNUMBER(SEARCH("BRIDGE",E206)),"BRIDGE",IF(ISNUMBER(SEARCH("CDS",E206)),"CDS",IF(ISNUMBER(SEARCH("TOGAF",E206)),"TOGAF",IF(ISNUMBER(SEARCH("DPI",E206)),"DPI",IF(ISNUMBER(SEARCH("DITS",E206)),"DITS",IF(ISNUMBER(SEARCH("AGILE",E206)),"AGILE",IF(ISNUMBER(SEARCH("Ciberseguridad",E206)),"Ciberseguridad","Otros")))))))))))))) | Q206: =IF(B206="","",IF(ISNUMBER(K206),IF(K206<=3,"1-3 meses",IF(K206<=6,"4-6 meses","+6 meses")),"Sin dato registrado")) | R206: =IF(OR(B206="",M206=""),"",RANK(M206,$M$3:$M$306)+COUNTIF($M$3:M206,M206)-1)
A207: 24 | B207: Miguel Ángel zambrano Sánchez | D207: Ximena | E207: ITIL 5 Fundamentos | F207: Curso y examen | G207: P | H207: X | I207: 850000 | J207: P | L207: P | M207: =IF(B207="","",IF(ISNUMBER(I207),I207,IFERROR(VALUE(SUBSTITUTE(SUBSTITUTE(I207,"$",""),".","")),0))) -> 850000 | N207: =IF(B207="","",PROPER(TRIM(D207))) -> Ximena | O207: =IF(B207="","",IF(OR(ISNUMBER(SEARCH("AL DIA",L207)),ISNUMBER(SEARCH("AL DIA",F207))),"Al día",IF(OR(ISNUMBER(SEARCH("QUIETO",L207)),ISNUMBER(SEARCH("QUIETO",F207)),ISNUMBER(SEARCH("ESPERANDO",L207)),ISNUMBER(SEARCH("ESPERANDO",F207))),"Sin respuesta / Inactivo",IF(OR(ISNUMBER(SEARCH("PENDIENTE",L207)),ISNUMBER(SEARCH("PENDIENTE",F207)),ISNUMBER(SEARCH("COMPROMISO",F207)),ISNUMBER(SEARCH("COMPROMISO",L207)),ISNUMBER(SEARCH("PROCESO",F207)),ISNUMBER(SEARCH("LLAMAR",F207)),ISNUMBER(SEARCH("ABONO",J207)),EXACT(L207,"P"),EXACT(F207,"P")),"Pendiente / Compromiso","Sin gestionar")))) -> Pendiente / Compromiso | P207: =IF(B207="","",IF(E207="","Sin definir",IF(ISNUMBER(SEARCH("ITIL",E207)),"ITIL",IF(ISNUMBER(SEARCH("ISO 27001",E207)),"ISO 27001",IF(ISNUMBER(SEARCH("ISO 42001",E207)),"ISO 42001",IF(ISNUMBER(SEARCH("ISO",E207)),"Otras ISO",IF(ISNUMBER(SEARCH("SCRUM",E207)),"SCRUM",IF(ISNUMBER(SEARCH("BRIDGE",E207)),"BRIDGE",IF(ISNUMBER(SEARCH("CDS",E207)),"CDS",IF(ISNUMBER(SEARCH("TOGAF",E207)),"TOGAF",IF(ISNUMBER(SEARCH("DPI",E207)),"DPI",IF(ISNUMBER(SEARCH("DITS",E207)),"DITS",IF(ISNUMBER(SEARCH("AGILE",E207)),"AGILE",IF(ISNUMBER(SEARCH("Ciberseguridad",E207)),"Ciberseguridad","Otros")))))))))))))) -> ITIL | Q207: =IF(B207="","",IF(ISNUMBER(K207),IF(K207<=3,"1-3 meses",IF(K207<=6,"4-6 meses","+6 meses")),"Sin dato registrado")) -> Sin dato registrado | R207: =IF(OR(B207="",M207=""),"",RANK(M207,$M$3:$M$306)+COUNTIF($M$3:M207,M207)-1) -> 29
A208: 25 | B208: Janner Mauricio Giraldo Daza | D208: Ximena | E208: ITIL 5 Fundamentos | F208: Curso y examen | G208: P | K208: PEAR | M208: =IF(B208="","",IF(ISNUMBER(I208),I208,IFERROR(VALUE(SUBSTITUTE(SUBSTITUTE(I208,"$",""),".","")),0))) -> 0 | N208: =IF(B208="","",PROPER(TRIM(D208))) -> Ximena | O208: =IF(B208="","",IF(OR(ISNUMBER(SEARCH("AL DIA",L208)),ISNUMBER(SEARCH("AL DIA",F208))),"Al día",IF(OR(ISNUMBER(SEARCH("QUIETO",L208)),ISNUMBER(SEARCH("QUIETO",F208)),ISNUMBER(SEARCH("ESPERANDO",L208)),ISNUMBER(SEARCH("ESPERANDO",F208))),"Sin respuesta / Inactivo",IF(OR(ISNUMBER(SEARCH("PENDIENTE",L208)),ISNUMBER(SEARCH("PENDIENTE",F208)),ISNUMBER(SEARCH("COMPROMISO",F208)),ISNUMBER(SEARCH("COMPROMISO",L208)),ISNUMBER(SEARCH("PROCESO",F208)),ISNUMBER(SEARCH("LLAMAR",F208)),ISNUMBER(SEARCH("ABONO",J208)),EXACT(L208,"P"),EXACT(F208,"P")),"Pendiente / Compromiso","Sin gestionar")))) -> Sin gestionar | P208: =IF(B208="","",IF(E208="","Sin definir",IF(ISNUMBER(SEARCH("ITIL",E208)),"ITIL",IF(ISNUMBER(SEARCH("ISO 27001",E208)),"ISO 27001",IF(ISNUMBER(SEARCH("ISO 42001",E208)),"ISO 42001",IF(ISNUMBER(SEARCH("ISO",E208)),"Otras ISO",IF(ISNUMBER(SEARCH("SCRUM",E208)),"SCRUM",IF(ISNUMBER(SEARCH("BRIDGE",E208)),"BRIDGE",IF(ISNUMBER(SEARCH("CDS",E208)),"CDS",IF(ISNUMBER(SEARCH("TOGAF",E208)),"TOGAF",IF(ISNUMBER(SEARCH("DPI",E208)),"DPI",IF(ISNUMBER(SEARCH("DITS",E208)),"DITS",IF(ISNUMBER(SEARCH("AGILE",E208)),"AGILE",IF(ISNUMBER(SEARCH("Ciberseguridad",E208)),"Ciberseguridad","Otros")))))))))))))) -> ITIL | Q208: =IF(B208="","",IF(ISNUMBER(K208),IF(K208<=3,"1-3 meses",IF(K208<=6,"4-6 meses","+6 meses")),"Sin dato registrado")) -> Sin dato registrado | R208: =IF(OR(B208="",M208=""),"",RANK(M208,$M$3:$M$306)+COUNTIF($M$3:M208,M208)-1) -> 62
A209: 26 | B209: Omar Jose Diaz Campuzano | D209: Ximena | E209: ITIL 5 Fundamentos | I209: 650000 | J209: 46203 | M209: =IF(B209="","",IF(ISNUMBER(I209),I209,IFERROR(VALUE(SUBSTITUTE(SUBSTITUTE(I209,"$",""),".","")),0))) -> 650000 | N209: =IF(B209="","",PROPER(TRIM(D209))) -> Ximena | O209: =IF(B209="","",IF(OR(ISNUMBER(SEARCH("AL DIA",L209)),ISNUMBER(SEARCH("AL DIA",F209))),"Al día",IF(OR(ISNUMBER(SEARCH("QUIETO",L209)),ISNUMBER(SEARCH("QUIETO",F209)),ISNUMBER(SEARCH("ESPERANDO",L209)),ISNUMBER(SEARCH("ESPERANDO",F209))),"Sin respuesta / Inactivo",IF(OR(ISNUMBER(SEARCH("PENDIENTE",L209)),ISNUMBER(SEARCH("PENDIENTE",F209)),ISNUMBER(SEARCH("COMPROMISO",F209)),ISNUMBER(SEARCH("COMPROMISO",L209)),ISNUMBER(SEARCH("PROCESO",F209)),ISNUMBER(SEARCH("LLAMAR",F209)),ISNUMBER(SEARCH("ABONO",J209)),EXACT(L209,"P"),EXACT(F209,"P")),"Pendiente / Compromiso","Sin gestionar")))) -> Sin gestionar | P209: =IF(B209="","",IF(E209="","Sin definir",IF(ISNUMBER(SEARCH("ITIL",E209)),"ITIL",IF(ISNUMBER(SEARCH("ISO 27001",E209)),"ISO 27001",IF(ISNUMBER(SEARCH("ISO 42001",E209)),"ISO 42001",IF(ISNUMBER(SEARCH("ISO",E209)),"Otras ISO",IF(ISNUMBER(SEARCH("SCRUM",E209)),"SCRUM",IF(ISNUMBER(SEARCH("BRIDGE",E209)),"BRIDGE",IF(ISNUMBER(SEARCH("CDS",E209)),"CDS",IF(ISNUMBER(SEARCH("TOGAF",E209)),"TOGAF",IF(ISNUMBER(SEARCH("DPI",E209)),"DPI",IF(ISNUMBER(SEARCH("DITS",E209)),"DITS",IF(ISNUMBER(SEARCH("AGILE",E209)),"AGILE",IF(ISNUMBER(SEARCH("Ciberseguridad",E209)),"Ciberseguridad","Otros")))))))))))))) -> ITIL | Q209: =IF(B209="","",IF(ISNUMBER(K209),IF(K209<=3,"1-3 meses",IF(K209<=6,"4-6 meses","+6 meses")),"Sin dato registrado")) -> Sin dato registrado | R209: =IF(OR(B209="",M209=""),"",RANK(M209,$M$3:$M$306)+COUNTIF($M$3:M209,M209)-1) -> 37
A210: 27 | B210: Brayan Stiven Moreno Valdes | D210: ximena | E210: ITIL 4 Fundamentos | I210: 500000 | J210: ABONO 05 JUN | L210: Pendiente X FECHA | M210: =IF(B210="","",IF(ISNUMBER(I210),I210,IFERROR(VALUE(SUBSTITUTE(SUBSTITUTE(I210,"$",""),".","")),0))) -> 500000 | N210: =IF(B210="","",PROPER(TRIM(D210))) -> Ximena | O210: =IF(B210="","",IF(OR(ISNUMBER(SEARCH("AL DIA",L210)),ISNUMBER(SEARCH("AL DIA",F210))),"Al día",IF(OR(ISNUMBER(SEARCH("QUIETO",L210)),ISNUMBER(SEARCH("QUIETO",F210)),ISNUMBER(SEARCH("ESPERANDO",L210)),ISNUMBER(SEARCH("ESPERANDO",F210))),"Sin respuesta / Inactivo",IF(OR(ISNUMBER(SEARCH("PENDIENTE",L210)),ISNUMBER(SEARCH("PENDIENTE",F210)),ISNUMBER(SEARCH("COMPROMISO",F210)),ISNUMBER(SEARCH("COMPROMISO",L210)),ISNUMBER(SEARCH("PROCESO",F210)),ISNUMBER(SEARCH("LLAMAR",F210)),ISNUMBER(SEARCH("ABONO",J210)),EXACT(L210,"P"),EXACT(F210,"P")),"Pendiente / Compromiso","Sin gestionar")))) -> Pendiente / Compromiso | P210: =IF(B210="","",IF(E210="","Sin definir",IF(ISNUMBER(SEARCH("ITIL",E210)),"ITIL",IF(ISNUMBER(SEARCH("ISO 27001",E210)),"ISO 27001",IF(ISNUMBER(SEARCH("ISO 42001",E210)),"ISO 42001",IF(ISNUMBER(SEARCH("ISO",E210)),"Otras ISO",IF(ISNUMBER(SEARCH("SCRUM",E210)),"SCRUM",IF(ISNUMBER(SEARCH("BRIDGE",E210)),"BRIDGE",IF(ISNUMBER(SEARCH("CDS",E210)),"CDS",IF(ISNUMBER(SEARCH("TOGAF",E210)),"TOGAF",IF(ISNUMBER(SEARCH("DPI",E210)),"DPI",IF(ISNUMBER(SEARCH("DITS",E210)),"DITS",IF(ISNUMBER(SEARCH("AGILE",E210)),"AGILE",IF(ISNUMBER(SEARCH("Ciberseguridad",E210)),"Ciberseguridad","Otros")))))))))))))) -> ITIL | Q210: =IF(B210="","",IF(ISNUMBER(K210),IF(K210<=3,"1-3 meses",IF(K210<=6,"4-6 meses","+6 meses")),"Sin dato registrado")) -> Sin dato registrado | R210: =IF(OR(B210="",M210=""),"",RANK(M210,$M$3:$M$306)+COUNTIF($M$3:M210,M210)-1) -> 47
A211: 28 | B211: Jhon Isaias Muñoz Remolina | D211: Ximena | E211: DPI | J211: 05 ABR 05 MAY 05 JUN | M211: =IF(B211="","",IF(ISNUMBER(I211),I211,IFERROR(VALUE(SUBSTITUTE(SUBSTITUTE(I211,"$",""),".","")),0))) -> 0 | N211: =IF(B211="","",PROPER(TRIM(D211))) -> Ximena | O211: =IF(B211="","",IF(OR(ISNUMBER(SEARCH("AL DIA",L211)),ISNUMBER(SEARCH("AL DIA",F211))),"Al día",IF(OR(ISNUMBER(SEARCH("QUIETO",L211)),ISNUMBER(SEARCH("QUIETO",F211)),ISNUMBER(SEARCH("ESPERANDO",L211)),ISNUMBER(SEARCH("ESPERANDO",F211))),"Sin respuesta / Inactivo",IF(OR(ISNUMBER(SEARCH("PENDIENTE",L211)),ISNUMBER(SEARCH("PENDIENTE",F211)),ISNUMBER(SEARCH("COMPROMISO",F211)),ISNUMBER(SEARCH("COMPROMISO",L211)),ISNUMBER(SEARCH("PROCESO",F211)),ISNUMBER(SEARCH("LLAMAR",F211)),ISNUMBER(SEARCH("ABONO",J211)),EXACT(L211,"P"),EXACT(F211,"P")),"Pendiente / Compromiso","Sin gestionar")))) -> Sin gestionar | P211: =IF(B211="","",IF(E211="","Sin definir",IF(ISNUMBER(SEARCH("ITIL",E211)),"ITIL",IF(ISNUMBER(SEARCH("ISO 27001",E211)),"ISO 27001",IF(ISNUMBER(SEARCH("ISO 42001",E211)),"ISO 42001",IF(ISNUMBER(SEARCH("ISO",E211)),"Otras ISO",IF(ISNUMBER(SEARCH("SCRUM",E211)),"SCRUM",IF(ISNUMBER(SEARCH("BRIDGE",E211)),"BRIDGE",IF(ISNUMBER(SEARCH("CDS",E211)),"CDS",IF(ISNUMBER(SEARCH("TOGAF",E211)),"TOGAF",IF(ISNUMBER(SEARCH("DPI",E211)),"DPI",IF(ISNUMBER(SEARCH("DITS",E211)),"DITS",IF(ISNUMBER(SEARCH("AGILE",E211)),"AGILE",IF(ISNUMBER(SEARCH("Ciberseguridad",E211)),"Ciberseguridad","Otros")))))))))))))) -> DPI | Q211: =IF(B211="","",IF(ISNUMBER(K211),IF(K211<=3,"1-3 meses",IF(K211<=6,"4-6 meses","+6 meses")),"Sin dato registrado")) -> Sin dato registrado | R211: =IF(OR(B211="",M211=""),"",RANK(M211,$M$3:$M$306)+COUNTIF($M$3:M211,M211)-1) -> 63
A212: 29 | B212: Eliana Lizeth Florez Gonzalez | D212: Ximena | E212: scrum po | I212: 345000 | L212: Pendiente X FECHA | M212: =IF(B212="","",IF(ISNUMBER(I212),I212,IFERROR(VALUE(SUBSTITUTE(SUBSTITUTE(I212,"$",""),".","")),0))) -> 345000 | N212: =IF(B212="","",PROPER(TRIM(D212))) -> Ximena | O212: =IF(B212="","",IF(OR(ISNUMBER(SEARCH("AL DIA",L212)),ISNUMBER(SEARCH("AL DIA",F212))),"Al día",IF(OR(ISNUMBER(SEARCH("QUIETO",L212)),ISNUMBER(SEARCH("QUIETO",F212)),ISNUMBER(SEARCH("ESPERANDO",L212)),ISNUMBER(SEARCH("ESPERANDO",F212))),"Sin respuesta / Inactivo",IF(OR(ISNUMBER(SEARCH("PENDIENTE",L212)),ISNUMBER(SEARCH("PENDIENTE",F212)),ISNUMBER(SEARCH("COMPROMISO",F212)),ISNUMBER(SEARCH("COMPROMISO",L212)),ISNUMBER(SEARCH("PROCESO",F212)),ISNUMBER(SEARCH("LLAMAR",F212)),ISNUMBER(SEARCH("ABONO",J212)),EXACT(L212,"P"),EXACT(F212,"P")),"Pendiente / Compromiso","Sin gestionar")))) -> Pendiente / Compromiso | P212: =IF(B212="","",IF(E212="","Sin definir",IF(ISNUMBER(SEARCH("ITIL",E212)),"ITIL",IF(ISNUMBER(SEARCH("ISO 27001",E212)),"ISO 27001",IF(ISNUMBER(SEARCH("ISO 42001",E212)),"ISO 42001",IF(ISNUMBER(SEARCH("ISO",E212)),"Otras ISO",IF(ISNUMBER(SEARCH("SCRUM",E212)),"SCRUM",IF(ISNUMBER(SEARCH("BRIDGE",E212)),"BRIDGE",IF(ISNUMBER(SEARCH("CDS",E212)),"CDS",IF(ISNUMBER(SEARCH("TOGAF",E212)),"TOGAF",IF(ISNUMBER(SEARCH("DPI",E212)),"DPI",IF(ISNUMBER(SEARCH("DITS",E212)),"DITS",IF(ISNUMBER(SEARCH("AGILE",E212)),"AGILE",IF(ISNUMBER(SEARCH("Ciberseguridad",E212)),"Ciberseguridad","Otros")))))))))))))) -> SCRUM | Q212: =IF(B212="","",IF(ISNUMBER(K212),IF(K212<=3,"1-3 meses",IF(K212<=6,"4-6 meses","+6 meses")),"Sin dato registrado")) -> Sin dato registrado | R212: =IF(OR(B212="",M212=""),"",RANK(M212,$M$3:$M$306)+COUNTIF($M$3:M212,M212)-1) -> 54
A213: 30 | B213: María Teresa Ortiz Covaleda | D213: Ximena | E213: ISO 27001 | I213: 860000 | J213: 20 may y 01 jun | L213: Pendiente X FECHA | M213: =IF(B213="","",IF(ISNUMBER(I213),I213,IFERROR(VALUE(SUBSTITUTE(SUBSTITUTE(I213,"$",""),".","")),0))) -> 860000 | N213: =IF(B213="","",PROPER(TRIM(D213))) -> Ximena | O213: =IF(B213="","",IF(OR(ISNUMBER(SEARCH("AL DIA",L213)),ISNUMBER(SEARCH("AL DIA",F213))),"Al día",IF(OR(ISNUMBER(SEARCH("QUIETO",L213)),ISNUMBER(SEARCH("QUIETO",F213)),ISNUMBER(SEARCH("ESPERANDO",L213)),ISNUMBER(SEARCH("ESPERANDO",F213))),"Sin respuesta / Inactivo",IF(OR(ISNUMBER(SEARCH("PENDIENTE",L213)),ISNUMBER(SEARCH("PENDIENTE",F213)),ISNUMBER(SEARCH("COMPROMISO",F213)),ISNUMBER(SEARCH("COMPROMISO",L213)),ISNUMBER(SEARCH("PROCESO",F213)),ISNUMBER(SEARCH("LLAMAR",F213)),ISNUMBER(SEARCH("ABONO",J213)),EXACT(L213,"P"),EXACT(F213,"P")),"Pendiente / Compromiso","Sin gestionar")))) -> Pendiente / Compromiso | P213: =IF(B213="","",IF(E213="","Sin definir",IF(ISNUMBER(SEARCH("ITIL",E213)),"ITIL",IF(ISNUMBER(SEARCH("ISO 27001",E213)),"ISO 27001",IF(ISNUMBER(SEARCH("ISO 42001",E213)),"ISO 42001",IF(ISNUMBER(SEARCH("ISO",E213)),"Otras ISO",IF(ISNUMBER(SEARCH("SCRUM",E213)),"SCRUM",IF(ISNUMBER(SEARCH("BRIDGE",E213)),"BRIDGE",IF(ISNUMBER(SEARCH("CDS",E213)),"CDS",IF(ISNUMBER(SEARCH("TOGAF",E213)),"TOGAF",IF(ISNUMBER(SEARCH("DPI",E213)),"DPI",IF(ISNUMBER(SEARCH("DITS",E213)),"DITS",IF(ISNUMBER(SEARCH("AGILE",E213)),"AGILE",IF(ISNUMBER(SEARCH("Ciberseguridad",E213)),"Ciberseguridad","Otros")))))))))))))) -> ISO 27001 | Q213: =IF(B213="","",IF(ISNUMBER(K213),IF(K213<=3,"1-3 meses",IF(K213<=6,"4-6 meses","+6 meses")),"Sin dato registrado")) -> Sin dato registrado | R213: =IF(OR(B213="",M213=""),"",RANK(M213,$M$3:$M$306)+COUNTIF($M$3:M213,M213)-1) -> 26
A214: 31 | B214: Sabrina Bastos | D214: Sebas | E214: ITIL V5 | F214: Curso y examen | G214: pendiente x fecha compromiso de pago | I214: 975000 | J214: - | K214: - | L214: AL DIA | M214: =IF(B214="","",IF(ISNUMBER(I214),I214,IFERROR(VALUE(SUBSTITUTE(SUBSTITUTE(I214,"$",""),".","")),0))) -> 975000 | N214: =IF(B214="","",PROPER(TRIM(D214))) -> Sebas | O214: =IF(B214="","",IF(OR(ISNUMBER(SEARCH("AL DIA",L214)),ISNUMBER(SEARCH("AL DIA",F214))),"Al día",IF(OR(ISNUMBER(SEARCH("QUIETO",L214)),ISNUMBER(SEARCH("QUIETO",F214)),ISNUMBER(SEARCH("ESPERANDO",L214)),ISNUMBER(SEARCH("ESPERANDO",F214))),"Sin respuesta / Inactivo",IF(OR(ISNUMBER(SEARCH("PENDIENTE",L214)),ISNUMBER(SEARCH("PENDIENTE",F214)),ISNUMBER(SEARCH("COMPROMISO",F214)),ISNUMBER(SEARCH("COMPROMISO",L214)),ISNUMBER(SEARCH("PROCESO",F214)),ISNUMBER(SEARCH("LLAMAR",F214)),ISNUMBER(SEARCH("ABONO",J214)),EXACT(L214,"P"),EXACT(F214,"P")),"Pendiente / Compromiso","Sin gestionar")))) -> Al día | P214: =IF(B214="","",IF(E214="","Sin definir",IF(ISNUMBER(SEARCH("ITIL",E214)),"ITIL",IF(ISNUMBER(SEARCH("ISO 27001",E214)),"ISO 27001",IF(ISNUMBER(SEARCH("ISO 42001",E214)),"ISO 42001",IF(ISNUMBER(SEARCH("ISO",E214)),"Otras ISO",IF(ISNUMBER(SEARCH("SCRUM",E214)),"SCRUM",IF(ISNUMBER(SEARCH("BRIDGE",E214)),"BRIDGE",IF(ISNUMBER(SEARCH("CDS",E214)),"CDS",IF(ISNUMBER(SEARCH("TOGAF",E214)),"TOGAF",IF(ISNUMBER(SEARCH("DPI",E214)),"DPI",IF(ISNUMBER(SEARCH("DITS",E214)),"DITS",IF(ISNUMBER(SEARCH("AGILE",E214)),"AGILE",IF(ISNUMBER(SEARCH("Ciberseguridad",E214)),"Ciberseguridad","Otros")))))))))))))) -> ITIL | Q214: =IF(B214="","",IF(ISNUMBER(K214),IF(K214<=3,"1-3 meses",IF(K214<=6,"4-6 meses","+6 meses")),"Sin dato registrado")) -> Sin dato registrado | R214: =IF(OR(B214="",M214=""),"",RANK(M214,$M$3:$M$306)+COUNTIF($M$3:M214,M214)-1) -> 23
A215: 32 | B215: Liliana Bustos | D215: Sebas | E215: BRIDGE | F215: Curso y examen | G215: pendiente x fecha compromiso de pago | I215: 650000 | J215: - | K215: - | L215: - | M215: =IF(B215="","",IF(ISNUMBER(I215),I215,IFERROR(VALUE(SUBSTITUTE(SUBSTITUTE(I215,"$",""),".","")),0))) -> 650000 | N215: =IF(B215="","",PROPER(TRIM(D215))) -> Sebas | O215: =IF(B215="","",IF(OR(ISNUMBER(SEARCH("AL DIA",L215)),ISNUMBER(SEARCH("AL DIA",F215))),"Al día",IF(OR(ISNUMBER(SEARCH("QUIETO",L215)),ISNUMBER(SEARCH("QUIETO",F215)),ISNUMBER(SEARCH("ESPERANDO",L215)),ISNUMBER(SEARCH("ESPERANDO",F215))),"Sin respuesta / Inactivo",IF(OR(ISNUMBER(SEARCH("PENDIENTE",L215)),ISNUMBER(SEARCH("PENDIENTE",F215)),ISNUMBER(SEARCH("COMPROMISO",F215)),ISNUMBER(SEARCH("COMPROMISO",L215)),ISNUMBER(SEARCH("PROCESO",F215)),ISNUMBER(SEARCH("LLAMAR",F215)),ISNUMBER(SEARCH("ABONO",J215)),EXACT(L215,"P"),EXACT(F215,"P")),"Pendiente / Compromiso","Sin gestionar")))) -> Sin gestionar | P215: =IF(B215="","",IF(E215="","Sin definir",IF(ISNUMBER(SEARCH("ITIL",E215)),"ITIL",IF(ISNUMBER(SEARCH("ISO 27001",E215)),"ISO 27001",IF(ISNUMBER(SEARCH("ISO 42001",E215)),"ISO 42001",IF(ISNUMBER(SEARCH("ISO",E215)),"Otras ISO",IF(ISNUMBER(SEARCH("SCRUM",E215)),"SCRUM",IF(ISNUMBER(SEARCH("BRIDGE",E215)),"BRIDGE",IF(ISNUMBER(SEARCH("CDS",E215)),"CDS",IF(ISNUMBER(SEARCH("TOGAF",E215)),"TOGAF",IF(ISNUMBER(SEARCH("DPI",E215)),"DPI",IF(ISNUMBER(SEARCH("DITS",E215)),"DITS",IF(ISNUMBER(SEARCH("AGILE",E215)),"AGILE",IF(ISNUMBER(SEARCH("Ciberseguridad",E215)),"Ciberseguridad","Otros")))))))))))))) -> BRIDGE | Q215: =IF(B215="","",IF(ISNUMBER(K215),IF(K215<=3,"1-3 meses",IF(K215<=6,"4-6 meses","+6 meses")),"Sin dato registrado")) -> Sin dato registrado | R215: =IF(OR(B215="",M215=""),"",RANK(M215,$M$3:$M$306)+COUNTIF($M$3:M215,M215)-1) -> 38
A216: 33 | B216: Alvaro Enrique Rodriguez Chaves | D216: Carolina | E216: TOGAF 10 | F216: Curso y examen | G216: pendiente x fecha compromiso de pago | I216: 1000000 | J216: - | K216: - | L216: - | M216: =IF(B216="","",IF(ISNUMBER(I216),I216,IFERROR(VALUE(SUBSTITUTE(SUBSTITUTE(I216,"$",""),".","")),0))) -> 1000000 | N216: =IF(B216="","",PROPER(TRIM(D216))) -> Carolina | O216: =IF(B216="","",IF(OR(ISNUMBER(SEARCH("AL DIA",L216)),ISNUMBER(SEARCH("AL DIA",F216))),"Al día",IF(OR(ISNUMBER(SEARCH("QUIETO",L216)),ISNUMBER(SEARCH("QUIETO",F216)),ISNUMBER(SEARCH("ESPERANDO",L216)),ISNUMBER(SEARCH("ESPERANDO",F216))),"Sin respuesta / Inactivo",IF(OR(ISNUMBER(SEARCH("PENDIENTE",L216)),ISNUMBER(SEARCH("PENDIENTE",F216)),ISNUMBER(SEARCH("COMPROMISO",F216)),ISNUMBER(SEARCH("COMPROMISO",L216)),ISNUMBER(SEARCH("PROCESO",F216)),ISNUMBER(SEARCH("LLAMAR",F216)),ISNUMBER(SEARCH("ABONO",J216)),EXACT(L216,"P"),EXACT(F216,"P")),"Pendiente / Compromiso","Sin gestionar")))) -> Sin gestionar | P216: =IF(B216="","",IF(E216="","Sin definir",IF(ISNUMBER(SEARCH("ITIL",E216)),"ITIL",IF(ISNUMBER(SEARCH("ISO 27001",E216)),"ISO 27001",IF(ISNUMBER(SEARCH("ISO 42001",E216)),"ISO 42001",IF(ISNUMBER(SEARCH("ISO",E216)),"Otras ISO",IF(ISNUMBER(SEARCH("SCRUM",E216)),"SCRUM",IF(ISNUMBER(SEARCH("BRIDGE",E216)),"BRIDGE",IF(ISNUMBER(SEARCH("CDS",E216)),"CDS",IF(ISNUMBER(SEARCH("TOGAF",E216)),"TOGAF",IF(ISNUMBER(SEARCH("DPI",E216)),"DPI",IF(ISNUMBER(SEARCH("DITS",E216)),"DITS",IF(ISNUMBER(SEARCH("AGILE",E216)),"AGILE",IF(ISNUMBER(SEARCH("Ciberseguridad",E216)),"Ciberseguridad","Otros")))))))))))))) -> TOGAF | Q216: =IF(B216="","",IF(ISNUMBER(K216),IF(K216<=3,"1-3 meses",IF(K216<=6,"4-6 meses","+6 meses")),"Sin dato registrado")) -> Sin dato registrado | R216: =IF(OR(B216="",M216=""),"",RANK(M216,$M$3:$M$306)+COUNTIF($M$3:M216,M216)-1) -> 20
A217: 34 | B217: Jose Nelson Nariño Naranjo | D217: Carolina | E217: ITIL V5 | F217: Curso y examen | G217: pendiente x fecha compromiso de pago | I217: 250000 | J217: - | K217: - | L217: - | M217: =IF(B217="","",IF(ISNUMBER(I217),I217,IFERROR(VALUE(SUBSTITUTE(SUBSTITUTE(I217,"$",""),".","")),0))) -> 250000 | N217: =IF(B217="","",PROPER(TRIM(D217))) -> Carolina | O217: =IF(B217="","",IF(OR(ISNUMBER(SEARCH("AL DIA",L217)),ISNUMBER(SEARCH("AL DIA",F217))),"Al día",IF(OR(ISNUMBER(SEARCH("QUIETO",L217)),ISNUMBER(SEARCH("QUIETO",F217)),ISNUMBER(SEARCH("ESPERANDO",L217)),ISNUMBER(SEARCH("ESPERANDO",F217))),"Sin respuesta / Inactivo",IF(OR(ISNUMBER(SEARCH("PENDIENTE",L217)),ISNUMBER(SEARCH("PENDIENTE",F217)),ISNUMBER(SEARCH("COMPROMISO",F217)),ISNUMBER(SEARCH("COMPROMISO",L217)),ISNUMBER(SEARCH("PROCESO",F217)),ISNUMBER(SEARCH("LLAMAR",F217)),ISNUMBER(SEARCH("ABONO",J217)),EXACT(L217,"P"),EXACT(F217,"P")),"Pendiente / Compromiso","Sin gestionar")))) -> Sin gestionar | P217: =IF(B217="","",IF(E217="","Sin definir",IF(ISNUMBER(SEARCH("ITIL",E217)),"ITIL",IF(ISNUMBER(SEARCH("ISO 27001",E217)),"ISO 27001",IF(ISNUMBER(SEARCH("ISO 42001",E217)),"ISO 42001",IF(ISNUMBER(SEARCH("ISO",E217)),"Otras ISO",IF(ISNUMBER(SEARCH("SCRUM",E217)),"SCRUM",IF(ISNUMBER(SEARCH("BRIDGE",E217)),"BRIDGE",IF(ISNUMBER(SEARCH("CDS",E217)),"CDS",IF(ISNUMBER(SEARCH("TOGAF",E217)),"TOGAF",IF(ISNUMBER(SEARCH("DPI",E217)),"DPI",IF(ISNUMBER(SEARCH("DITS",E217)),"DITS",IF(ISNUMBER(SEARCH("AGILE",E217)),"AGILE",IF(ISNUMBER(SEARCH("Ciberseguridad",E217)),"Ciberseguridad","Otros")))))))))))))) -> ITIL | Q217: =IF(B217="","",IF(ISNUMBER(K217),IF(K217<=3,"1-3 meses",IF(K217<=6,"4-6 meses","+6 meses")),"Sin dato registrado")) -> Sin dato registrado | R217: =IF(OR(B217="",M217=""),"",RANK(M217,$M$3:$M$306)+COUNTIF($M$3:M217,M217)-1) -> 57
A218: 35 | B218: María del Carmen Bolaño Cortissoz | D218: Sebas | E218: BRIDGE | F218: Curso y examen | G218: pendiente x fecha compromiso de pago | I218: 660000 | J218: - | K218: - | L218: - | M218: =IF(B218="","",IF(ISNUMBER(I218),I218,IFERROR(VALUE(SUBSTITUTE(SUBSTITUTE(I218,"$",""),".","")),0))) -> 660000 | N218: =IF(B218="","",PROPER(TRIM(D218))) -> Sebas | O218: =IF(B218="","",IF(OR(ISNUMBER(SEARCH("AL DIA",L218)),ISNUMBER(SEARCH("AL DIA",F218))),"Al día",IF(OR(ISNUMBER(SEARCH("QUIETO",L218)),ISNUMBER(SEARCH("QUIETO",F218)),ISNUMBER(SEARCH("ESPERANDO",L218)),ISNUMBER(SEARCH("ESPERANDO",F218))),"Sin respuesta / Inactivo",IF(OR(ISNUMBER(SEARCH("PENDIENTE",L218)),ISNUMBER(SEARCH("PENDIENTE",F218)),ISNUMBER(SEARCH("COMPROMISO",F218)),ISNUMBER(SEARCH("COMPROMISO",L218)),ISNUMBER(SEARCH("PROCESO",F218)),ISNUMBER(SEARCH("LLAMAR",F218)),ISNUMBER(SEARCH("ABONO",J218)),EXACT(L218,"P"),EXACT(F218,"P")),"Pendiente / Compromiso","Sin gestionar")))) -> Sin gestionar | P218: =IF(B218="","",IF(E218="","Sin definir",IF(ISNUMBER(SEARCH("ITIL",E218)),"ITIL",IF(ISNUMBER(SEARCH("ISO 27001",E218)),"ISO 27001",IF(ISNUMBER(SEARCH("ISO 42001",E218)),"ISO 42001",IF(ISNUMBER(SEARCH("ISO",E218)),"Otras ISO",IF(ISNUMBER(SEARCH("SCRUM",E218)),"SCRUM",IF(ISNUMBER(SEARCH("BRIDGE",E218)),"BRIDGE",IF(ISNUMBER(SEARCH("CDS",E218)),"CDS",IF(ISNUMBER(SEARCH("TOGAF",E218)),"TOGAF",IF(ISNUMBER(SEARCH("DPI",E218)),"DPI",IF(ISNUMBER(SEARCH("DITS",E218)),"DITS",IF(ISNUMBER(SEARCH("AGILE",E218)),"AGILE",IF(ISNUMBER(SEARCH("Ciberseguridad",E218)),"Ciberseguridad","Otros")))))))))))))) -> BRIDGE | Q218: =IF(B218="","",IF(ISNUMBER(K218),IF(K218<=3,"1-3 meses",IF(K218<=6,"4-6 meses","+6 meses")),"Sin dato registrado")) -> Sin dato registrado | R218: =IF(OR(B218="",M218=""),"",RANK(M218,$M$3:$M$306)+COUNTIF($M$3:M218,M218)-1) -> 36
A219: 37 | B219: Rosa Helena Barrera | D219: Ximena | E219: ITIL V5 | F219: Curso y examen | G219: 30 may y 30 jun | I219: 650000 | J219: 46203 | K219: Colvatel | M219: =IF(B219="","",IF(ISNUMBER(I219),I219,IFERROR(VALUE(SUBSTITUTE(SUBSTITUTE(I219,"$",""),".","")),0))) -> 650000 | N219: =IF(B219="","",PROPER(TRIM(D219))) -> Ximena | O219: =IF(B219="","",IF(OR(ISNUMBER(SEARCH("AL DIA",L219)),ISNUMBER(SEARCH("AL DIA",F219))),"Al día",IF(OR(ISNUMBER(SEARCH("QUIETO",L219)),ISNUMBER(SEARCH("QUIETO",F219)),ISNUMBER(SEARCH("ESPERANDO",L219)),ISNUMBER(SEARCH("ESPERANDO",F219))),"Sin respuesta / Inactivo",IF(OR(ISNUMBER(SEARCH("PENDIENTE",L219)),ISNUMBER(SEARCH("PENDIENTE",F219)),ISNUMBER(SEARCH("COMPROMISO",F219)),ISNUMBER(SEARCH("COMPROMISO",L219)),ISNUMBER(SEARCH("PROCESO",F219)),ISNUMBER(SEARCH("LLAMAR",F219)),ISNUMBER(SEARCH("ABONO",J219)),EXACT(L219,"P"),EXACT(F219,"P")),"Pendiente / Compromiso","Sin gestionar")))) -> Sin gestionar | P219: =IF(B219="","",IF(E219="","Sin definir",IF(ISNUMBER(SEARCH("ITIL",E219)),"ITIL",IF(ISNUMBER(SEARCH("ISO 27001",E219)),"ISO 27001",IF(ISNUMBER(SEARCH("ISO 42001",E219)),"ISO 42001",IF(ISNUMBER(SEARCH("ISO",E219)),"Otras ISO",IF(ISNUMBER(SEARCH("SCRUM",E219)),"SCRUM",IF(ISNUMBER(SEARCH("BRIDGE",E219)),"BRIDGE",IF(ISNUMBER(SEARCH("CDS",E219)),"CDS",IF(ISNUMBER(SEARCH("TOGAF",E219)),"TOGAF",IF(ISNUMBER(SEARCH("DPI",E219)),"DPI",IF(ISNUMBER(SEARCH("DITS",E219)),"DITS",IF(ISNUMBER(SEARCH("AGILE",E219)),"AGILE",IF(ISNUMBER(SEARCH("Ciberseguridad",E219)),"Ciberseguridad","Otros")))))))))))))) -> ITIL | Q219: =IF(B219="","",IF(ISNUMBER(K219),IF(K219<=3,"1-3 meses",IF(K219<=6,"4-6 meses","+6 meses")),"Sin dato registrado")) -> Sin dato registrado | R219: =IF(OR(B219="",M219=""),"",RANK(M219,$M$3:$M$306)+COUNTIF($M$3:M219,M219)-1) -> 39
A220: 38 | B220: Juan Camilo Corredor Espinosa | D220: Ximena | E220: ISO 27001 | F220: Curso y examen | G220: PENDIENTE CP | I220: 890000 | J220: - | K220: - | L220: - | M220: =IF(B220="","",IF(ISNUMBER(I220),I220,IFERROR(VALUE(SUBSTITUTE(SUBSTITUTE(I220,"$",""),".","")),0))) -> 890000 | N220: =IF(B220="","",PROPER(TRIM(D220))) -> Ximena | O220: =IF(B220="","",IF(OR(ISNUMBER(SEARCH("AL DIA",L220)),ISNUMBER(SEARCH("AL DIA",F220))),"Al día",IF(OR(ISNUMBER(SEARCH("QUIETO",L220)),ISNUMBER(SEARCH("QUIETO",F220)),ISNUMBER(SEARCH("ESPERANDO",L220)),ISNUMBER(SEARCH("ESPERANDO",F220))),"Sin respuesta / Inactivo",IF(OR(ISNUMBER(SEARCH("PENDIENTE",L220)),ISNUMBER(SEARCH("PENDIENTE",F220)),ISNUMBER(SEARCH("COMPROMISO",F220)),ISNUMBER(SEARCH("COMPROMISO",L220)),ISNUMBER(SEARCH("PROCESO",F220)),ISNUMBER(SEARCH("LLAMAR",F220)),ISNUMBER(SEARCH("ABONO",J220)),EXACT(L220,"P"),EXACT(F220,"P")),"Pendiente / Compromiso","Sin gestionar")))) -> Sin gestionar | P220: =IF(B220="","",IF(E220="","Sin definir",IF(ISNUMBER(SEARCH("ITIL",E220)),"ITIL",IF(ISNUMBER(SEARCH("ISO 27001",E220)),"ISO 27001",IF(ISNUMBER(SEARCH("ISO 42001",E220)),"ISO 42001",IF(ISNUMBER(SEARCH("ISO",E220)),"Otras ISO",IF(ISNUMBER(SEARCH("SCRUM",E220)),"SCRUM",IF(ISNUMBER(SEARCH("BRIDGE",E220)),"BRIDGE",IF(ISNUMBER(SEARCH("CDS",E220)),"CDS",IF(ISNUMBER(SEARCH("TOGAF",E220)),"TOGAF",IF(ISNUMBER(SEARCH("DPI",E220)),"DPI",IF(ISNUMBER(SEARCH("DITS",E220)),"DITS",IF(ISNUMBER(SEARCH("AGILE",E220)),"AGILE",IF(ISNUMBER(SEARCH("Ciberseguridad",E220)),"Ciberseguridad","Otros")))))))))))))) -> ISO 27001 | Q220: =IF(B220="","",IF(ISNUMBER(K220),IF(K220<=3,"1-3 meses",IF(K220<=6,"4-6 meses","+6 meses")),"Sin dato registrado")) -> Sin dato registrado | R220: =IF(OR(B220="",M220=""),"",RANK(M220,$M$3:$M$306)+COUNTIF($M$3:M220,M220)-1) -> 25
A221: 39 | B221: Édgar Raúl Quintero Rojas | D221: Ximena | E221: ISO 27001 | F221: Curso y examen | G221: PENDIENTE CP | I221: 790000 | M221: =IF(B221="","",IF(ISNUMBER(I221),I221,IFERROR(VALUE(SUBSTITUTE(SUBSTITUTE(I221,"$",""),".","")),0))) -> 790000 | N221: =IF(B221="","",PROPER(TRIM(D221))) -> Ximena | O221: =IF(B221="","",IF(OR(ISNUMBER(SEARCH("AL DIA",L221)),ISNUMBER(SEARCH("AL DIA",F221))),"Al día",IF(OR(ISNUMBER(SEARCH("QUIETO",L221)),ISNUMBER(SEARCH("QUIETO",F221)),ISNUMBER(SEARCH("ESPERANDO",L221)),ISNUMBER(SEARCH("ESPERANDO",F221))),"Sin respuesta / Inactivo",IF(OR(ISNUMBER(SEARCH("PENDIENTE",L221)),ISNUMBER(SEARCH("PENDIENTE",F221)),ISNUMBER(SEARCH("COMPROMISO",F221)),ISNUMBER(SEARCH("COMPROMISO",L221)),ISNUMBER(SEARCH("PROCESO",F221)),ISNUMBER(SEARCH("LLAMAR",F221)),ISNUMBER(SEARCH("ABONO",J221)),EXACT(L221,"P"),EXACT(F221,"P")),"Pendiente / Compromiso","Sin gestionar")))) -> Sin gestionar | P221: =IF(B221="","",IF(E221="","Sin definir",IF(ISNUMBER(SEARCH("ITIL",E221)),"ITIL",IF(ISNUMBER(SEARCH("ISO 27001",E221)),"ISO 27001",IF(ISNUMBER(SEARCH("ISO 42001",E221)),"ISO 42001",IF(ISNUMBER(SEARCH("ISO",E221)),"Otras ISO",IF(ISNUMBER(SEARCH("SCRUM",E221)),"SCRUM",IF(ISNUMBER(SEARCH("BRIDGE",E221)),"BRIDGE",IF(ISNUMBER(SEARCH("CDS",E221)),"CDS",IF(ISNUMBER(SEARCH("TOGAF",E221)),"TOGAF",IF(ISNUMBER(SEARCH("DPI",E221)),"DPI",IF(ISNUMBER(SEARCH("DITS",E221)),"DITS",IF(ISNUMBER(SEARCH("AGILE",E221)),"AGILE",IF(ISNUMBER(SEARCH("Ciberseguridad",E221)),"Ciberseguridad","Otros")))))))))))))) -> ISO 27001 | Q221: =IF(B221="","",IF(ISNUMBER(K221),IF(K221<=3,"1-3 meses",IF(K221<=6,"4-6 meses","+6 meses")),"Sin dato registrado")) -> Sin dato registrado | R221: =IF(OR(B221="",M221=""),"",RANK(M221,$M$3:$M$306)+COUNTIF($M$3:M221,M221)-1) -> 34
A222: 40 | B222: Nelson Saul Gonzalez Jimenez | D222: Ximena | E222: AGILE C+L | F222: Curso y examen | G222: PENDIENTE CO | I222: 390000 | M222: =IF(B222="","",IF(ISNUMBER(I222),I222,IFERROR(VALUE(SUBSTITUTE(SUBSTITUTE(I222,"$",""),".","")),0))) -> 390000 | N222: =IF(B222="","",PROPER(TRIM(D222))) -> Ximena | O222: =IF(B222="","",IF(OR(ISNUMBER(SEARCH("AL DIA",L222)),ISNUMBER(SEARCH("AL DIA",F222))),"Al día",IF(OR(ISNUMBER(SEARCH("QUIETO",L222)),ISNUMBER(SEARCH("QUIETO",F222)),ISNUMBER(SEARCH("ESPERANDO",L222)),ISNUMBER(SEARCH("ESPERANDO",F222))),"Sin respuesta / Inactivo",IF(OR(ISNUMBER(SEARCH("PENDIENTE",L222)),ISNUMBER(SEARCH("PENDIENTE",F222)),ISNUMBER(SEARCH("COMPROMISO",F222)),ISNUMBER(SEARCH("COMPROMISO",L222)),ISNUMBER(SEARCH("PROCESO",F222)),ISNUMBER(SEARCH("LLAMAR",F222)),ISNUMBER(SEARCH("ABONO",J222)),EXACT(L222,"P"),EXACT(F222,"P")),"Pendiente / Compromiso","Sin gestionar")))) -> Sin gestionar | P222: =IF(B222="","",IF(E222="","Sin definir",IF(ISNUMBER(SEARCH("ITIL",E222)),"ITIL",IF(ISNUMBER(SEARCH("ISO 27001",E222)),"ISO 27001",IF(ISNUMBER(SEARCH("ISO 42001",E222)),"ISO 42001",IF(ISNUMBER(SEARCH("ISO",E222)),"Otras ISO",IF(ISNUMBER(SEARCH("SCRUM",E222)),"SCRUM",IF(ISNUMBER(SEARCH("BRIDGE",E222)),"BRIDGE",IF(ISNUMBER(SEARCH("CDS",E222)),"CDS",IF(ISNUMBER(SEARCH("TOGAF",E222)),"TOGAF",IF(ISNUMBER(SEARCH("DPI",E222)),"DPI",IF(ISNUMBER(SEARCH("DITS",E222)),"DITS",IF(ISNUMBER(SEARCH("AGILE",E222)),"AGILE",IF(ISNUMBER(SEARCH("Ciberseguridad",E222)),"Ciberseguridad","Otros")))))))))))))) -> AGILE | Q222: =IF(B222="","",IF(ISNUMBER(K222),IF(K222<=3,"1-3 meses",IF(K222<=6,"4-6 meses","+6 meses")),"Sin dato registrado")) -> Sin dato registrado | R222: =IF(OR(B222="",M222=""),"",RANK(M222,$M$3:$M$306)+COUNTIF($M$3:M222,M222)-1) -> 52
B223: brayan steven ortiz gil | D223: Ximena | E223: ISO 42001 | F223: Curso y examen | G223: P CP | M223: =IF(B223="","",IF(ISNUMBER(I223),I223,IFERROR(VALUE(SUBSTITUTE(SUBSTITUTE(I223,"$",""),".","")),0))) -> 0 | N223: =IF(B223="","",PROPER(TRIM(D223))) -> Ximena | O223: =IF(B223="","",IF(OR(ISNUMBER(SEARCH("AL DIA",L223)),ISNUMBER(SEARCH("AL DIA",F223))),"Al día",IF(OR(ISNUMBER(SEARCH("QUIETO",L223)),ISNUMBER(SEARCH("QUIETO",F223)),ISNUMBER(SEARCH("ESPERANDO",L223)),ISNUMBER(SEARCH("ESPERANDO",F223))),"Sin respuesta / Inactivo",IF(OR(ISNUMBER(SEARCH("PENDIENTE",L223)),ISNUMBER(SEARCH("PENDIENTE",F223)),ISNUMBER(SEARCH("COMPROMISO",F223)),ISNUMBER(SEARCH("COMPROMISO",L223)),ISNUMBER(SEARCH("PROCESO",F223)),ISNUMBER(SEARCH("LLAMAR",F223)),ISNUMBER(SEARCH("ABONO",J223)),EXACT(L223,"P"),EXACT(F223,"P")),"Pendiente / Compromiso","Sin gestionar")))) -> Sin gestionar | P223: =IF(B223="","",IF(E223="","Sin definir",IF(ISNUMBER(SEARCH("ITIL",E223)),"ITIL",IF(ISNUMBER(SEARCH("ISO 27001",E223)),"ISO 27001",IF(ISNUMBER(SEARCH("ISO 42001",E223)),"ISO 42001",IF(ISNUMBER(SEARCH("ISO",E223)),"Otras ISO",IF(ISNUMBER(SEARCH("SCRUM",E223)),"SCRUM",IF(ISNUMBER(SEARCH("BRIDGE",E223)),"BRIDGE",IF(ISNUMBER(SEARCH("CDS",E223)),"CDS",IF(ISNUMBER(SEARCH("TOGAF",E223)),"TOGAF",IF(ISNUMBER(SEARCH("DPI",E223)),"DPI",IF(ISNUMBER(SEARCH("DITS",E223)),"DITS",IF(ISNUMBER(SEARCH("AGILE",E223)),"AGILE",IF(ISNUMBER(SEARCH("Ciberseguridad",E223)),"Ciberseguridad","Otros")))))))))))))) -> ISO 42001 | Q223: =IF(B223="","",IF(ISNUMBER(K223),IF(K223<=3,"1-3 meses",IF(K223<=6,"4-6 meses","+6 meses")),"Sin dato registrado")) -> Sin dato registrado | R223: =IF(OR(B223="",M223=""),"",RANK(M223,$M$3:$M$306)+COUNTIF($M$3:M223,M223)-1) -> 64
B224: Oscar Chocontá Pérez | D224: Ximena | E224: ITIL | I224: 650000 | M224: =IF(B224="","",IF(ISNUMBER(I224),I224,IFERROR(VALUE(SUBSTITUTE(SUBSTITUTE(I224,"$",""),".","")),0))) -> 650000 | N224: =IF(B224="","",PROPER(TRIM(D224))) -> Ximena | O224: =IF(B224="","",IF(OR(ISNUMBER(SEARCH("AL DIA",L224)),ISNUMBER(SEARCH("AL DIA",F224))),"Al día",IF(OR(ISNUMBER(SEARCH("QUIETO",L224)),ISNUMBER(SEARCH("QUIETO",F224)),ISNUMBER(SEARCH("ESPERANDO",L224)),ISNUMBER(SEARCH("ESPERANDO",F224))),"Sin respuesta / Inactivo",IF(OR(ISNUMBER(SEARCH("PENDIENTE",L224)),ISNUMBER(SEARCH("PENDIENTE",F224)),ISNUMBER(SEARCH("COMPROMISO",F224)),ISNUMBER(SEARCH("COMPROMISO",L224)),ISNUMBER(SEARCH("PROCESO",F224)),ISNUMBER(SEARCH("LLAMAR",F224)),ISNUMBER(SEARCH("ABONO",J224)),EXACT(L224,"P"),EXACT(F224,"P")),"Pendiente / Compromiso","Sin gestionar")))) -> Sin gestionar | P224: =IF(B224="","",IF(E224="","Sin definir",IF(ISNUMBER(SEARCH("ITIL",E224)),"ITIL",IF(ISNUMBER(SEARCH("ISO 27001",E224)),"ISO 27001",IF(ISNUMBER(SEARCH("ISO 42001",E224)),"ISO 42001",IF(ISNUMBER(SEARCH("ISO",E224)),"Otras ISO",IF(ISNUMBER(SEARCH("SCRUM",E224)),"SCRUM",IF(ISNUMBER(SEARCH("BRIDGE",E224)),"BRIDGE",IF(ISNUMBER(SEARCH("CDS",E224)),"CDS",IF(ISNUMBER(SEARCH("TOGAF",E224)),"TOGAF",IF(ISNUMBER(SEARCH("DPI",E224)),"DPI",IF(ISNUMBER(SEARCH("DITS",E224)),"DITS",IF(ISNUMBER(SEARCH("AGILE",E224)),"AGILE",IF(ISNUMBER(SEARCH("Ciberseguridad",E224)),"Ciberseguridad","Otros")))))))))))))) -> ITIL | Q224: =IF(B224="","",IF(ISNUMBER(K224),IF(K224<=3,"1-3 meses",IF(K224<=6,"4-6 meses","+6 meses")),"Sin dato registrado")) -> Sin dato registrado | R224: =IF(OR(B224="",M224=""),"",RANK(M224,$M$3:$M$306)+COUNTIF($M$3:M224,M224)-1) -> 40
B225: ANGELA LILIETH MENDEZ MATAMOROS | D225: Sebas | E225: ISO 27001 TCERT | F225: Curso y examen | G225: p cp | I225: 600000 | M225: =IF(B225="","",IF(ISNUMBER(I225),I225,IFERROR(VALUE(SUBSTITUTE(SUBSTITUTE(I225,"$",""),".","")),0))) -> 600000 | N225: =IF(B225="","",PROPER(TRIM(D225))) -> Sebas | O225: =IF(B225="","",IF(OR(ISNUMBER(SEARCH("AL DIA",L225)),ISNUMBER(SEARCH("AL DIA",F225))),"Al día",IF(OR(ISNUMBER(SEARCH("QUIETO",L225)),ISNUMBER(SEARCH("QUIETO",F225)),ISNUMBER(SEARCH("ESPERANDO",L225)),ISNUMBER(SEARCH("ESPERANDO",F225))),"Sin respuesta / Inactivo",IF(OR(ISNUMBER(SEARCH("PENDIENTE",L225)),ISNUMBER(SEARCH("PENDIENTE",F225)),ISNUMBER(SEARCH("COMPROMISO",F225)),ISNUMBER(SEARCH("COMPROMISO",L225)),ISNUMBER(SEARCH("PROCESO",F225)),ISNUMBER(SEARCH("LLAMAR",F225)),ISNUMBER(SEARCH("ABONO",J225)),EXACT(L225,"P"),EXACT(F225,"P")),"Pendiente / Compromiso","Sin gestionar")))) -> Sin gestionar | P225: =IF(B225="","",IF(E225="","Sin definir",IF(ISNUMBER(SEARCH("ITIL",E225)),"ITIL",IF(ISNUMBER(SEARCH("ISO 27001",E225)),"ISO 27001",IF(ISNUMBER(SEARCH("ISO 42001",E225)),"ISO 42001",IF(ISNUMBER(SEARCH("ISO",E225)),"Otras ISO",IF(ISNUMBER(SEARCH("SCRUM",E225)),"SCRUM",IF(ISNUMBER(SEARCH("BRIDGE",E225)),"BRIDGE",IF(ISNUMBER(SEARCH("CDS",E225)),"CDS",IF(ISNUMBER(SEARCH("TOGAF",E225)),"TOGAF",IF(ISNUMBER(SEARCH("DPI",E225)),"DPI",IF(ISNUMBER(SEARCH("DITS",E225)),"DITS",IF(ISNUMBER(SEARCH("AGILE",E225)),"AGILE",IF(ISNUMBER(SEARCH("Ciberseguridad",E225)),"Ciberseguridad","Otros")))))))))))))) -> ISO 27001 | Q225: =IF(B225="","",IF(ISNUMBER(K225),IF(K225<=3,"1-3 meses",IF(K225<=6,"4-6 meses","+6 meses")),"Sin dato registrado")) -> Sin dato registrado | R225: =IF(OR(B225="",M225=""),"",RANK(M225,$M$3:$M$306)+COUNTIF($M$3:M225,M225)-1) -> 44
B226: Jennifer Andrea Joyas Rodriguez | D226: Carolina | E226: BRIDGE | F226: Curso y examen | I226: 250000 | M226: =IF(B226="","",IF(ISNUMBER(I226),I226,IFERROR(VALUE(SUBSTITUTE(SUBSTITUTE(I226,"$",""),".","")),0))) -> 250000 | N226: =IF(B226="","",PROPER(TRIM(D226))) -> Carolina | O226: =IF(B226="","",IF(OR(ISNUMBER(SEARCH("AL DIA",L226)),ISNUMBER(SEARCH("AL DIA",F226))),"Al día",IF(OR(ISNUMBER(SEARCH("QUIETO",L226)),ISNUMBER(SEARCH("QUIETO",F226)),ISNUMBER(SEARCH("ESPERANDO",L226)),ISNUMBER(SEARCH("ESPERANDO",F226))),"Sin respuesta / Inactivo",IF(OR(ISNUMBER(SEARCH("PENDIENTE",L226)),ISNUMBER(SEARCH("PENDIENTE",F226)),ISNUMBER(SEARCH("COMPROMISO",F226)),ISNUMBER(SEARCH("COMPROMISO",L226)),ISNUMBER(SEARCH("PROCESO",F226)),ISNUMBER(SEARCH("LLAMAR",F226)),ISNUMBER(SEARCH("ABONO",J226)),EXACT(L226,"P"),EXACT(F226,"P")),"Pendiente / Compromiso","Sin gestionar")))) -> Sin gestionar | P226: =IF(B226="","",IF(E226="","Sin definir",IF(ISNUMBER(SEARCH("ITIL",E226)),"ITIL",IF(ISNUMBER(SEARCH("ISO 27001",E226)),"ISO 27001",IF(ISNUMBER(SEARCH("ISO 42001",E226)),"ISO 42001",IF(ISNUMBER(SEARCH("ISO",E226)),"Otras ISO",IF(ISNUMBER(SEARCH("SCRUM",E226)),"SCRUM",IF(ISNUMBER(SEARCH("BRIDGE",E226)),"BRIDGE",IF(ISNUMBER(SEARCH("CDS",E226)),"CDS",IF(ISNUMBER(SEARCH("TOGAF",E226)),"TOGAF",IF(ISNUMBER(SEARCH("DPI",E226)),"DPI",IF(ISNUMBER(SEARCH("DITS",E226)),"DITS",IF(ISNUMBER(SEARCH("AGILE",E226)),"AGILE",IF(ISNUMBER(SEARCH("Ciberseguridad",E226)),"Ciberseguridad","Otros")))))))))))))) -> BRIDGE | Q226: =IF(B226="","",IF(ISNUMBER(K226),IF(K226<=3,"1-3 meses",IF(K226<=6,"4-6 meses","+6 meses")),"Sin dato registrado")) -> Sin dato registrado | R226: =IF(OR(B226="",M226=""),"",RANK(M226,$M$3:$M$306)+COUNTIF($M$3:M226,M226)-1) -> 58
B227: LEIDY JANNETH SORIANO CASTAÑEDA | D227: Carolina | E227: BRIDGE | F227: Curso y examen | I227: 400000 | M227: =IF(B227="","",IF(ISNUMBER(I227),I227,IFERROR(VALUE(SUBSTITUTE(SUBSTITUTE(I227,"$",""),".","")),0))) -> 400000 | N227: =IF(B227="","",PROPER(TRIM(D227))) -> Carolina | O227: =IF(B227="","",IF(OR(ISNUMBER(SEARCH("AL DIA",L227)),ISNUMBER(SEARCH("AL DIA",F227))),"Al día",IF(OR(ISNUMBER(SEARCH("QUIETO",L227)),ISNUMBER(SEARCH("QUIETO",F227)),ISNUMBER(SEARCH("ESPERANDO",L227)),ISNUMBER(SEARCH("ESPERANDO",F227))),"Sin respuesta / Inactivo",IF(OR(ISNUMBER(SEARCH("PENDIENTE",L227)),ISNUMBER(SEARCH("PENDIENTE",F227)),ISNUMBER(SEARCH("COMPROMISO",F227)),ISNUMBER(SEARCH("COMPROMISO",L227)),ISNUMBER(SEARCH("PROCESO",F227)),ISNUMBER(SEARCH("LLAMAR",F227)),ISNUMBER(SEARCH("ABONO",J227)),EXACT(L227,"P"),EXACT(F227,"P")),"Pendiente / Compromiso","Sin gestionar")))) -> Sin gestionar | P227: =IF(B227="","",IF(E227="","Sin definir",IF(ISNUMBER(SEARCH("ITIL",E227)),"ITIL",IF(ISNUMBER(SEARCH("ISO 27001",E227)),"ISO 27001",IF(ISNUMBER(SEARCH("ISO 42001",E227)),"ISO 42001",IF(ISNUMBER(SEARCH("ISO",E227)),"Otras ISO",IF(ISNUMBER(SEARCH("SCRUM",E227)),"SCRUM",IF(ISNUMBER(SEARCH("BRIDGE",E227)),"BRIDGE",IF(ISNUMBER(SEARCH("CDS",E227)),"CDS",IF(ISNUMBER(SEARCH("TOGAF",E227)),"TOGAF",IF(ISNUMBER(SEARCH("DPI",E227)),"DPI",IF(ISNUMBER(SEARCH("DITS",E227)),"DITS",IF(ISNUMBER(SEARCH("AGILE",E227)),"AGILE",IF(ISNUMBER(SEARCH("Ciberseguridad",E227)),"Ciberseguridad","Otros")))))))))))))) -> BRIDGE | Q227: =IF(B227="","",IF(ISNUMBER(K227),IF(K227<=3,"1-3 meses",IF(K227<=6,"4-6 meses","+6 meses")),"Sin dato registrado")) -> Sin dato registrado | R227: =IF(OR(B227="",M227=""),"",RANK(M227,$M$3:$M$306)+COUNTIF($M$3:M227,M227)-1) -> 49
B228: Angélica Jazmín Soler Barrera | D228: Carolina | E228: ITIL V5 | F228: Curso y examen | I228: 400000 | M228: =IF(B228="","",IF(ISNUMBER(I228),I228,IFERROR(VALUE(SUBSTITUTE(SUBSTITUTE(I228,"$",""),".","")),0))) -> 400000 | N228: =IF(B228="","",PROPER(TRIM(D228))) -> Carolina | O228: =IF(B228="","",IF(OR(ISNUMBER(SEARCH("AL DIA",L228)),ISNUMBER(SEARCH("AL DIA",F228))),"Al día",IF(OR(ISNUMBER(SEARCH("QUIETO",L228)),ISNUMBER(SEARCH("QUIETO",F228)),ISNUMBER(SEARCH("ESPERANDO",L228)),ISNUMBER(SEARCH("ESPERANDO",F228))),"Sin respuesta / Inactivo",IF(OR(ISNUMBER(SEARCH("PENDIENTE",L228)),ISNUMBER(SEARCH("PENDIENTE",F228)),ISNUMBER(SEARCH("COMPROMISO",F228)),ISNUMBER(SEARCH("COMPROMISO",L228)),ISNUMBER(SEARCH("PROCESO",F228)),ISNUMBER(SEARCH("LLAMAR",F228)),ISNUMBER(SEARCH("ABONO",J228)),EXACT(L228,"P"),EXACT(F228,"P")),"Pendiente / Compromiso","Sin gestionar")))) -> Sin gestionar | P228: =IF(B228="","",IF(E228="","Sin definir",IF(ISNUMBER(SEARCH("ITIL",E228)),"ITIL",IF(ISNUMBER(SEARCH("ISO 27001",E228)),"ISO 27001",IF(ISNUMBER(SEARCH("ISO 42001",E228)),"ISO 42001",IF(ISNUMBER(SEARCH("ISO",E228)),"Otras ISO",IF(ISNUMBER(SEARCH("SCRUM",E228)),"SCRUM",IF(ISNUMBER(SEARCH("BRIDGE",E228)),"BRIDGE",IF(ISNUMBER(SEARCH("CDS",E228)),"CDS",IF(ISNUMBER(SEARCH("TOGAF",E228)),"TOGAF",IF(ISNUMBER(SEARCH("DPI",E228)),"DPI",IF(ISNUMBER(SEARCH("DITS",E228)),"DITS",IF(ISNUMBER(SEARCH("AGILE",E228)),"AGILE",IF(ISNUMBER(SEARCH("Ciberseguridad",E228)),"Ciberseguridad","Otros")))))))))))))) -> ITIL | Q228: =IF(B228="","",IF(ISNUMBER(K228),IF(K228<=3,"1-3 meses",IF(K228<=6,"4-6 meses","+6 meses")),"Sin dato registrado")) -> Sin dato registrado | R228: =IF(OR(B228="",M228=""),"",RANK(M228,$M$3:$M$306)+COUNTIF($M$3:M228,M228)-1) -> 50
B229: Jorge Andrés Díaz Torres | D229: Carolina | E229: BRIDGE | F229: Curso y examen | I229: 400000 | M229: =IF(B229="","",IF(ISNUMBER(I229),I229,IFERROR(VALUE(SUBSTITUTE(SUBSTITUTE(I229,"$",""),".","")),0))) -> 400000 | N229: =IF(B229="","",PROPER(TRIM(D229))) -> Carolina | O229: =IF(B229="","",IF(OR(ISNUMBER(SEARCH("AL DIA",L229)),ISNUMBER(SEARCH("AL DIA",F229))),"Al día",IF(OR(ISNUMBER(SEARCH("QUIETO",L229)),ISNUMBER(SEARCH("QUIETO",F229)),ISNUMBER(SEARCH("ESPERANDO",L229)),ISNUMBER(SEARCH("ESPERANDO",F229))),"Sin respuesta / Inactivo",IF(OR(ISNUMBER(SEARCH("PENDIENTE",L229)),ISNUMBER(SEARCH("PENDIENTE",F229)),ISNUMBER(SEARCH("COMPROMISO",F229)),ISNUMBER(SEARCH("COMPROMISO",L229)),ISNUMBER(SEARCH("PROCESO",F229)),ISNUMBER(SEARCH("LLAMAR",F229)),ISNUMBER(SEARCH("ABONO",J229)),EXACT(L229,"P"),EXACT(F229,"P")),"Pendiente / Compromiso","Sin gestionar")))) -> Sin gestionar | P229: =IF(B229="","",IF(E229="","Sin definir",IF(ISNUMBER(SEARCH("ITIL",E229)),"ITIL",IF(ISNUMBER(SEARCH("ISO 27001",E229)),"ISO 27001",IF(ISNUMBER(SEARCH("ISO 42001",E229)),"ISO 42001",IF(ISNUMBER(SEARCH("ISO",E229)),"Otras ISO",IF(ISNUMBER(SEARCH("SCRUM",E229)),"SCRUM",IF(ISNUMBER(SEARCH("BRIDGE",E229)),"BRIDGE",IF(ISNUMBER(SEARCH("CDS",E229)),"CDS",IF(ISNUMBER(SEARCH("TOGAF",E229)),"TOGAF",IF(ISNUMBER(SEARCH("DPI",E229)),"DPI",IF(ISNUMBER(SEARCH("DITS",E229)),"DITS",IF(ISNUMBER(SEARCH("AGILE",E229)),"AGILE",IF(ISNUMBER(SEARCH("Ciberseguridad",E229)),"Ciberseguridad","Otros")))))))))))))) -> BRIDGE | Q229: =IF(B229="","",IF(ISNUMBER(K229),IF(K229<=3,"1-3 meses",IF(K229<=6,"4-6 meses","+6 meses")),"Sin dato registrado")) -> Sin dato registrado | R229: =IF(OR(B229="",M229=""),"",RANK(M229,$M$3:$M$306)+COUNTIF($M$3:M229,M229)-1) -> 51
B230: Esneyder Herreño | D230: Ximena | E230: ITIL V5 | F230: Curso y examen | I230: 850000 | M230: =IF(B230="","",IF(ISNUMBER(I230),I230,IFERROR(VALUE(SUBSTITUTE(SUBSTITUTE(I230,"$",""),".","")),0))) -> 850000 | N230: =IF(B230="","",PROPER(TRIM(D230))) -> Ximena | O230: =IF(B230="","",IF(OR(ISNUMBER(SEARCH("AL DIA",L230)),ISNUMBER(SEARCH("AL DIA",F230))),"Al día",IF(OR(ISNUMBER(SEARCH("QUIETO",L230)),ISNUMBER(SEARCH("QUIETO",F230)),ISNUMBER(SEARCH("ESPERANDO",L230)),ISNUMBER(SEARCH("ESPERANDO",F230))),"Sin respuesta / Inactivo",IF(OR(ISNUMBER(SEARCH("PENDIENTE",L230)),ISNUMBER(SEARCH("PENDIENTE",F230)),ISNUMBER(SEARCH("COMPROMISO",F230)),ISNUMBER(SEARCH("COMPROMISO",L230)),ISNUMBER(SEARCH("PROCESO",F230)),ISNUMBER(SEARCH("LLAMAR",F230)),ISNUMBER(SEARCH("ABONO",J230)),EXACT(L230,"P"),EXACT(F230,"P")),"Pendiente / Compromiso","Sin gestionar")))) -> Sin gestionar | P230: =IF(B230="","",IF(E230="","Sin definir",IF(ISNUMBER(SEARCH("ITIL",E230)),"ITIL",IF(ISNUMBER(SEARCH("ISO 27001",E230)),"ISO 27001",IF(ISNUMBER(SEARCH("ISO 42001",E230)),"ISO 42001",IF(ISNUMBER(SEARCH("ISO",E230)),"Otras ISO",IF(ISNUMBER(SEARCH("SCRUM",E230)),"SCRUM",IF(ISNUMBER(SEARCH("BRIDGE",E230)),"BRIDGE",IF(ISNUMBER(SEARCH("CDS",E230)),"CDS",IF(ISNUMBER(SEARCH("TOGAF",E230)),"TOGAF",IF(ISNUMBER(SEARCH("DPI",E230)),"DPI",IF(ISNUMBER(SEARCH("DITS",E230)),"DITS",IF(ISNUMBER(SEARCH("AGILE",E230)),"AGILE",IF(ISNUMBER(SEARCH("Ciberseguridad",E230)),"Ciberseguridad","Otros")))))))))))))) -> ITIL | Q230: =IF(B230="","",IF(ISNUMBER(K230),IF(K230<=3,"1-3 meses",IF(K230<=6,"4-6 meses","+6 meses")),"Sin dato registrado")) -> Sin dato registrado | R230: =IF(OR(B230="",M230=""),"",RANK(M230,$M$3:$M$306)+COUNTIF($M$3:M230,M230)-1) -> 30
B231: ERICK RAMON ORTIZ FIGUEROA | D231: Carolina | E231: BRIDGE | F231: Curso y examen | I231: 500000 | M231: =IF(B231="","",IF(ISNUMBER(I231),I231,IFERROR(VALUE(SUBSTITUTE(SUBSTITUTE(I231,"$",""),".","")),0))) -> 500000 | N231: =IF(B231="","",PROPER(TRIM(D231))) -> Carolina | O231: =IF(B231="","",IF(OR(ISNUMBER(SEARCH("AL DIA",L231)),ISNUMBER(SEARCH("AL DIA",F231))),"Al día",IF(OR(ISNUMBER(SEARCH("QUIETO",L231)),ISNUMBER(SEARCH("QUIETO",F231)),ISNUMBER(SEARCH("ESPERANDO",L231)),ISNUMBER(SEARCH("ESPERANDO",F231))),"Sin respuesta / Inactivo",IF(OR(ISNUMBER(SEARCH("PENDIENTE",L231)),ISNUMBER(SEARCH("PENDIENTE",F231)),ISNUMBER(SEARCH("COMPROMISO",F231)),ISNUMBER(SEARCH("COMPROMISO",L231)),ISNUMBER(SEARCH("PROCESO",F231)),ISNUMBER(SEARCH("LLAMAR",F231)),ISNUMBER(SEARCH("ABONO",J231)),EXACT(L231,"P"),EXACT(F231,"P")),"Pendiente / Compromiso","Sin gestionar")))) -> Sin gestionar | P231: =IF(B231="","",IF(E231="","Sin definir",IF(ISNUMBER(SEARCH("ITIL",E231)),"ITIL",IF(ISNUMBER(SEARCH("ISO 27001",E231)),"ISO 27001",IF(ISNUMBER(SEARCH("ISO 42001",E231)),"ISO 42001",IF(ISNUMBER(SEARCH("ISO",E231)),"Otras ISO",IF(ISNUMBER(SEARCH("SCRUM",E231)),"SCRUM",IF(ISNUMBER(SEARCH("BRIDGE",E231)),"BRIDGE",IF(ISNUMBER(SEARCH("CDS",E231)),"CDS",IF(ISNUMBER(SEARCH("TOGAF",E231)),"TOGAF",IF(ISNUMBER(SEARCH("DPI",E231)),"DPI",IF(ISNUMBER(SEARCH("DITS",E231)),"DITS",IF(ISNUMBER(SEARCH("AGILE",E231)),"AGILE",IF(ISNUMBER(SEARCH("Ciberseguridad",E231)),"Ciberseguridad","Otros")))))))))))))) -> BRIDGE | Q231: =IF(B231="","",IF(ISNUMBER(K231),IF(K231<=3,"1-3 meses",IF(K231<=6,"4-6 meses","+6 meses")),"Sin dato registrado")) -> Sin dato registrado | R231: =IF(OR(B231="",M231=""),"",RANK(M231,$M$3:$M$306)+COUNTIF($M$3:M231,M231)-1) -> 48
B232: Luis Eduardo Peña Plazas | D232: Carolina | E232: ISO 42001 | F232: Curso y examen | I232: 800000 | M232: =IF(B232="","",IF(ISNUMBER(I232),I232,IFERROR(VALUE(SUBSTITUTE(SUBSTITUTE(I232,"$",""),".","")),0))) -> 800000 | N232: =IF(B232="","",PROPER(TRIM(D232))) -> Carolina | O232: =IF(B232="","",IF(OR(ISNUMBER(SEARCH("AL DIA",L232)),ISNUMBER(SEARCH("AL DIA",F232))),"Al día",IF(OR(ISNUMBER(SEARCH("QUIETO",L232)),ISNUMBER(SEARCH("QUIETO",F232)),ISNUMBER(SEARCH("ESPERANDO",L232)),ISNUMBER(SEARCH("ESPERANDO",F232))),"Sin respuesta / Inactivo",IF(OR(ISNUMBER(SEARCH("PENDIENTE",L232)),ISNUMBER(SEARCH("PENDIENTE",F232)),ISNUMBER(SEARCH("COMPROMISO",F232)),ISNUMBER(SEARCH("COMPROMISO",L232)),ISNUMBER(SEARCH("PROCESO",F232)),ISNUMBER(SEARCH("LLAMAR",F232)),ISNUMBER(SEARCH("ABONO",J232)),EXACT(L232,"P"),EXACT(F232,"P")),"Pendiente / Compromiso","Sin gestionar")))) -> Sin gestionar | P232: =IF(B232="","",IF(E232="","Sin definir",IF(ISNUMBER(SEARCH("ITIL",E232)),"ITIL",IF(ISNUMBER(SEARCH("ISO 27001",E232)),"ISO 27001",IF(ISNUMBER(SEARCH("ISO 42001",E232)),"ISO 42001",IF(ISNUMBER(SEARCH("ISO",E232)),"Otras ISO",IF(ISNUMBER(SEARCH("SCRUM",E232)),"SCRUM",IF(ISNUMBER(SEARCH("BRIDGE",E232)),"BRIDGE",IF(ISNUMBER(SEARCH("CDS",E232)),"CDS",IF(ISNUMBER(SEARCH("TOGAF",E232)),"TOGAF",IF(ISNUMBER(SEARCH("DPI",E232)),"DPI",IF(ISNUMBER(SEARCH("DITS",E232)),"DITS",IF(ISNUMBER(SEARCH("AGILE",E232)),"AGILE",IF(ISNUMBER(SEARCH("Ciberseguridad",E232)),"Ciberseguridad","Otros")))))))))))))) -> ISO 42001 | Q232: =IF(B232="","",IF(ISNUMBER(K232),IF(K232<=3,"1-3 meses",IF(K232<=6,"4-6 meses","+6 meses")),"Sin dato registrado")) -> Sin dato registrado | R232: =IF(OR(B232="",M232=""),"",RANK(M232,$M$3:$M$306)+COUNTIF($M$3:M232,M232)-1) -> 32
B233: Natalia Fernanda Huertas Rodriguez | D233: Ximena | I233: 1600000 | M233: =IF(B233="","",IF(ISNUMBER(I233),I233,IFERROR(VALUE(SUBSTITUTE(SUBSTITUTE(I233,"$",""),".","")),0))) -> 1600000 | N233: =IF(B233="","",PROPER(TRIM(D233))) -> Ximena | O233: =IF(B233="","",IF(OR(ISNUMBER(SEARCH("AL DIA",L233)),ISNUMBER(SEARCH("AL DIA",F233))),"Al día",IF(OR(ISNUMBER(SEARCH("QUIETO",L233)),ISNUMBER(SEARCH("QUIETO",F233)),ISNUMBER(SEARCH("ESPERANDO",L233)),ISNUMBER(SEARCH("ESPERANDO",F233))),"Sin respuesta / Inactivo",IF(OR(ISNUMBER(SEARCH("PENDIENTE",L233)),ISNUMBER(SEARCH("PENDIENTE",F233)),ISNUMBER(SEARCH("COMPROMISO",F233)),ISNUMBER(SEARCH("COMPROMISO",L233)),ISNUMBER(SEARCH("PROCESO",F233)),ISNUMBER(SEARCH("LLAMAR",F233)),ISNUMBER(SEARCH("ABONO",J233)),EXACT(L233,"P"),EXACT(F233,"P")),"Pendiente / Compromiso","Sin gestionar")))) -> Sin gestionar | P233: =IF(B233="","",IF(E233="","Sin definir",IF(ISNUMBER(SEARCH("ITIL",E233)),"ITIL",IF(ISNUMBER(SEARCH("ISO 27001",E233)),"ISO 27001",IF(ISNUMBER(SEARCH("ISO 42001",E233)),"ISO 42001",IF(ISNUMBER(SEARCH("ISO",E233)),"Otras ISO",IF(ISNUMBER(SEARCH("SCRUM",E233)),"SCRUM",IF(ISNUMBER(SEARCH("BRIDGE",E233)),"BRIDGE",IF(ISNUMBER(SEARCH("CDS",E233)),"CDS",IF(ISNUMBER(SEARCH("TOGAF",E233)),"TOGAF",IF(ISNUMBER(SEARCH("DPI",E233)),"DPI",IF(ISNUMBER(SEARCH("DITS",E233)),"DITS",IF(ISNUMBER(SEARCH("AGILE",E233)),"AGILE",IF(ISNUMBER(SEARCH("Ciberseguridad",E233)),"Ciberseguridad","Otros")))))))))))))) -> Sin definir | Q233: =IF(B233="","",IF(ISNUMBER(K233),IF(K233<=3,"1-3 meses",IF(K233<=6,"4-6 meses","+6 meses")),"Sin dato registrado")) -> Sin dato registrado | R233: =IF(OR(B233="",M233=""),"",RANK(M233,$M$3:$M$306)+COUNTIF($M$3:M233,M233)-1) -> 7
B234: Diana Carolina Rodriguez | D234: Ximena | I234: 650000 | M234: =IF(B234="","",IF(ISNUMBER(I234),I234,IFERROR(VALUE(SUBSTITUTE(SUBSTITUTE(I234,"$",""),".","")),0))) -> 650000 | N234: =IF(B234="","",PROPER(TRIM(D234))) -> Ximena | O234: =IF(B234="","",IF(OR(ISNUMBER(SEARCH("AL DIA",L234)),ISNUMBER(SEARCH("AL DIA",F234))),"Al día",IF(OR(ISNUMBER(SEARCH("QUIETO",L234)),ISNUMBER(SEARCH("QUIETO",F234)),ISNUMBER(SEARCH("ESPERANDO",L234)),ISNUMBER(SEARCH("ESPERANDO",F234))),"Sin respuesta / Inactivo",IF(OR(ISNUMBER(SEARCH("PENDIENTE",L234)),ISNUMBER(SEARCH("PENDIENTE",F234)),ISNUMBER(SEARCH("COMPROMISO",F234)),ISNUMBER(SEARCH("COMPROMISO",L234)),ISNUMBER(SEARCH("PROCESO",F234)),ISNUMBER(SEARCH("LLAMAR",F234)),ISNUMBER(SEARCH("ABONO",J234)),EXACT(L234,"P"),EXACT(F234,"P")),"Pendiente / Compromiso","Sin gestionar")))) -> Sin gestionar | P234: =IF(B234="","",IF(E234="","Sin definir",IF(ISNUMBER(SEARCH("ITIL",E234)),"ITIL",IF(ISNUMBER(SEARCH("ISO 27001",E234)),"ISO 27001",IF(ISNUMBER(SEARCH("ISO 42001",E234)),"ISO 42001",IF(ISNUMBER(SEARCH("ISO",E234)),"Otras ISO",IF(ISNUMBER(SEARCH("SCRUM",E234)),"SCRUM",IF(ISNUMBER(SEARCH("BRIDGE",E234)),"BRIDGE",IF(ISNUMBER(SEARCH("CDS",E234)),"CDS",IF(ISNUMBER(SEARCH("TOGAF",E234)),"TOGAF",IF(ISNUMBER(SEARCH("DPI",E234)),"DPI",IF(ISNUMBER(SEARCH("DITS",E234)),"DITS",IF(ISNUMBER(SEARCH("AGILE",E234)),"AGILE",IF(ISNUMBER(SEARCH("Ciberseguridad",E234)),"Ciberseguridad","Otros")))))))))))))) -> Sin definir | Q234: =IF(B234="","",IF(ISNUMBER(K234),IF(K234<=3,"1-3 meses",IF(K234<=6,"4-6 meses","+6 meses")),"Sin dato registrado")) -> Sin dato registrado | R234: =IF(OR(B234="",M234=""),"",RANK(M234,$M$3:$M$306)+COUNTIF($M$3:M234,M234)-1) -> 41
B235: Diego Alexander González Calvo | D235: Sebas | I235: 1400000 | M235: =IF(B235="","",IF(ISNUMBER(I235),I235,IFERROR(VALUE(SUBSTITUTE(SUBSTITUTE(I235,"$",""),".","")),0))) -> 1400000 | N235: =IF(B235="","",PROPER(TRIM(D235))) -> Sebas | O235: =IF(B235="","",IF(OR(ISNUMBER(SEARCH("AL DIA",L235)),ISNUMBER(SEARCH("AL DIA",F235))),"Al día",IF(OR(ISNUMBER(SEARCH("QUIETO",L235)),ISNUMBER(SEARCH("QUIETO",F235)),ISNUMBER(SEARCH("ESPERANDO",L235)),ISNUMBER(SEARCH("ESPERANDO",F235))),"Sin respuesta / Inactivo",IF(OR(ISNUMBER(SEARCH("PENDIENTE",L235)),ISNUMBER(SEARCH("PENDIENTE",F235)),ISNUMBER(SEARCH("COMPROMISO",F235)),ISNUMBER(SEARCH("COMPROMISO",L235)),ISNUMBER(SEARCH("PROCESO",F235)),ISNUMBER(SEARCH("LLAMAR",F235)),ISNUMBER(SEARCH("ABONO",J235)),EXACT(L235,"P"),EXACT(F235,"P")),"Pendiente / Compromiso","Sin gestionar")))) -> Sin gestionar | P235: =IF(B235="","",IF(E235="","Sin definir",IF(ISNUMBER(SEARCH("ITIL",E235)),"ITIL",IF(ISNUMBER(SEARCH("ISO 27001",E235)),"ISO 27001",IF(ISNUMBER(SEARCH("ISO 42001",E235)),"ISO 42001",IF(ISNUMBER(SEARCH("ISO",E235)),"Otras ISO",IF(ISNUMBER(SEARCH("SCRUM",E235)),"SCRUM",IF(ISNUMBER(SEARCH("BRIDGE",E235)),"BRIDGE",IF(ISNUMBER(SEARCH("CDS",E235)),"CDS",IF(ISNUMBER(SEARCH("TOGAF",E235)),"TOGAF",IF(ISNUMBER(SEARCH("DPI",E235)),"DPI",IF(ISNUMBER(SEARCH("DITS",E235)),"DITS",IF(ISNUMBER(SEARCH("AGILE",E235)),"AGILE",IF(ISNUMBER(SEARCH("Ciberseguridad",E235)),"Ciberseguridad","Otros")))))))))))))) -> Sin definir | Q235: =IF(B235="","",IF(ISNUMBER(K235),IF(K235<=3,"1-3 meses",IF(K235<=6,"4-6 meses","+6 meses")),"Sin dato registrado")) -> Sin dato registrado | R235: =IF(OR(B235="",M235=""),"",RANK(M235,$M$3:$M$306)+COUNTIF($M$3:M235,M235)-1) -> 13
B236: Maria Soraya Serna Torres | D236: Ximena | I236: 680000 | J236: 31 jul y 31 ago | M236: =IF(B236="","",IF(ISNUMBER(I236),I236,IFERROR(VALUE(SUBSTITUTE(SUBSTITUTE(I236,"$",""),".","")),0))) -> 680000 | N236: =IF(B236="","",PROPER(TRIM(D236))) -> Ximena | O236: =IF(B236="","",IF(OR(ISNUMBER(SEARCH("AL DIA",L236)),ISNUMBER(SEARCH("AL DIA",F236))),"Al día",IF(OR(ISNUMBER(SEARCH("QUIETO",L236)),ISNUMBER(SEARCH("QUIETO",F236)),ISNUMBER(SEARCH("ESPERANDO",L236)),ISNUMBER(SEARCH("ESPERANDO",F236))),"Sin respuesta / Inactivo",IF(OR(ISNUMBER(SEARCH("PENDIENTE",L236)),ISNUMBER(SEARCH("PENDIENTE",F236)),ISNUMBER(SEARCH("COMPROMISO",F236)),ISNUMBER(SEARCH("COMPROMISO",L236)),ISNUMBER(SEARCH("PROCESO",F236)),ISNUMBER(SEARCH("LLAMAR",F236)),ISNUMBER(SEARCH("ABONO",J236)),EXACT(L236,"P"),EXACT(F236,"P")),"Pendiente / Compromiso","Sin gestionar")))) -> Sin gestionar | P236: =IF(B236="","",IF(E236="","Sin definir",IF(ISNUMBER(SEARCH("ITIL",E236)),"ITIL",IF(ISNUMBER(SEARCH("ISO 27001",E236)),"ISO 27001",IF(ISNUMBER(SEARCH("ISO 42001",E236)),"ISO 42001",IF(ISNUMBER(SEARCH("ISO",E236)),"Otras ISO",IF(ISNUMBER(SEARCH("SCRUM",E236)),"SCRUM",IF(ISNUMBER(SEARCH("BRIDGE",E236)),"BRIDGE",IF(ISNUMBER(SEARCH("CDS",E236)),"CDS",IF(ISNUMBER(SEARCH("TOGAF",E236)),"TOGAF",IF(ISNUMBER(SEARCH("DPI",E236)),"DPI",IF(ISNUMBER(SEARCH("DITS",E236)),"DITS",IF(ISNUMBER(SEARCH("AGILE",E236)),"AGILE",IF(ISNUMBER(SEARCH("Ciberseguridad",E236)),"Ciberseguridad","Otros")))))))))))))) -> Sin definir | Q236: =IF(B236="","",IF(ISNUMBER(K236),IF(K236<=3,"1-3 meses",IF(K236<=6,"4-6 meses","+6 meses")),"Sin dato registrado")) -> Sin dato registrado | R236: =IF(OR(B236="",M236=""),"",RANK(M236,$M$3:$M$306)+COUNTIF($M$3:M236,M236)-1) -> 35
B237: Nelson Saul Gonzalez Jimenez | D237: Ximena | I237: 285000 | M237: =IF(B237="","",IF(ISNUMBER(I237),I237,IFERROR(VALUE(SUBSTITUTE(SUBSTITUTE(I237,"$",""),".","")),0))) -> 285000 | N237: =IF(B237="","",PROPER(TRIM(D237))) -> Ximena | O237: =IF(B237="","",IF(OR(ISNUMBER(SEARCH("AL DIA",L237)),ISNUMBER(SEARCH("AL DIA",F237))),"Al día",IF(OR(ISNUMBER(SEARCH("QUIETO",L237)),ISNUMBER(SEARCH("QUIETO",F237)),ISNUMBER(SEARCH("ESPERANDO",L237)),ISNUMBER(SEARCH("ESPERANDO",F237))),"Sin respuesta / Inactivo",IF(OR(ISNUMBER(SEARCH("PENDIENTE",L237)),ISNUMBER(SEARCH("PENDIENTE",F237)),ISNUMBER(SEARCH("COMPROMISO",F237)),ISNUMBER(SEARCH("COMPROMISO",L237)),ISNUMBER(SEARCH("PROCESO",F237)),ISNUMBER(SEARCH("LLAMAR",F237)),ISNUMBER(SEARCH("ABONO",J237)),EXACT(L237,"P"),EXACT(F237,"P")),"Pendiente / Compromiso","Sin gestionar")))) -> Sin gestionar | P237: =IF(B237="","",IF(E237="","Sin definir",IF(ISNUMBER(SEARCH("ITIL",E237)),"ITIL",IF(ISNUMBER(SEARCH("ISO 27001",E237)),"ISO 27001",IF(ISNUMBER(SEARCH("ISO 42001",E237)),"ISO 42001",IF(ISNUMBER(SEARCH("ISO",E237)),"Otras ISO",IF(ISNUMBER(SEARCH("SCRUM",E237)),"SCRUM",IF(ISNUMBER(SEARCH("BRIDGE",E237)),"BRIDGE",IF(ISNUMBER(SEARCH("CDS",E237)),"CDS",IF(ISNUMBER(SEARCH("TOGAF",E237)),"TOGAF",IF(ISNUMBER(SEARCH("DPI",E237)),"DPI",IF(ISNUMBER(SEARCH("DITS",E237)),"DITS",IF(ISNUMBER(SEARCH("AGILE",E237)),"AGILE",IF(ISNUMBER(SEARCH("Ciberseguridad",E237)),"Ciberseguridad","Otros")))))))))))))) -> Sin definir | Q237: =IF(B237="","",IF(ISNUMBER(K237),IF(K237<=3,"1-3 meses",IF(K237<=6,"4-6 meses","+6 meses")),"Sin dato registrado")) -> Sin dato registrado | R237: =IF(OR(B237="",M237=""),"",RANK(M237,$M$3:$M$306)+COUNTIF($M$3:M237,M237)-1) -> 56
B238: Niver Alberto López Gómez | D238: Carolina | E238: itil v5 | I238: 1600000 | M238: =IF(B238="","",IF(ISNUMBER(I238),I238,IFERROR(VALUE(SUBSTITUTE(SUBSTITUTE(I238,"$",""),".","")),0))) -> 1600000 | N238: =IF(B238="","",PROPER(TRIM(D238))) -> Carolina | O238: =IF(B238="","",IF(OR(ISNUMBER(SEARCH("AL DIA",L238)),ISNUMBER(SEARCH("AL DIA",F238))),"Al día",IF(OR(ISNUMBER(SEARCH("QUIETO",L238)),ISNUMBER(SEARCH("QUIETO",F238)),ISNUMBER(SEARCH("ESPERANDO",L238)),ISNUMBER(SEARCH("ESPERANDO",F238))),"Sin respuesta / Inactivo",IF(OR(ISNUMBER(SEARCH("PENDIENTE",L238)),ISNUMBER(SEARCH("PENDIENTE",F238)),ISNUMBER(SEARCH("COMPROMISO",F238)),ISNUMBER(SEARCH("COMPROMISO",L238)),ISNUMBER(SEARCH("PROCESO",F238)),ISNUMBER(SEARCH("LLAMAR",F238)),ISNUMBER(SEARCH("ABONO",J238)),EXACT(L238,"P"),EXACT(F238,"P")),"Pendiente / Compromiso","Sin gestionar")))) -> Sin gestionar | P238: =IF(B238="","",IF(E238="","Sin definir",IF(ISNUMBER(SEARCH("ITIL",E238)),"ITIL",IF(ISNUMBER(SEARCH("ISO 27001",E238)),"ISO 27001",IF(ISNUMBER(SEARCH("ISO 42001",E238)),"ISO 42001",IF(ISNUMBER(SEARCH("ISO",E238)),"Otras ISO",IF(ISNUMBER(SEARCH("SCRUM",E238)),"SCRUM",IF(ISNUMBER(SEARCH("BRIDGE",E238)),"BRIDGE",IF(ISNUMBER(SEARCH("CDS",E238)),"CDS",IF(ISNUMBER(SEARCH("TOGAF",E238)),"TOGAF",IF(ISNUMBER(SEARCH("DPI",E238)),"DPI",IF(ISNUMBER(SEARCH("DITS",E238)),"DITS",IF(ISNUMBER(SEARCH("AGILE",E238)),"AGILE",IF(ISNUMBER(SEARCH("Ciberseguridad",E238)),"Ciberseguridad","Otros")))))))))))))) -> ITIL | Q238: =IF(B238="","",IF(ISNUMBER(K238),IF(K238<=3,"1-3 meses",IF(K238<=6,"4-6 meses","+6 meses")),"Sin dato registrado")) -> Sin dato registrado | R238: =IF(OR(B238="",M238=""),"",RANK(M238,$M$3:$M$306)+COUNTIF($M$3:M238,M238)-1) -> 8
B239: Mauricio Villate Granados | D239: Carolina | I239: 1470000 | M239: =IF(B239="","",IF(ISNUMBER(I239),I239,IFERROR(VALUE(SUBSTITUTE(SUBSTITUTE(I239,"$",""),".","")),0))) -> 1470000 | N239: =IF(B239="","",PROPER(TRIM(D239))) -> Carolina | O239: =IF(B239="","",IF(OR(ISNUMBER(SEARCH("AL DIA",L239)),ISNUMBER(SEARCH("AL DIA",F239))),"Al día",IF(OR(ISNUMBER(SEARCH("QUIETO",L239)),ISNUMBER(SEARCH("QUIETO",F239)),ISNUMBER(SEARCH("ESPERANDO",L239)),ISNUMBER(SEARCH("ESPERANDO",F239))),"Sin respuesta / Inactivo",IF(OR(ISNUMBER(SEARCH("PENDIENTE",L239)),ISNUMBER(SEARCH("PENDIENTE",F239)),ISNUMBER(SEARCH("COMPROMISO",F239)),ISNUMBER(SEARCH("COMPROMISO",L239)),ISNUMBER(SEARCH("PROCESO",F239)),ISNUMBER(SEARCH("LLAMAR",F239)),ISNUMBER(SEARCH("ABONO",J239)),EXACT(L239,"P"),EXACT(F239,"P")),"Pendiente / Compromiso","Sin gestionar")))) -> Sin gestionar | P239: =IF(B239="","",IF(E239="","Sin definir",IF(ISNUMBER(SEARCH("ITIL",E239)),"ITIL",IF(ISNUMBER(SEARCH("ISO 27001",E239)),"ISO 27001",IF(ISNUMBER(SEARCH("ISO 42001",E239)),"ISO 42001",IF(ISNUMBER(SEARCH("ISO",E239)),"Otras ISO",IF(ISNUMBER(SEARCH("SCRUM",E239)),"SCRUM",IF(ISNUMBER(SEARCH("BRIDGE",E239)),"BRIDGE",IF(ISNUMBER(SEARCH("CDS",E239)),"CDS",IF(ISNUMBER(SEARCH("TOGAF",E239)),"TOGAF",IF(ISNUMBER(SEARCH("DPI",E239)),"DPI",IF(ISNUMBER(SEARCH("DITS",E239)),"DITS",IF(ISNUMBER(SEARCH("AGILE",E239)),"AGILE",IF(ISNUMBER(SEARCH("Ciberseguridad",E239)),"Ciberseguridad","Otros")))))))))))))) -> Sin definir | Q239: =IF(B239="","",IF(ISNUMBER(K239),IF(K239<=3,"1-3 meses",IF(K239<=6,"4-6 meses","+6 meses")),"Sin dato registrado")) -> Sin dato registrado | R239: =IF(OR(B239="",M239=""),"",RANK(M239,$M$3:$M$306)+COUNTIF($M$3:M239,M239)-1) -> 10
B240: Juan Diego Salcedo García | D240: Carolina | I240: 1500000 | M240: =IF(B240="","",IF(ISNUMBER(I240),I240,IFERROR(VALUE(SUBSTITUTE(SUBSTITUTE(I240,"$",""),".","")),0))) -> 1500000 | N240: =IF(B240="","",PROPER(TRIM(D240))) -> Carolina | O240: =IF(B240="","",IF(OR(ISNUMBER(SEARCH("AL DIA",L240)),ISNUMBER(SEARCH("AL DIA",F240))),"Al día",IF(OR(ISNUMBER(SEARCH("QUIETO",L240)),ISNUMBER(SEARCH("QUIETO",F240)),ISNUMBER(SEARCH("ESPERANDO",L240)),ISNUMBER(SEARCH("ESPERANDO",F240))),"Sin respuesta / Inactivo",IF(OR(ISNUMBER(SEARCH("PENDIENTE",L240)),ISNUMBER(SEARCH("PENDIENTE",F240)),ISNUMBER(SEARCH("COMPROMISO",F240)),ISNUMBER(SEARCH("COMPROMISO",L240)),ISNUMBER(SEARCH("PROCESO",F240)),ISNUMBER(SEARCH("LLAMAR",F240)),ISNUMBER(SEARCH("ABONO",J240)),EXACT(L240,"P"),EXACT(F240,"P")),"Pendiente / Compromiso","Sin gestionar")))) -> Sin gestionar | P240: =IF(B240="","",IF(E240="","Sin definir",IF(ISNUMBER(SEARCH("ITIL",E240)),"ITIL",IF(ISNUMBER(SEARCH("ISO 27001",E240)),"ISO 27001",IF(ISNUMBER(SEARCH("ISO 42001",E240)),"ISO 42001",IF(ISNUMBER(SEARCH("ISO",E240)),"Otras ISO",IF(ISNUMBER(SEARCH("SCRUM",E240)),"SCRUM",IF(ISNUMBER(SEARCH("BRIDGE",E240)),"BRIDGE",IF(ISNUMBER(SEARCH("CDS",E240)),"CDS",IF(ISNUMBER(SEARCH("TOGAF",E240)),"TOGAF",IF(ISNUMBER(SEARCH("DPI",E240)),"DPI",IF(ISNUMBER(SEARCH("DITS",E240)),"DITS",IF(ISNUMBER(SEARCH("AGILE",E240)),"AGILE",IF(ISNUMBER(SEARCH("Ciberseguridad",E240)),"Ciberseguridad","Otros")))))))))))))) -> Sin definir | Q240: =IF(B240="","",IF(ISNUMBER(K240),IF(K240<=3,"1-3 meses",IF(K240<=6,"4-6 meses","+6 meses")),"Sin dato registrado")) -> Sin dato registrado | R240: =IF(OR(B240="",M240=""),"",RANK(M240,$M$3:$M$306)+COUNTIF($M$3:M240,M240)-1) -> 9
B241: JAVIER CUBILLOS CASTRO | D241: Carolina | I241: 1470000 | M241: =IF(B241="","",IF(ISNUMBER(I241),I241,IFERROR(VALUE(SUBSTITUTE(SUBSTITUTE(I241,"$",""),".","")),0))) -> 1470000 | N241: =IF(B241="","",PROPER(TRIM(D241))) -> Carolina | O241: =IF(B241="","",IF(OR(ISNUMBER(SEARCH("AL DIA",L241)),ISNUMBER(SEARCH("AL DIA",F241))),"Al día",IF(OR(ISNUMBER(SEARCH("QUIETO",L241)),ISNUMBER(SEARCH("QUIETO",F241)),ISNUMBER(SEARCH("ESPERANDO",L241)),ISNUMBER(SEARCH("ESPERANDO",F241))),"Sin respuesta / Inactivo",IF(OR(ISNUMBER(SEARCH("PENDIENTE",L241)),ISNUMBER(SEARCH("PENDIENTE",F241)),ISNUMBER(SEARCH("COMPROMISO",F241)),ISNUMBER(SEARCH("COMPROMISO",L241)),ISNUMBER(SEARCH("PROCESO",F241)),ISNUMBER(SEARCH("LLAMAR",F241)),ISNUMBER(SEARCH("ABONO",J241)),EXACT(L241,"P"),EXACT(F241,"P")),"Pendiente / Compromiso","Sin gestionar")))) -> Sin gestionar | P241: =IF(B241="","",IF(E241="","Sin definir",IF(ISNUMBER(SEARCH("ITIL",E241)),"ITIL",IF(ISNUMBER(SEARCH("ISO 27001",E241)),"ISO 27001",IF(ISNUMBER(SEARCH("ISO 42001",E241)),"ISO 42001",IF(ISNUMBER(SEARCH("ISO",E241)),"Otras ISO",IF(ISNUMBER(SEARCH("SCRUM",E241)),"SCRUM",IF(ISNUMBER(SEARCH("BRIDGE",E241)),"BRIDGE",IF(ISNUMBER(SEARCH("CDS",E241)),"CDS",IF(ISNUMBER(SEARCH("TOGAF",E241)),"TOGAF",IF(ISNUMBER(SEARCH("DPI",E241)),"DPI",IF(ISNUMBER(SEARCH("DITS",E241)),"DITS",IF(ISNUMBER(SEARCH("AGILE",E241)),"AGILE",IF(ISNUMBER(SEARCH("Ciberseguridad",E241)),"Ciberseguridad","Otros")))))))))))))) -> Sin definir | Q241: =IF(B241="","",IF(ISNUMBER(K241),IF(K241<=3,"1-3 meses",IF(K241<=6,"4-6 meses","+6 meses")),"Sin dato registrado")) -> Sin dato registrado | R241: =IF(OR(B241="",M241=""),"",RANK(M241,$M$3:$M$306)+COUNTIF($M$3:M241,M241)-1) -> 11
B242: Miguel Ángel Martinez Moreno | D242: Sebas | I242: 850000 | M242: =IF(B242="","",IF(ISNUMBER(I242),I242,IFERROR(VALUE(SUBSTITUTE(SUBSTITUTE(I242,"$",""),".","")),0))) -> 850000 | N242: =IF(B242="","",PROPER(TRIM(D242))) -> Sebas | O242: =IF(B242="","",IF(OR(ISNUMBER(SEARCH("AL DIA",L242)),ISNUMBER(SEARCH("AL DIA",F242))),"Al día",IF(OR(ISNUMBER(SEARCH("QUIETO",L242)),ISNUMBER(SEARCH("QUIETO",F242)),ISNUMBER(SEARCH("ESPERANDO",L242)),ISNUMBER(SEARCH("ESPERANDO",F242))),"Sin respuesta / Inactivo",IF(OR(ISNUMBER(SEARCH("PENDIENTE",L242)),ISNUMBER(SEARCH("PENDIENTE",F242)),ISNUMBER(SEARCH("COMPROMISO",F242)),ISNUMBER(SEARCH("COMPROMISO",L242)),ISNUMBER(SEARCH("PROCESO",F242)),ISNUMBER(SEARCH("LLAMAR",F242)),ISNUMBER(SEARCH("ABONO",J242)),EXACT(L242,"P"),EXACT(F242,"P")),"Pendiente / Compromiso","Sin gestionar")))) -> Sin gestionar | P242: =IF(B242="","",IF(E242="","Sin definir",IF(ISNUMBER(SEARCH("ITIL",E242)),"ITIL",IF(ISNUMBER(SEARCH("ISO 27001",E242)),"ISO 27001",IF(ISNUMBER(SEARCH("ISO 42001",E242)),"ISO 42001",IF(ISNUMBER(SEARCH("ISO",E242)),"Otras ISO",IF(ISNUMBER(SEARCH("SCRUM",E242)),"SCRUM",IF(ISNUMBER(SEARCH("BRIDGE",E242)),"BRIDGE",IF(ISNUMBER(SEARCH("CDS",E242)),"CDS",IF(ISNUMBER(SEARCH("TOGAF",E242)),"TOGAF",IF(ISNUMBER(SEARCH("DPI",E242)),"DPI",IF(ISNUMBER(SEARCH("DITS",E242)),"DITS",IF(ISNUMBER(SEARCH("AGILE",E242)),"AGILE",IF(ISNUMBER(SEARCH("Ciberseguridad",E242)),"Ciberseguridad","Otros")))))))))))))) -> Sin definir | Q242: =IF(B242="","",IF(ISNUMBER(K242),IF(K242<=3,"1-3 meses",IF(K242<=6,"4-6 meses","+6 meses")),"Sin dato registrado")) -> Sin dato registrado | R242: =IF(OR(B242="",M242=""),"",RANK(M242,$M$3:$M$306)+COUNTIF($M$3:M242,M242)-1) -> 31
B243: Laura Maria Contreras Velandia | D243: Ximena | I243: 800000 | M243: =IF(B243="","",IF(ISNUMBER(I243),I243,IFERROR(VALUE(SUBSTITUTE(SUBSTITUTE(I243,"$",""),".","")),0))) -> 800000 | N243: =IF(B243="","",PROPER(TRIM(D243))) -> Ximena | O243: =IF(B243="","",IF(OR(ISNUMBER(SEARCH("AL DIA",L243)),ISNUMBER(SEARCH("AL DIA",F243))),"Al día",IF(OR(ISNUMBER(SEARCH("QUIETO",L243)),ISNUMBER(SEARCH("QUIETO",F243)),ISNUMBER(SEARCH("ESPERANDO",L243)),ISNUMBER(SEARCH("ESPERANDO",F243))),"Sin respuesta / Inactivo",IF(OR(ISNUMBER(SEARCH("PENDIENTE",L243)),ISNUMBER(SEARCH("PENDIENTE",F243)),ISNUMBER(SEARCH("COMPROMISO",F243)),ISNUMBER(SEARCH("COMPROMISO",L243)),ISNUMBER(SEARCH("PROCESO",F243)),ISNUMBER(SEARCH("LLAMAR",F243)),ISNUMBER(SEARCH("ABONO",J243)),EXACT(L243,"P"),EXACT(F243,"P")),"Pendiente / Compromiso","Sin gestionar")))) -> Sin gestionar | P243: =IF(B243="","",IF(E243="","Sin definir",IF(ISNUMBER(SEARCH("ITIL",E243)),"ITIL",IF(ISNUMBER(SEARCH("ISO 27001",E243)),"ISO 27001",IF(ISNUMBER(SEARCH("ISO 42001",E243)),"ISO 42001",IF(ISNUMBER(SEARCH("ISO",E243)),"Otras ISO",IF(ISNUMBER(SEARCH("SCRUM",E243)),"SCRUM",IF(ISNUMBER(SEARCH("BRIDGE",E243)),"BRIDGE",IF(ISNUMBER(SEARCH("CDS",E243)),"CDS",IF(ISNUMBER(SEARCH("TOGAF",E243)),"TOGAF",IF(ISNUMBER(SEARCH("DPI",E243)),"DPI",IF(ISNUMBER(SEARCH("DITS",E243)),"DITS",IF(ISNUMBER(SEARCH("AGILE",E243)),"AGILE",IF(ISNUMBER(SEARCH("Ciberseguridad",E243)),"Ciberseguridad","Otros")))))))))))))) -> Sin definir | Q243: =IF(B243="","",IF(ISNUMBER(K243),IF(K243<=3,"1-3 meses",IF(K243<=6,"4-6 meses","+6 meses")),"Sin dato registrado")) -> Sin dato registrado | R243: =IF(OR(B243="",M243=""),"",RANK(M243,$M$3:$M$306)+COUNTIF($M$3:M243,M243)-1) -> 33
B244: Laura Sofía Carmona Mina | D244: Carolina | I244: 1200000 | M244: =IF(B244="","",IF(ISNUMBER(I244),I244,IFERROR(VALUE(SUBSTITUTE(SUBSTITUTE(I244,"$",""),".","")),0))) -> 1200000 | N244: =IF(B244="","",PROPER(TRIM(D244))) -> Carolina | O244: =IF(B244="","",IF(OR(ISNUMBER(SEARCH("AL DIA",L244)),ISNUMBER(SEARCH("AL DIA",F244))),"Al día",IF(OR(ISNUMBER(SEARCH("QUIETO",L244)),ISNUMBER(SEARCH("QUIETO",F244)),ISNUMBER(SEARCH("ESPERANDO",L244)),ISNUMBER(SEARCH("ESPERANDO",F244))),"Sin respuesta / Inactivo",IF(OR(ISNUMBER(SEARCH("PENDIENTE",L244)),ISNUMBER(SEARCH("PENDIENTE",F244)),ISNUMBER(SEARCH("COMPROMISO",F244)),ISNUMBER(SEARCH("COMPROMISO",L244)),ISNUMBER(SEARCH("PROCESO",F244)),ISNUMBER(SEARCH("LLAMAR",F244)),ISNUMBER(SEARCH("ABONO",J244)),EXACT(L244,"P"),EXACT(F244,"P")),"Pendiente / Compromiso","Sin gestionar")))) -> Sin gestionar | P244: =IF(B244="","",IF(E244="","Sin definir",IF(ISNUMBER(SEARCH("ITIL",E244)),"ITIL",IF(ISNUMBER(SEARCH("ISO 27001",E244)),"ISO 27001",IF(ISNUMBER(SEARCH("ISO 42001",E244)),"ISO 42001",IF(ISNUMBER(SEARCH("ISO",E244)),"Otras ISO",IF(ISNUMBER(SEARCH("SCRUM",E244)),"SCRUM",IF(ISNUMBER(SEARCH("BRIDGE",E244)),"BRIDGE",IF(ISNUMBER(SEARCH("CDS",E244)),"CDS",IF(ISNUMBER(SEARCH("TOGAF",E244)),"TOGAF",IF(ISNUMBER(SEARCH("DPI",E244)),"DPI",IF(ISNUMBER(SEARCH("DITS",E244)),"DITS",IF(ISNUMBER(SEARCH("AGILE",E244)),"AGILE",IF(ISNUMBER(SEARCH("Ciberseguridad",E244)),"Ciberseguridad","Otros")))))))))))))) -> Sin definir | Q244: =IF(B244="","",IF(ISNUMBER(K244),IF(K244<=3,"1-3 meses",IF(K244<=6,"4-6 meses","+6 meses")),"Sin dato registrado")) -> Sin dato registrado | R244: =IF(OR(B244="",M244=""),"",RANK(M244,$M$3:$M$306)+COUNTIF($M$3:M244,M244)-1) -> 16
B245: Andrea Olarte Trujillo | D245: Sebas | I245: 1750000 | M245: =IF(B245="","",IF(ISNUMBER(I245),I245,IFERROR(VALUE(SUBSTITUTE(SUBSTITUTE(I245,"$",""),".","")),0))) -> 1750000 | N245: =IF(B245="","",PROPER(TRIM(D245))) -> Sebas | O245: =IF(B245="","",IF(OR(ISNUMBER(SEARCH("AL DIA",L245)),ISNUMBER(SEARCH("AL DIA",F245))),"Al día",IF(OR(ISNUMBER(SEARCH("QUIETO",L245)),ISNUMBER(SEARCH("QUIETO",F245)),ISNUMBER(SEARCH("ESPERANDO",L245)),ISNUMBER(SEARCH("ESPERANDO",F245))),"Sin respuesta / Inactivo",IF(OR(ISNUMBER(SEARCH("PENDIENTE",L245)),ISNUMBER(SEARCH("PENDIENTE",F245)),ISNUMBER(SEARCH("COMPROMISO",F245)),ISNUMBER(SEARCH("COMPROMISO",L245)),ISNUMBER(SEARCH("PROCESO",F245)),ISNUMBER(SEARCH("LLAMAR",F245)),ISNUMBER(SEARCH("ABONO",J245)),EXACT(L245,"P"),EXACT(F245,"P")),"Pendiente / Compromiso","Sin gestionar")))) -> Sin gestionar | P245: =IF(B245="","",IF(E245="","Sin definir",IF(ISNUMBER(SEARCH("ITIL",E245)),"ITIL",IF(ISNUMBER(SEARCH("ISO 27001",E245)),"ISO 27001",IF(ISNUMBER(SEARCH("ISO 42001",E245)),"ISO 42001",IF(ISNUMBER(SEARCH("ISO",E245)),"Otras ISO",IF(ISNUMBER(SEARCH("SCRUM",E245)),"SCRUM",IF(ISNUMBER(SEARCH("BRIDGE",E245)),"BRIDGE",IF(ISNUMBER(SEARCH("CDS",E245)),"CDS",IF(ISNUMBER(SEARCH("TOGAF",E245)),"TOGAF",IF(ISNUMBER(SEARCH("DPI",E245)),"DPI",IF(ISNUMBER(SEARCH("DITS",E245)),"DITS",IF(ISNUMBER(SEARCH("AGILE",E245)),"AGILE",IF(ISNUMBER(SEARCH("Ciberseguridad",E245)),"Ciberseguridad","Otros")))))))))))))) -> Sin definir | Q245: =IF(B245="","",IF(ISNUMBER(K245),IF(K245<=3,"1-3 meses",IF(K245<=6,"4-6 meses","+6 meses")),"Sin dato registrado")) -> Sin dato registrado | R245: =IF(OR(B245="",M245=""),"",RANK(M245,$M$3:$M$306)+COUNTIF($M$3:M245,M245)-1) -> 6
B246: Jorge Andrés Castañeda Muñoz | D246: Carolina | I246: 650000 | M246: =IF(B246="","",IF(ISNUMBER(I246),I246,IFERROR(VALUE(SUBSTITUTE(SUBSTITUTE(I246,"$",""),".","")),0))) -> 650000 | N246: =IF(B246="","",PROPER(TRIM(D246))) -> Carolina | O246: =IF(B246="","",IF(OR(ISNUMBER(SEARCH("AL DIA",L246)),ISNUMBER(SEARCH("AL DIA",F246))),"Al día",IF(OR(ISNUMBER(SEARCH("QUIETO",L246)),ISNUMBER(SEARCH("QUIETO",F246)),ISNUMBER(SEARCH("ESPERANDO",L246)),ISNUMBER(SEARCH("ESPERANDO",F246))),"Sin respuesta / Inactivo",IF(OR(ISNUMBER(SEARCH("PENDIENTE",L246)),ISNUMBER(SEARCH("PENDIENTE",F246)),ISNUMBER(SEARCH("COMPROMISO",F246)),ISNUMBER(SEARCH("COMPROMISO",L246)),ISNUMBER(SEARCH("PROCESO",F246)),ISNUMBER(SEARCH("LLAMAR",F246)),ISNUMBER(SEARCH("ABONO",J246)),EXACT(L246,"P"),EXACT(F246,"P")),"Pendiente / Compromiso","Sin gestionar")))) -> Sin gestionar | P246: =IF(B246="","",IF(E246="","Sin definir",IF(ISNUMBER(SEARCH("ITIL",E246)),"ITIL",IF(ISNUMBER(SEARCH("ISO 27001",E246)),"ISO 27001",IF(ISNUMBER(SEARCH("ISO 42001",E246)),"ISO 42001",IF(ISNUMBER(SEARCH("ISO",E246)),"Otras ISO",IF(ISNUMBER(SEARCH("SCRUM",E246)),"SCRUM",IF(ISNUMBER(SEARCH("BRIDGE",E246)),"BRIDGE",IF(ISNUMBER(SEARCH("CDS",E246)),"CDS",IF(ISNUMBER(SEARCH("TOGAF",E246)),"TOGAF",IF(ISNUMBER(SEARCH("DPI",E246)),"DPI",IF(ISNUMBER(SEARCH("DITS",E246)),"DITS",IF(ISNUMBER(SEARCH("AGILE",E246)),"AGILE",IF(ISNUMBER(SEARCH("Ciberseguridad",E246)),"Ciberseguridad","Otros")))))))))))))) -> Sin definir | Q246: =IF(B246="","",IF(ISNUMBER(K246),IF(K246<=3,"1-3 meses",IF(K246<=6,"4-6 meses","+6 meses")),"Sin dato registrado")) -> Sin dato registrado | R246: =IF(OR(B246="",M246=""),"",RANK(M246,$M$3:$M$306)+COUNTIF($M$3:M246,M246)-1) -> 42
B247: Sara Valentina Rivera Chiquillo | D247: Ximena | I247: 350000 | M247: =IF(B247="","",IF(ISNUMBER(I247),I247,IFERROR(VALUE(SUBSTITUTE(SUBSTITUTE(I247,"$",""),".","")),0))) -> 350000 | N247: =IF(B247="","",PROPER(TRIM(D247))) -> Ximena | O247: =IF(B247="","",IF(OR(ISNUMBER(SEARCH("AL DIA",L247)),ISNUMBER(SEARCH("AL DIA",F247))),"Al día",IF(OR(ISNUMBER(SEARCH("QUIETO",L247)),ISNUMBER(SEARCH("QUIETO",F247)),ISNUMBER(SEARCH("ESPERANDO",L247)),ISNUMBER(SEARCH("ESPERANDO",F247))),"Sin respuesta / Inactivo",IF(OR(ISNUMBER(SEARCH("PENDIENTE",L247)),ISNUMBER(SEARCH("PENDIENTE",F247)),ISNUMBER(SEARCH("COMPROMISO",F247)),ISNUMBER(SEARCH("COMPROMISO",L247)),ISNUMBER(SEARCH("PROCESO",F247)),ISNUMBER(SEARCH("LLAMAR",F247)),ISNUMBER(SEARCH("ABONO",J247)),EXACT(L247,"P"),EXACT(F247,"P")),"Pendiente / Compromiso","Sin gestionar")))) -> Sin gestionar | P247: =IF(B247="","",IF(E247="","Sin definir",IF(ISNUMBER(SEARCH("ITIL",E247)),"ITIL",IF(ISNUMBER(SEARCH("ISO 27001",E247)),"ISO 27001",IF(ISNUMBER(SEARCH("ISO 42001",E247)),"ISO 42001",IF(ISNUMBER(SEARCH("ISO",E247)),"Otras ISO",IF(ISNUMBER(SEARCH("SCRUM",E247)),"SCRUM",IF(ISNUMBER(SEARCH("BRIDGE",E247)),"BRIDGE",IF(ISNUMBER(SEARCH("CDS",E247)),"CDS",IF(ISNUMBER(SEARCH("TOGAF",E247)),"TOGAF",IF(ISNUMBER(SEARCH("DPI",E247)),"DPI",IF(ISNUMBER(SEARCH("DITS",E247)),"DITS",IF(ISNUMBER(SEARCH("AGILE",E247)),"AGILE",IF(ISNUMBER(SEARCH("Ciberseguridad",E247)),"Ciberseguridad","Otros")))))))))))))) -> Sin definir | Q247: =IF(B247="","",IF(ISNUMBER(K247),IF(K247<=3,"1-3 meses",IF(K247<=6,"4-6 meses","+6 meses")),"Sin dato registrado")) -> Sin dato registrado | R247: =IF(OR(B247="",M247=""),"",RANK(M247,$M$3:$M$306)+COUNTIF($M$3:M247,M247)-1) -> 53
B248: Elias Alejandro Lopez Palacios | D248: Carolina | E248: ISO42001 27 JUL | I248: 1000000 | M248: =IF(B248="","",IF(ISNUMBER(I248),I248,IFERROR(VALUE(SUBSTITUTE(SUBSTITUTE(I248,"$",""),".","")),0))) -> 1000000 | N248: =IF(B248="","",PROPER(TRIM(D248))) -> Carolina | O248: =IF(B248="","",IF(OR(ISNUMBER(SEARCH("AL DIA",L248)),ISNUMBER(SEARCH("AL DIA",F248))),"Al día",IF(OR(ISNUMBER(SEARCH("QUIETO",L248)),ISNUMBER(SEARCH("QUIETO",F248)),ISNUMBER(SEARCH("ESPERANDO",L248)),ISNUMBER(SEARCH("ESPERANDO",F248))),"Sin respuesta / Inactivo",IF(OR(ISNUMBER(SEARCH("PENDIENTE",L248)),ISNUMBER(SEARCH("PENDIENTE",F248)),ISNUMBER(SEARCH("COMPROMISO",F248)),ISNUMBER(SEARCH("COMPROMISO",L248)),ISNUMBER(SEARCH("PROCESO",F248)),ISNUMBER(SEARCH("LLAMAR",F248)),ISNUMBER(SEARCH("ABONO",J248)),EXACT(L248,"P"),EXACT(F248,"P")),"Pendiente / Compromiso","Sin gestionar")))) -> Sin gestionar | P248: =IF(B248="","",IF(E248="","Sin definir",IF(ISNUMBER(SEARCH("ITIL",E248)),"ITIL",IF(ISNUMBER(SEARCH("ISO 27001",E248)),"ISO 27001",IF(ISNUMBER(SEARCH("ISO 42001",E248)),"ISO 42001",IF(ISNUMBER(SEARCH("ISO",E248)),"Otras ISO",IF(ISNUMBER(SEARCH("SCRUM",E248)),"SCRUM",IF(ISNUMBER(SEARCH("BRIDGE",E248)),"BRIDGE",IF(ISNUMBER(SEARCH("CDS",E248)),"CDS",IF(ISNUMBER(SEARCH("TOGAF",E248)),"TOGAF",IF(ISNUMBER(SEARCH("DPI",E248)),"DPI",IF(ISNUMBER(SEARCH("DITS",E248)),"DITS",IF(ISNUMBER(SEARCH("AGILE",E248)),"AGILE",IF(ISNUMBER(SEARCH("Ciberseguridad",E248)),"Ciberseguridad","Otros")))))))))))))) -> Otras ISO | Q248: =IF(B248="","",IF(ISNUMBER(K248),IF(K248<=3,"1-3 meses",IF(K248<=6,"4-6 meses","+6 meses")),"Sin dato registrado")) -> Sin dato registrado | R248: =IF(OR(B248="",M248=""),"",RANK(M248,$M$3:$M$306)+COUNTIF($M$3:M248,M248)-1) -> 21
M249: =IF(B249="","",IF(ISNUMBER(I249),I249,IFERROR(VALUE(SUBSTITUTE(SUBSTITUTE(I249,"$",""),".","")),0))) | N249: =IF(B249="","",PROPER(TRIM(D249))) | O249: =IF(B249="","",IF(OR(ISNUMBER(SEARCH("AL DIA",L249)),ISNUMBER(SEARCH("AL DIA",F249))),"Al día",IF(OR(ISNUMBER(SEARCH("QUIETO",L249)),ISNUMBER(SEARCH("QUIETO",F249)),ISNUMBER(SEARCH("ESPERANDO",L249)),ISNUMBER(SEARCH("ESPERANDO",F249))),"Sin respuesta / Inactivo",IF(OR(ISNUMBER(SEARCH("PENDIENTE",L249)),ISNUMBER(SEARCH("PENDIENTE",F249)),ISNUMBER(SEARCH("COMPROMISO",F249)),ISNUMBER(SEARCH("COMPROMISO",L249)),ISNUMBER(SEARCH("PROCESO",F249)),ISNUMBER(SEARCH("LLAMAR",F249)),ISNUMBER(SEARCH("ABONO",J249)),EXACT(L249,"P"),EXACT(F249,"P")),"Pendiente / Compromiso","Sin gestionar")))) | P249: =IF(B249="","",IF(E249="","Sin definir",IF(ISNUMBER(SEARCH("ITIL",E249)),"ITIL",IF(ISNUMBER(SEARCH("ISO 27001",E249)),"ISO 27001",IF(ISNUMBER(SEARCH("ISO 42001",E249)),"ISO 42001",IF(ISNUMBER(SEARCH("ISO",E249)),"Otras ISO",IF(ISNUMBER(SEARCH("SCRUM",E249)),"SCRUM",IF(ISNUMBER(SEARCH("BRIDGE",E249)),"BRIDGE",IF(ISNUMBER(SEARCH("CDS",E249)),"CDS",IF(ISNUMBER(SEARCH("TOGAF",E249)),"TOGAF",IF(ISNUMBER(SEARCH("DPI",E249)),"DPI",IF(ISNUMBER(SEARCH("DITS",E249)),"DITS",IF(ISNUMBER(SEARCH("AGILE",E249)),"AGILE",IF(ISNUMBER(SEARCH("Ciberseguridad",E249)),"Ciberseguridad","Otros")))))))))))))) | Q249: =IF(B249="","",IF(ISNUMBER(K249),IF(K249<=3,"1-3 meses",IF(K249<=6,"4-6 meses","+6 meses")),"Sin dato registrado")) | R249: =IF(OR(B249="",M249=""),"",RANK(M249,$M$3:$M$306)+COUNTIF($M$3:M249,M249)-1)
M250: =IF(B250="","",IF(ISNUMBER(I250),I250,IFERROR(VALUE(SUBSTITUTE(SUBSTITUTE(I250,"$",""),".","")),0))) | N250: =IF(B250="","",PROPER(TRIM(D250))) | O250: =IF(B250="","",IF(OR(ISNUMBER(SEARCH("AL DIA",L250)),ISNUMBER(SEARCH("AL DIA",F250))),"Al día",IF(OR(ISNUMBER(SEARCH("QUIETO",L250)),ISNUMBER(SEARCH("QUIETO",F250)),ISNUMBER(SEARCH("ESPERANDO",L250)),ISNUMBER(SEARCH("ESPERANDO",F250))),"Sin respuesta / Inactivo",IF(OR(ISNUMBER(SEARCH("PENDIENTE",L250)),ISNUMBER(SEARCH("PENDIENTE",F250)),ISNUMBER(SEARCH("COMPROMISO",F250)),ISNUMBER(SEARCH("COMPROMISO",L250)),ISNUMBER(SEARCH("PROCESO",F250)),ISNUMBER(SEARCH("LLAMAR",F250)),ISNUMBER(SEARCH("ABONO",J250)),EXACT(L250,"P"),EXACT(F250,"P")),"Pendiente / Compromiso","Sin gestionar")))) | P250: =IF(B250="","",IF(E250="","Sin definir",IF(ISNUMBER(SEARCH("ITIL",E250)),"ITIL",IF(ISNUMBER(SEARCH("ISO 27001",E250)),"ISO 27001",IF(ISNUMBER(SEARCH("ISO 42001",E250)),"ISO 42001",IF(ISNUMBER(SEARCH("ISO",E250)),"Otras ISO",IF(ISNUMBER(SEARCH("SCRUM",E250)),"SCRUM",IF(ISNUMBER(SEARCH("BRIDGE",E250)),"BRIDGE",IF(ISNUMBER(SEARCH("CDS",E250)),"CDS",IF(ISNUMBER(SEARCH("TOGAF",E250)),"TOGAF",IF(ISNUMBER(SEARCH("DPI",E250)),"DPI",IF(ISNUMBER(SEARCH("DITS",E250)),"DITS",IF(ISNUMBER(SEARCH("AGILE",E250)),"AGILE",IF(ISNUMBER(SEARCH("Ciberseguridad",E250)),"Ciberseguridad","Otros")))))))))))))) | Q250: =IF(B250="","",IF(ISNUMBER(K250),IF(K250<=3,"1-3 meses",IF(K250<=6,"4-6 meses","+6 meses")),"Sin dato registrado")) | R250: =IF(OR(B250="",M250=""),"",RANK(M250,$M$3:$M$306)+COUNTIF($M$3:M250,M250)-1)
M251: =IF(B251="","",IF(ISNUMBER(I251),I251,IFERROR(VALUE(SUBSTITUTE(SUBSTITUTE(I251,"$",""),".","")),0))) | N251: =IF(B251="","",PROPER(TRIM(D251))) | O251: =IF(B251="","",IF(OR(ISNUMBER(SEARCH("AL DIA",L251)),ISNUMBER(SEARCH("AL DIA",F251))),"Al día",IF(OR(ISNUMBER(SEARCH("QUIETO",L251)),ISNUMBER(SEARCH("QUIETO",F251)),ISNUMBER(SEARCH("ESPERANDO",L251)),ISNUMBER(SEARCH("ESPERANDO",F251))),"Sin respuesta / Inactivo",IF(OR(ISNUMBER(SEARCH("PENDIENTE",L251)),ISNUMBER(SEARCH("PENDIENTE",F251)),ISNUMBER(SEARCH("COMPROMISO",F251)),ISNUMBER(SEARCH("COMPROMISO",L251)),ISNUMBER(SEARCH("PROCESO",F251)),ISNUMBER(SEARCH("LLAMAR",F251)),ISNUMBER(SEARCH("ABONO",J251)),EXACT(L251,"P"),EXACT(F251,"P")),"Pendiente / Compromiso","Sin gestionar")))) | P251: =IF(B251="","",IF(E251="","Sin definir",IF(ISNUMBER(SEARCH("ITIL",E251)),"ITIL",IF(ISNUMBER(SEARCH("ISO 27001",E251)),"ISO 27001",IF(ISNUMBER(SEARCH("ISO 42001",E251)),"ISO 42001",IF(ISNUMBER(SEARCH("ISO",E251)),"Otras ISO",IF(ISNUMBER(SEARCH("SCRUM",E251)),"SCRUM",IF(ISNUMBER(SEARCH("BRIDGE",E251)),"BRIDGE",IF(ISNUMBER(SEARCH("CDS",E251)),"CDS",IF(ISNUMBER(SEARCH("TOGAF",E251)),"TOGAF",IF(ISNUMBER(SEARCH("DPI",E251)),"DPI",IF(ISNUMBER(SEARCH("DITS",E251)),"DITS",IF(ISNUMBER(SEARCH("AGILE",E251)),"AGILE",IF(ISNUMBER(SEARCH("Ciberseguridad",E251)),"Ciberseguridad","Otros")))))))))))))) | Q251: =IF(B251="","",IF(ISNUMBER(K251),IF(K251<=3,"1-3 meses",IF(K251<=6,"4-6 meses","+6 meses")),"Sin dato registrado")) | R251: =IF(OR(B251="",M251=""),"",RANK(M251,$M$3:$M$306)+COUNTIF($M$3:M251,M251)-1)
M252: =IF(B252="","",IF(ISNUMBER(I252),I252,IFERROR(VALUE(SUBSTITUTE(SUBSTITUTE(I252,"$",""),".","")),0))) | N252: =IF(B252="","",PROPER(TRIM(D252))) | O252: =IF(B252="","",IF(OR(ISNUMBER(SEARCH("AL DIA",L252)),ISNUMBER(SEARCH("AL DIA",F252))),"Al día",IF(OR(ISNUMBER(SEARCH("QUIETO",L252)),ISNUMBER(SEARCH("QUIETO",F252)),ISNUMBER(SEARCH("ESPERANDO",L252)),ISNUMBER(SEARCH("ESPERANDO",F252))),"Sin respuesta / Inactivo",IF(OR(ISNUMBER(SEARCH("PENDIENTE",L252)),ISNUMBER(SEARCH("PENDIENTE",F252)),ISNUMBER(SEARCH("COMPROMISO",F252)),ISNUMBER(SEARCH("COMPROMISO",L252)),ISNUMBER(SEARCH("PROCESO",F252)),ISNUMBER(SEARCH("LLAMAR",F252)),ISNUMBER(SEARCH("ABONO",J252)),EXACT(L252,"P"),EXACT(F252,"P")),"Pendiente / Compromiso","Sin gestionar")))) | P252: =IF(B252="","",IF(E252="","Sin definir",IF(ISNUMBER(SEARCH("ITIL",E252)),"ITIL",IF(ISNUMBER(SEARCH("ISO 27001",E252)),"ISO 27001",IF(ISNUMBER(SEARCH("ISO 42001",E252)),"ISO 42001",IF(ISNUMBER(SEARCH("ISO",E252)),"Otras ISO",IF(ISNUMBER(SEARCH("SCRUM",E252)),"SCRUM",IF(ISNUMBER(SEARCH("BRIDGE",E252)),"BRIDGE",IF(ISNUMBER(SEARCH("CDS",E252)),"CDS",IF(ISNUMBER(SEARCH("TOGAF",E252)),"TOGAF",IF(ISNUMBER(SEARCH("DPI",E252)),"DPI",IF(ISNUMBER(SEARCH("DITS",E252)),"DITS",IF(ISNUMBER(SEARCH("AGILE",E252)),"AGILE",IF(ISNUMBER(SEARCH("Ciberseguridad",E252)),"Ciberseguridad","Otros")))))))))))))) | Q252: =IF(B252="","",IF(ISNUMBER(K252),IF(K252<=3,"1-3 meses",IF(K252<=6,"4-6 meses","+6 meses")),"Sin dato registrado")) | R252: =IF(OR(B252="",M252=""),"",RANK(M252,$M$3:$M$306)+COUNTIF($M$3:M252,M252)-1)
M253: =IF(B253="","",IF(ISNUMBER(I253),I253,IFERROR(VALUE(SUBSTITUTE(SUBSTITUTE(I253,"$",""),".","")),0))) | N253: =IF(B253="","",PROPER(TRIM(D253))) | O253: =IF(B253="","",IF(OR(ISNUMBER(SEARCH("AL DIA",L253)),ISNUMBER(SEARCH("AL DIA",F253))),"Al día",IF(OR(ISNUMBER(SEARCH("QUIETO",L253)),ISNUMBER(SEARCH("QUIETO",F253)),ISNUMBER(SEARCH("ESPERANDO",L253)),ISNUMBER(SEARCH("ESPERANDO",F253))),"Sin respuesta / Inactivo",IF(OR(ISNUMBER(SEARCH("PENDIENTE",L253)),ISNUMBER(SEARCH("PENDIENTE",F253)),ISNUMBER(SEARCH("COMPROMISO",F253)),ISNUMBER(SEARCH("COMPROMISO",L253)),ISNUMBER(SEARCH("PROCESO",F253)),ISNUMBER(SEARCH("LLAMAR",F253)),ISNUMBER(SEARCH("ABONO",J253)),EXACT(L253,"P"),EXACT(F253,"P")),"Pendiente / Compromiso","Sin gestionar")))) | P253: =IF(B253="","",IF(E253="","Sin definir",IF(ISNUMBER(SEARCH("ITIL",E253)),"ITIL",IF(ISNUMBER(SEARCH("ISO 27001",E253)),"ISO 27001",IF(ISNUMBER(SEARCH("ISO 42001",E253)),"ISO 42001",IF(ISNUMBER(SEARCH("ISO",E253)),"Otras ISO",IF(ISNUMBER(SEARCH("SCRUM",E253)),"SCRUM",IF(ISNUMBER(SEARCH("BRIDGE",E253)),"BRIDGE",IF(ISNUMBER(SEARCH("CDS",E253)),"CDS",IF(ISNUMBER(SEARCH("TOGAF",E253)),"TOGAF",IF(ISNUMBER(SEARCH("DPI",E253)),"DPI",IF(ISNUMBER(SEARCH("DITS",E253)),"DITS",IF(ISNUMBER(SEARCH("AGILE",E253)),"AGILE",IF(ISNUMBER(SEARCH("Ciberseguridad",E253)),"Ciberseguridad","Otros")))))))))))))) | Q253: =IF(B253="","",IF(ISNUMBER(K253),IF(K253<=3,"1-3 meses",IF(K253<=6,"4-6 meses","+6 meses")),"Sin dato registrado")) | R253: =IF(OR(B253="",M253=""),"",RANK(M253,$M$3:$M$306)+COUNTIF($M$3:M253,M253)-1)
M254: =IF(B254="","",IF(ISNUMBER(I254),I254,IFERROR(VALUE(SUBSTITUTE(SUBSTITUTE(I254,"$",""),".","")),0))) | N254: =IF(B254="","",PROPER(TRIM(D254))) | O254: =IF(B254="","",IF(OR(ISNUMBER(SEARCH("AL DIA",L254)),ISNUMBER(SEARCH("AL DIA",F254))),"Al día",IF(OR(ISNUMBER(SEARCH("QUIETO",L254)),ISNUMBER(SEARCH("QUIETO",F254)),ISNUMBER(SEARCH("ESPERANDO",L254)),ISNUMBER(SEARCH("ESPERANDO",F254))),"Sin respuesta / Inactivo",IF(OR(ISNUMBER(SEARCH("PENDIENTE",L254)),ISNUMBER(SEARCH("PENDIENTE",F254)),ISNUMBER(SEARCH("COMPROMISO",F254)),ISNUMBER(SEARCH("COMPROMISO",L254)),ISNUMBER(SEARCH("PROCESO",F254)),ISNUMBER(SEARCH("LLAMAR",F254)),ISNUMBER(SEARCH("ABONO",J254)),EXACT(L254,"P"),EXACT(F254,"P")),"Pendiente / Compromiso","Sin gestionar")))) | P254: =IF(B254="","",IF(E254="","Sin definir",IF(ISNUMBER(SEARCH("ITIL",E254)),"ITIL",IF(ISNUMBER(SEARCH("ISO 27001",E254)),"ISO 27001",IF(ISNUMBER(SEARCH("ISO 42001",E254)),"ISO 42001",IF(ISNUMBER(SEARCH("ISO",E254)),"Otras ISO",IF(ISNUMBER(SEARCH("SCRUM",E254)),"SCRUM",IF(ISNUMBER(SEARCH("BRIDGE",E254)),"BRIDGE",IF(ISNUMBER(SEARCH("CDS",E254)),"CDS",IF(ISNUMBER(SEARCH("TOGAF",E254)),"TOGAF",IF(ISNUMBER(SEARCH("DPI",E254)),"DPI",IF(ISNUMBER(SEARCH("DITS",E254)),"DITS",IF(ISNUMBER(SEARCH("AGILE",E254)),"AGILE",IF(ISNUMBER(SEARCH("Ciberseguridad",E254)),"Ciberseguridad","Otros")))))))))))))) | Q254: =IF(B254="","",IF(ISNUMBER(K254),IF(K254<=3,"1-3 meses",IF(K254<=6,"4-6 meses","+6 meses")),"Sin dato registrado")) | R254: =IF(OR(B254="",M254=""),"",RANK(M254,$M$3:$M$306)+COUNTIF($M$3:M254,M254)-1)
M255: =IF(B255="","",IF(ISNUMBER(I255),I255,IFERROR(VALUE(SUBSTITUTE(SUBSTITUTE(I255,"$",""),".","")),0))) | N255: =IF(B255="","",PROPER(TRIM(D255))) | O255: =IF(B255="","",IF(OR(ISNUMBER(SEARCH("AL DIA",L255)),ISNUMBER(SEARCH("AL DIA",F255))),"Al día",IF(OR(ISNUMBER(SEARCH("QUIETO",L255)),ISNUMBER(SEARCH("QUIETO",F255)),ISNUMBER(SEARCH("ESPERANDO",L255)),ISNUMBER(SEARCH("ESPERANDO",F255))),"Sin respuesta / Inactivo",IF(OR(ISNUMBER(SEARCH("PENDIENTE",L255)),ISNUMBER(SEARCH("PENDIENTE",F255)),ISNUMBER(SEARCH("COMPROMISO",F255)),ISNUMBER(SEARCH("COMPROMISO",L255)),ISNUMBER(SEARCH("PROCESO",F255)),ISNUMBER(SEARCH("LLAMAR",F255)),ISNUMBER(SEARCH("ABONO",J255)),EXACT(L255,"P"),EXACT(F255,"P")),"Pendiente / Compromiso","Sin gestionar")))) | P255: =IF(B255="","",IF(E255="","Sin definir",IF(ISNUMBER(SEARCH("ITIL",E255)),"ITIL",IF(ISNUMBER(SEARCH("ISO 27001",E255)),"ISO 27001",IF(ISNUMBER(SEARCH("ISO 42001",E255)),"ISO 42001",IF(ISNUMBER(SEARCH("ISO",E255)),"Otras ISO",IF(ISNUMBER(SEARCH("SCRUM",E255)),"SCRUM",IF(ISNUMBER(SEARCH("BRIDGE",E255)),"BRIDGE",IF(ISNUMBER(SEARCH("CDS",E255)),"CDS",IF(ISNUMBER(SEARCH("TOGAF",E255)),"TOGAF",IF(ISNUMBER(SEARCH("DPI",E255)),"DPI",IF(ISNUMBER(SEARCH("DITS",E255)),"DITS",IF(ISNUMBER(SEARCH("AGILE",E255)),"AGILE",IF(ISNUMBER(SEARCH("Ciberseguridad",E255)),"Ciberseguridad","Otros")))))))))))))) | Q255: =IF(B255="","",IF(ISNUMBER(K255),IF(K255<=3,"1-3 meses",IF(K255<=6,"4-6 meses","+6 meses")),"Sin dato registrado")) | R255: =IF(OR(B255="",M255=""),"",RANK(M255,$M$3:$M$306)+COUNTIF($M$3:M255,M255)-1)
M256: =IF(B256="","",IF(ISNUMBER(I256),I256,IFERROR(VALUE(SUBSTITUTE(SUBSTITUTE(I256,"$",""),".","")),0))) | N256: =IF(B256="","",PROPER(TRIM(D256))) | O256: =IF(B256="","",IF(OR(ISNUMBER(SEARCH("AL DIA",L256)),ISNUMBER(SEARCH("AL DIA",F256))),"Al día",IF(OR(ISNUMBER(SEARCH("QUIETO",L256)),ISNUMBER(SEARCH("QUIETO",F256)),ISNUMBER(SEARCH("ESPERANDO",L256)),ISNUMBER(SEARCH("ESPERANDO",F256))),"Sin respuesta / Inactivo",IF(OR(ISNUMBER(SEARCH("PENDIENTE",L256)),ISNUMBER(SEARCH("PENDIENTE",F256)),ISNUMBER(SEARCH("COMPROMISO",F256)),ISNUMBER(SEARCH("COMPROMISO",L256)),ISNUMBER(SEARCH("PROCESO",F256)),ISNUMBER(SEARCH("LLAMAR",F256)),ISNUMBER(SEARCH("ABONO",J256)),EXACT(L256,"P"),EXACT(F256,"P")),"Pendiente / Compromiso","Sin gestionar")))) | P256: =IF(B256="","",IF(E256="","Sin definir",IF(ISNUMBER(SEARCH("ITIL",E256)),"ITIL",IF(ISNUMBER(SEARCH("ISO 27001",E256)),"ISO 27001",IF(ISNUMBER(SEARCH("ISO 42001",E256)),"ISO 42001",IF(ISNUMBER(SEARCH("ISO",E256)),"Otras ISO",IF(ISNUMBER(SEARCH("SCRUM",E256)),"SCRUM",IF(ISNUMBER(SEARCH("BRIDGE",E256)),"BRIDGE",IF(ISNUMBER(SEARCH("CDS",E256)),"CDS",IF(ISNUMBER(SEARCH("TOGAF",E256)),"TOGAF",IF(ISNUMBER(SEARCH("DPI",E256)),"DPI",IF(ISNUMBER(SEARCH("DITS",E256)),"DITS",IF(ISNUMBER(SEARCH("AGILE",E256)),"AGILE",IF(ISNUMBER(SEARCH("Ciberseguridad",E256)),"Ciberseguridad","Otros")))))))))))))) | Q256: =IF(B256="","",IF(ISNUMBER(K256),IF(K256<=3,"1-3 meses",IF(K256<=6,"4-6 meses","+6 meses")),"Sin dato registrado")) | R256: =IF(OR(B256="",M256=""),"",RANK(M256,$M$3:$M$306)+COUNTIF($M$3:M256,M256)-1)
M257: =IF(B257="","",IF(ISNUMBER(I257),I257,IFERROR(VALUE(SUBSTITUTE(SUBSTITUTE(I257,"$",""),".","")),0))) | N257: =IF(B257="","",PROPER(TRIM(D257))) | O257: =IF(B257="","",IF(OR(ISNUMBER(SEARCH("AL DIA",L257)),ISNUMBER(SEARCH("AL DIA",F257))),"Al día",IF(OR(ISNUMBER(SEARCH("QUIETO",L257)),ISNUMBER(SEARCH("QUIETO",F257)),ISNUMBER(SEARCH("ESPERANDO",L257)),ISNUMBER(SEARCH("ESPERANDO",F257))),"Sin respuesta / Inactivo",IF(OR(ISNUMBER(SEARCH("PENDIENTE",L257)),ISNUMBER(SEARCH("PENDIENTE",F257)),ISNUMBER(SEARCH("COMPROMISO",F257)),ISNUMBER(SEARCH("COMPROMISO",L257)),ISNUMBER(SEARCH("PROCESO",F257)),ISNUMBER(SEARCH("LLAMAR",F257)),ISNUMBER(SEARCH("ABONO",J257)),EXACT(L257,"P"),EXACT(F257,"P")),"Pendiente / Compromiso","Sin gestionar")))) | P257: =IF(B257="","",IF(E257="","Sin definir",IF(ISNUMBER(SEARCH("ITIL",E257)),"ITIL",IF(ISNUMBER(SEARCH("ISO 27001",E257)),"ISO 27001",IF(ISNUMBER(SEARCH("ISO 42001",E257)),"ISO 42001",IF(ISNUMBER(SEARCH("ISO",E257)),"Otras ISO",IF(ISNUMBER(SEARCH("SCRUM",E257)),"SCRUM",IF(ISNUMBER(SEARCH("BRIDGE",E257)),"BRIDGE",IF(ISNUMBER(SEARCH("CDS",E257)),"CDS",IF(ISNUMBER(SEARCH("TOGAF",E257)),"TOGAF",IF(ISNUMBER(SEARCH("DPI",E257)),"DPI",IF(ISNUMBER(SEARCH("DITS",E257)),"DITS",IF(ISNUMBER(SEARCH("AGILE",E257)),"AGILE",IF(ISNUMBER(SEARCH("Ciberseguridad",E257)),"Ciberseguridad","Otros")))))))))))))) | Q257: =IF(B257="","",IF(ISNUMBER(K257),IF(K257<=3,"1-3 meses",IF(K257<=6,"4-6 meses","+6 meses")),"Sin dato registrado")) | R257: =IF(OR(B257="",M257=""),"",RANK(M257,$M$3:$M$306)+COUNTIF($M$3:M257,M257)-1)
M258: =IF(B258="","",IF(ISNUMBER(I258),I258,IFERROR(VALUE(SUBSTITUTE(SUBSTITUTE(I258,"$",""),".","")),0))) | N258: =IF(B258="","",PROPER(TRIM(D258))) | O258: =IF(B258="","",IF(OR(ISNUMBER(SEARCH("AL DIA",L258)),ISNUMBER(SEARCH("AL DIA",F258))),"Al día",IF(OR(ISNUMBER(SEARCH("QUIETO",L258)),ISNUMBER(SEARCH("QUIETO",F258)),ISNUMBER(SEARCH("ESPERANDO",L258)),ISNUMBER(SEARCH("ESPERANDO",F258))),"Sin respuesta / Inactivo",IF(OR(ISNUMBER(SEARCH("PENDIENTE",L258)),ISNUMBER(SEARCH("PENDIENTE",F258)),ISNUMBER(SEARCH("COMPROMISO",F258)),ISNUMBER(SEARCH("COMPROMISO",L258)),ISNUMBER(SEARCH("PROCESO",F258)),ISNUMBER(SEARCH("LLAMAR",F258)),ISNUMBER(SEARCH("ABONO",J258)),EXACT(L258,"P"),EXACT(F258,"P")),"Pendiente / Compromiso","Sin gestionar")))) | P258: =IF(B258="","",IF(E258="","Sin definir",IF(ISNUMBER(SEARCH("ITIL",E258)),"ITIL",IF(ISNUMBER(SEARCH("ISO 27001",E258)),"ISO 27001",IF(ISNUMBER(SEARCH("ISO 42001",E258)),"ISO 42001",IF(ISNUMBER(SEARCH("ISO",E258)),"Otras ISO",IF(ISNUMBER(SEARCH("SCRUM",E258)),"SCRUM",IF(ISNUMBER(SEARCH("BRIDGE",E258)),"BRIDGE",IF(ISNUMBER(SEARCH("CDS",E258)),"CDS",IF(ISNUMBER(SEARCH("TOGAF",E258)),"TOGAF",IF(ISNUMBER(SEARCH("DPI",E258)),"DPI",IF(ISNUMBER(SEARCH("DITS",E258)),"DITS",IF(ISNUMBER(SEARCH("AGILE",E258)),"AGILE",IF(ISNUMBER(SEARCH("Ciberseguridad",E258)),"Ciberseguridad","Otros")))))))))))))) | Q258: =IF(B258="","",IF(ISNUMBER(K258),IF(K258<=3,"1-3 meses",IF(K258<=6,"4-6 meses","+6 meses")),"Sin dato registrado")) | R258: =IF(OR(B258="",M258=""),"",RANK(M258,$M$3:$M$306)+COUNTIF($M$3:M258,M258)-1)
M259: =IF(B259="","",IF(ISNUMBER(I259),I259,IFERROR(VALUE(SUBSTITUTE(SUBSTITUTE(I259,"$",""),".","")),0))) | N259: =IF(B259="","",PROPER(TRIM(D259))) | O259: =IF(B259="","",IF(OR(ISNUMBER(SEARCH("AL DIA",L259)),ISNUMBER(SEARCH("AL DIA",F259))),"Al día",IF(OR(ISNUMBER(SEARCH("QUIETO",L259)),ISNUMBER(SEARCH("QUIETO",F259)),ISNUMBER(SEARCH("ESPERANDO",L259)),ISNUMBER(SEARCH("ESPERANDO",F259))),"Sin respuesta / Inactivo",IF(OR(ISNUMBER(SEARCH("PENDIENTE",L259)),ISNUMBER(SEARCH("PENDIENTE",F259)),ISNUMBER(SEARCH("COMPROMISO",F259)),ISNUMBER(SEARCH("COMPROMISO",L259)),ISNUMBER(SEARCH("PROCESO",F259)),ISNUMBER(SEARCH("LLAMAR",F259)),ISNUMBER(SEARCH("ABONO",J259)),EXACT(L259,"P"),EXACT(F259,"P")),"Pendiente / Compromiso","Sin gestionar")))) | P259: =IF(B259="","",IF(E259="","Sin definir",IF(ISNUMBER(SEARCH("ITIL",E259)),"ITIL",IF(ISNUMBER(SEARCH("ISO 27001",E259)),"ISO 27001",IF(ISNUMBER(SEARCH("ISO 42001",E259)),"ISO 42001",IF(ISNUMBER(SEARCH("ISO",E259)),"Otras ISO",IF(ISNUMBER(SEARCH("SCRUM",E259)),"SCRUM",IF(ISNUMBER(SEARCH("BRIDGE",E259)),"BRIDGE",IF(ISNUMBER(SEARCH("CDS",E259)),"CDS",IF(ISNUMBER(SEARCH("TOGAF",E259)),"TOGAF",IF(ISNUMBER(SEARCH("DPI",E259)),"DPI",IF(ISNUMBER(SEARCH("DITS",E259)),"DITS",IF(ISNUMBER(SEARCH("AGILE",E259)),"AGILE",IF(ISNUMBER(SEARCH("Ciberseguridad",E259)),"Ciberseguridad","Otros")))))))))))))) | Q259: =IF(B259="","",IF(ISNUMBER(K259),IF(K259<=3,"1-3 meses",IF(K259<=6,"4-6 meses","+6 meses")),"Sin dato registrado")) | R259: =IF(OR(B259="",M259=""),"",RANK(M259,$M$3:$M$306)+COUNTIF($M$3:M259,M259)-1)
M260: =IF(B260="","",IF(ISNUMBER(I260),I260,IFERROR(VALUE(SUBSTITUTE(SUBSTITUTE(I260,"$",""),".","")),0))) | N260: =IF(B260="","",PROPER(TRIM(D260))) | O260: =IF(B260="","",IF(OR(ISNUMBER(SEARCH("AL DIA",L260)),ISNUMBER(SEARCH("AL DIA",F260))),"Al día",IF(OR(ISNUMBER(SEARCH("QUIETO",L260)),ISNUMBER(SEARCH("QUIETO",F260)),ISNUMBER(SEARCH("ESPERANDO",L260)),ISNUMBER(SEARCH("ESPERANDO",F260))),"Sin respuesta / Inactivo",IF(OR(ISNUMBER(SEARCH("PENDIENTE",L260)),ISNUMBER(SEARCH("PENDIENTE",F260)),ISNUMBER(SEARCH("COMPROMISO",F260)),ISNUMBER(SEARCH("COMPROMISO",L260)),ISNUMBER(SEARCH("PROCESO",F260)),ISNUMBER(SEARCH("LLAMAR",F260)),ISNUMBER(SEARCH("ABONO",J260)),EXACT(L260,"P"),EXACT(F260,"P")),"Pendiente / Compromiso","Sin gestionar")))) | P260: =IF(B260="","",IF(E260="","Sin definir",IF(ISNUMBER(SEARCH("ITIL",E260)),"ITIL",IF(ISNUMBER(SEARCH("ISO 27001",E260)),"ISO 27001",IF(ISNUMBER(SEARCH("ISO 42001",E260)),"ISO 42001",IF(ISNUMBER(SEARCH("ISO",E260)),"Otras ISO",IF(ISNUMBER(SEARCH("SCRUM",E260)),"SCRUM",IF(ISNUMBER(SEARCH("BRIDGE",E260)),"BRIDGE",IF(ISNUMBER(SEARCH("CDS",E260)),"CDS",IF(ISNUMBER(SEARCH("TOGAF",E260)),"TOGAF",IF(ISNUMBER(SEARCH("DPI",E260)),"DPI",IF(ISNUMBER(SEARCH("DITS",E260)),"DITS",IF(ISNUMBER(SEARCH("AGILE",E260)),"AGILE",IF(ISNUMBER(SEARCH("Ciberseguridad",E260)),"Ciberseguridad","Otros")))))))))))))) | Q260: =IF(B260="","",IF(ISNUMBER(K260),IF(K260<=3,"1-3 meses",IF(K260<=6,"4-6 meses","+6 meses")),"Sin dato registrado")) | R260: =IF(OR(B260="",M260=""),"",RANK(M260,$M$3:$M$306)+COUNTIF($M$3:M260,M260)-1)
... M306: =IF(B306="","",IF(ISNUMBER(I306),I306,IFERROR(VALUE(SUBSTITUTE(SUBSTITUTE(I306,"$",""),".","")),0))) | N306: =IF(B306="","",PROPER(TRIM(D306))) | O306: =IF(B306="","",IF(OR(ISNUMBER(SEARCH("AL DIA",L306)),ISNUMBER(SEARCH("AL DIA",F306))),"Al día",IF(OR(ISNUMBER(SEARCH("QUIETO",L306)),ISNUMBER(SEARCH("QUIETO",F306)),ISNUMBER(SEARCH("ESPERANDO",L306)),ISNUMBER(SEARCH("ESPERANDO",F306))),"Sin respuesta / Inactivo",IF(OR(ISNUMBER(SEARCH("PENDIENTE",L306)),ISNUMBER(SEARCH("PENDIENTE",F306)),ISNUMBER(SEARCH("COMPROMISO",F306)),ISNUMBER(SEARCH("COMPROMISO",L306)),ISNUMBER(SEARCH("PROCESO",F306)),ISNUMBER(SEARCH("LLAMAR",F306)),ISNUMBER(SEARCH("ABONO",J306)),EXACT(L306,"P"),EXACT(F306,"P")),"Pendiente / Compromiso","Sin gestionar")))) | P306: =IF(B306="","",IF(E306="","Sin definir",IF(ISNUMBER(SEARCH("ITIL",E306)),"ITIL",IF(ISNUMBER(SEARCH("ISO 27001",E306)),"ISO 27001",IF(ISNUMBER(SEARCH("ISO 42001",E306)),"ISO 42001",IF(ISNUMBER(SEARCH("ISO",E306)),"Otras ISO",IF(ISNUMBER(SEARCH("SCRUM",E306)),"SCRUM",IF(ISNUMBER(SEARCH("BRIDGE",E306)),"BRIDGE",IF(ISNUMBER(SEARCH("CDS",E306)),"CDS",IF(ISNUMBER(SEARCH("TOGAF",E306)),"TOGAF",IF(ISNUMBER(SEARCH("DPI",E306)),"DPI",IF(ISNUMBER(SEARCH("DITS",E306)),"DITS",IF(ISNUMBER(SEARCH("AGILE",E306)),"AGILE",IF(ISNUMBER(SEARCH("Ciberseguridad",E306)),"Ciberseguridad","Otros")))))))))))))) | Q306: =IF(B306="","",IF(ISNUMBER(K306),IF(K306<=3,"1-3 meses",IF(K306<=6,"4-6 meses","+6 meses")),"Sin dato registrado")) | R306: =IF(OR(B306="",M306=""),"",RANK(M306,$M$3:$M$306)+COUNTIF($M$3:M306,M306)-1)

Sheet DSB
A3: (vacío)
A19: (vacío)
A39: (vacío)
A54: Vendedor | B54: (vacío)
A55: Carolina
A56: Sebas
A57: Ximena
A58: (vacío)
A59: Total Resultado
A69: (vacío)
A85: (vacío)

Sheet TABLERO
B40: VENTAS TOTALES
B43: =DSB!$B$6 -> 0
